Workbook

Sheet nithya
B1: Content player functionality
B2: MP4 Content
B3: Verify that a course can be created with a single MP4 content.
B4: Verify that the course with attached MP4 content can be enrolled by the learner
B5: Verify that the MP4 content can be launched from the catalog details page.
B6: Verify that the MP4 content can be launched from My Learning.
B7: Verify that the course moves to the Completed tab upon content completion.
B9: Verify that a course can be created with a single MP4 content and a pre-assessment.
B10: Verify that the course with attached MP4 content and pre-assessment can be enrolled.
B11: Verify that the MP4 content cannot be launched from the catalog details page without taking the pre-assessment.
B12: Verify that the MP4 content cannot be launched from My Learning without taking the pre-assessment.
B13: Verify that the pre-assessment can be taken and answered.
... B893: Verify that able to set mandatory access to user in Access setting
A894: Class Cancellation and Completion | B894: Verify course is created as Multi instance when the delivery type is choosed as Classroom/Virtual class
A895: Class Cancellation and Completion | B895: Verify course is not created as Multi instance when the delivery type is choosed as E-learning
A896: Class Cancellation and Completion | B896: Verify that the Cancellation option is available only for ILT/VC classes and not for E-learning classes.
A897: Class Cancellation and Completion | B897: Verify that the Cancellation option is available for ILT/VC classes at the instance level only.
A898: Class Cancellation and Completion | B898: Verify that class cancellation notification is triggered to the user when admin cancel the class
A899: Class Cancellation and Completion | B899: Verify that the 'Number of Instance' dropdown is disabled.
A900: Class Cancellation and Completion | B900: Verify that the admin does not have the privilege to perform any action on the 'Number of Instance' dropdown.
A901: Class Cancellation and Completion | B901: Verify that the admin can cancel an instance/class when there are no enrollments.
A902: Class Cancellation and Completion | B902: Verify that the admin can cancel an instance/class with enrollments in various states (Past, Future, Ongoing).
A903: Class Cancellation and Completion | B903: Verify that the 'Cancel' button is enabled only in the Edit - Class/Instance page.
A904: Class Cancellation and Completion | B904: Verify that the 'Cancel' button is enabled only when the Instance is either shown or hidden in the catalog.
A905: Class Cancellation and Completion | B905: Verify that the 'Cancel' button should not be available when the Instance is in the save draft state.
... A1142: Tenant creation | B1142: Verify that able to create a new tenant for Lite, Mid and Complex editions
B1143: Verify that able to login into the new tenant
B1144: Verify that data from existing tenant should not be visible in the new tenant
B1145: Verify all the modules are visible in the newly created tenants
B1146: Verify that the default learner portal is created for the newly created tenants
B1147: Table need to be added - subscribe

Sheet Praba
A1: Certification | B1: Verify the admin able to create a Certification with single instance and check created certification gets listed in the Certification list page Verify the created Certification will be displayed in Learner UI catalog in "Most Recent" section Verify the certification with single instance get auto enrolled via single click launch in catalog page Verify the enrolled certification course will be displayed in my learning To_complete tab Verify the learner able to launch and complete the course under certification via TP details page Verify the learner able to launch and complete the course under certification via My Leanrning page
A2: Certification | B2: Verify the admin able to create a Certification with multi instance and check created certification gets listed in the Certification list page Verify the created Certification will be displayed in Learner UI catalog in "Most Recent" section Verify the certification with single instance will not get auto enrolled via single click launch in catalog page ,only tp will get enrolled and learner need to select the class and enroll the course under certification Verify the enrolled certification course will be displayed in my learning To_complete tab Verify the learner able to launch and complete the course under certification via TP details page Verify the learner able to launch and complete the course under certification via My Leanrning page
A3: Certification | B3: Verify the admin able to create a Certification with 3 single instance and check created certification gets listed in the Certification list page Verify the Certification with 3 single instance get auto enrolled when admin enroll the certification in manage enrollment Verify the certification with all 3 single instance get auto enrolled via single click launch in catalog page Verify the enrolled certification courses are displayed in my learning To_complete tab(3 enrolled courses) Verify the learner able to launch and complete the all classes under certification via TP details page
A4: Certification | B4: Verify the admin able to create a Certification with 3 multi instance and check created certification gets listed in the Certification list page Verify the certification with all 3 multi instance will not get auto enrolled when admin enroll the certification in manage enrollment Verify the all instance will enroll through "View status/enroll learner to TP courses" screen for the certification with multi instance Verify the certification with all 3 multi instance will not auto enrolled via single click launch in catalog page only tp will get enrolled and learner need to select the class and enroll the course under certification Verify the enrolled certification courses are displayed in my learning To_complete tab(3 enrolled courses)
A5: Certification | B5: Verify admin able to create certification then add 3 modules with 2 single instance for each module Verify the certification single instance get auto enrolled via single click launch in catalog page for the certification with multiple modules Verify admin able to create certification then add 3 modules with 2 multi instance for each module Verify the certification multi instance will not get auto enrolled via single click launch in catalog page for the certification with multiple modules,learner needs to select and enroll it Verify the learner able to enroll and completed the certification in Tree view with module and without module Verify the learner able to enroll and completed the certification in Module view with module and without module
A6: Certification | B6: Verfiy the admin able to create Compliance Certification
A7: Certification | B7: Verify the Mandatory,Optional and Recommended access is not getting displayed in the Access setting when it is a Compliance TP
A8: Certification | B8: Verify the learner are automatically enrolled in the Compliance Certification via auto_register cron when their access is set.
A9: Certification | B9: Verify the Compliance Label is displayed after enrolling a Compliance Certification in TP details page and my dashboard certification/learning path section
A10: Certification | B10: Verify the Compliance Certification cannot be canceled as a learner
A11: Certification | B11: Verify the the Compliance certification gets expired after the expiry days
A12: Certification | B12: Verify the duplicate enrollments will not occur when same user attached to multiple learner group attached to the Certification
... A493: Transfer Enrollment - TP | B493: To verify that the Training plan will not be displayed when admin search in the not versioned cert or lp in transfer enrollment page

Sheet master_pivot

Sheet ALL1
A1: =MasterSheet_final!A1 -> S No | B1: =MasterSheet_final!B1 -> Module | C1: =MasterSheet_final!C1 -> Scenario | D1: =MasterSheet_final!D1 -> Status | E1: =MasterSheet_final!E1 -> Executed on | F1: =#REF! -> #REF! | G1: =MasterSheet_final!F1 -> Resource | H1: Week No | I1: Week | J1: Week Count
A2: =MasterSheet_final!A2 -> 1 | B2: =MasterSheet_final!B2 -> Tenant creation | C2: =MasterSheet_final!C2 -> Verify that able to create a new tenant for Lite, Mid and Complex editions | D2: =MasterSheet_final!D2 -> Pass | E2: =MasterSheet_final!E2 -> 45801 | F2: =#REF! -> #REF! | G2: =MasterSheet_final!F2 -> Nithya | H2: =IF(ISBLANK(E2)," ",WEEKNUM(E2,2)) -> 21 | I2: =if(H2=5,"27th Jan-2nd Feb", if(H2=6,"3rd Feb-9th Feb", if(H2=7,"10th Feb-16th Feb",if(H2=8,"17th Feb-23rd Feb", if(H2=9,"24th Feb-2nd March",if(H2=10,"3rd March - 9th March"," ")))))) | J2: =if(H2=5,"W1", if(H2=6,"W2", if(H2=7,"W3",if(H2=8,"W4", if(H2=9,"W5",if(H2=10,"W6"," "))))))
A3: =MasterSheet_final!A3 -> 2 | B3: =MasterSheet_final!B3 -> Tenant creation | C3: =MasterSheet_final!C3 -> Verify that able to login into the new tenant | D3: =MasterSheet_final!D3 -> Pass | E3: =MasterSheet_final!E3 -> 45801 | F3: =#REF! -> #REF! | G3: =MasterSheet_final!F3 -> Nithya | H3: =IF(ISBLANK(E3)," ",WEEKNUM(E3,2)) -> 21 | I3: =if(H3=5,"27th Jan-2nd Feb", if(H3=6,"3rd Feb-9th Feb", if(H3=7,"10th Feb-16th Feb",if(H3=8,"17th Feb-23rd Feb", if(H3=9,"24th Feb-2nd March",if(H3=10,"3rd March - 9th March"," ")))))) | J3: =if(H3=5,"W1", if(H3=6,"W2", if(H3=7,"W3",if(H3=8,"W4", if(H3=9,"W5",if(H3=10,"W6"," "))))))
A4: =MasterSheet_final!A4 -> 3 | B4: =MasterSheet_final!B4 -> Tenant creation | C4: =MasterSheet_final!C4 -> Verify that data from existing tenant should not be visible in the new tenant | D4: =MasterSheet_final!D4 -> Pass | E4: =MasterSheet_final!E4 -> 45801 | F4: =#REF! -> #REF! | G4: =MasterSheet_final!F4 -> Nithya | H4: =IF(ISBLANK(E4)," ",WEEKNUM(E4,2)) -> 21 | I4: =if(H4=5,"27th Jan-2nd Feb", if(H4=6,"3rd Feb-9th Feb", if(H4=7,"10th Feb-16th Feb",if(H4=8,"17th Feb-23rd Feb", if(H4=9,"24th Feb-2nd March",if(H4=10,"3rd March - 9th March"," ")))))) | J4: =if(H4=5,"W1", if(H4=6,"W2", if(H4=7,"W3",if(H4=8,"W4", if(H4=9,"W5",if(H4=10,"W6"," "))))))
A5: =MasterSheet_final!A5 -> 4 | B5: =MasterSheet_final!B5 -> Tenant creation | C5: =MasterSheet_final!C5 -> Verify all the modules are visible in the newly created tenants | D5: =MasterSheet_final!D5 -> Pass | E5: =MasterSheet_final!E5 -> 45801 | F5: =#REF! -> #REF! | G5: =MasterSheet_final!F5 -> Nithya | H5: =IF(ISBLANK(E5)," ",WEEKNUM(E5,2)) -> 21 | I5: =if(H5=5,"27th Jan-2nd Feb", if(H5=6,"3rd Feb-9th Feb", if(H5=7,"10th Feb-16th Feb",if(H5=8,"17th Feb-23rd Feb", if(H5=9,"24th Feb-2nd March",if(H5=10,"3rd March - 9th March"," ")))))) | J5: =if(H5=5,"W1", if(H5=6,"W2", if(H5=7,"W3",if(H5=8,"W4", if(H5=9,"W5",if(H5=10,"W6"," "))))))
A6: =MasterSheet_final!A6 -> 5 | B6: =MasterSheet_final!B6 -> Tenant creation | C6: =MasterSheet_final!C6 -> Verify that the default learner portal is created for the newly created tenants | D6: =MasterSheet_final!D6 -> Pass | E6: =MasterSheet_final!E6 -> 45801 | F6: =#REF! -> #REF! | G6: =MasterSheet_final!F6 -> Nithya | H6: =IF(ISBLANK(E6)," ",WEEKNUM(E6,2)) -> 21 | I6: =if(H6=5,"27th Jan-2nd Feb", if(H6=6,"3rd Feb-9th Feb", if(H6=7,"10th Feb-16th Feb",if(H6=8,"17th Feb-23rd Feb", if(H6=9,"24th Feb-2nd March",if(H6=10,"3rd March - 9th March"," ")))))) | J6: =if(H6=5,"W1", if(H6=6,"W2", if(H6=7,"W3",if(H6=8,"W4", if(H6=9,"W5",if(H6=10,"W6"," "))))))
A7: =#REF! -> #REF! | B7: =#REF! -> #REF! | C7: =#REF! -> #REF! | D7: =#REF! -> #REF! | E7: =#REF! -> #REF! | F7: =#REF! -> #REF! | G7: =#REF! -> #REF! | H7: =IF(ISBLANK(E7)," ",WEEKNUM(E7,2)) -> #REF! | I7: =if(H7=5,"27th Jan-2nd Feb", if(H7=6,"3rd Feb-9th Feb", if(H7=7,"10th Feb-16th Feb",if(H7=8,"17th Feb-23rd Feb", if(H7=9,"24th Feb-2nd March",if(H7=10,"3rd March - 9th March"," ")))))) -> #REF! | J7: =if(H7=5,"W1", if(H7=6,"W2", if(H7=7,"W3",if(H7=8,"W4", if(H7=9,"W5",if(H7=10,"W6"," ")))))) -> #REF!
A8: =MasterSheet_final!A7 -> 6 | B8: =MasterSheet_final!B7 -> Portal creation | C8: =MasterSheet_final!C7 -> Verify that able to create a new portal to the tenant | D8: =MasterSheet_final!D7 -> Pass | E8: =MasterSheet_final!E7 -> 45801 | F8: =#REF! -> #REF! | G8: =MasterSheet_final!F7 -> Nithya | H8: =IF(ISBLANK(E8)," ",WEEKNUM(E8,2)) -> 21 | I8: =if(H8=5,"27th Jan-2nd Feb", if(H8=6,"3rd Feb-9th Feb", if(H8=7,"10th Feb-16th Feb",if(H8=8,"17th Feb-23rd Feb", if(H8=9,"24th Feb-2nd March",if(H8=10,"3rd March - 9th March"," ")))))) | J8: =if(H8=5,"W1", if(H8=6,"W2", if(H8=7,"W3",if(H8=8,"W4", if(H8=9,"W5",if(H8=10,"W6"," "))))))
A9: =MasterSheet_final!A8 -> 7 | B9: =MasterSheet_final!B8 -> Portal creation | C9: =MasterSheet_final!C8 -> Verifty that able to login into the newly created portal | D9: =MasterSheet_final!D8 -> Pass | E9: =MasterSheet_final!E8 -> 45801 | F9: =#REF! -> #REF! | G9: =MasterSheet_final!F8 -> Nithya | H9: =IF(ISBLANK(E9)," ",WEEKNUM(E9,2)) -> 21 | I9: =if(H9=5,"27th Jan-2nd Feb", if(H9=6,"3rd Feb-9th Feb", if(H9=7,"10th Feb-16th Feb",if(H9=8,"17th Feb-23rd Feb", if(H9=9,"24th Feb-2nd March",if(H9=10,"3rd March - 9th March"," ")))))) | J9: =if(H9=5,"W1", if(H9=6,"W2", if(H9=7,"W3",if(H9=8,"W4", if(H9=9,"W5",if(H9=10,"W6"," "))))))
A10: =MasterSheet_final!A9 -> 8 | B10: =MasterSheet_final!B9 -> Portal creation | C10: =MasterSheet_final!C9 -> Verify that able to create template to the newly created portal | D10: =MasterSheet_final!D9 -> Pass | E10: =MasterSheet_final!E9 -> 45801 | F10: =#REF! -> #REF! | G10: =MasterSheet_final!F9 -> Nithya | H10: =IF(ISBLANK(E10)," ",WEEKNUM(E10,2)) -> 21 | I10: =if(H10=5,"27th Jan-2nd Feb", if(H10=6,"3rd Feb-9th Feb", if(H10=7,"10th Feb-16th Feb",if(H10=8,"17th Feb-23rd Feb", if(H10=9,"24th Feb-2nd March",if(H10=10,"3rd March - 9th March"," ")))))) | J10: =if(H10=5,"W1", if(H10=6,"W2", if(H10=7,"W3",if(H10=8,"W4", if(H10=9,"W5",if(H10=10,"W6"," "))))))
A11: =MasterSheet_final!A10 -> 9 | B11: =MasterSheet_final!B10 -> Portal creation | C11: =MasterSheet_final!C10 -> Verify that a default portal is created automatically while creating a new portal | D11: =MasterSheet_final!D10 -> Pass | E11: =MasterSheet_final!E10 -> 45801 | F11: =#REF! -> #REF! | G11: =MasterSheet_final!F10 -> Nithya | H11: =IF(ISBLANK(E11)," ",WEEKNUM(E11,2)) -> 21 | I11: =if(H11=5,"27th Jan-2nd Feb", if(H11=6,"3rd Feb-9th Feb", if(H11=7,"10th Feb-16th Feb",if(H11=8,"17th Feb-23rd Feb", if(H11=9,"24th Feb-2nd March",if(H11=10,"3rd March - 9th March"," ")))))) | J11: =if(H11=5,"W1", if(H11=6,"W2", if(H11=7,"W3",if(H11=8,"W4", if(H11=9,"W5",if(H11=10,"W6"," "))))))
A12: =MasterSheet_final!A11 -> 10 | B12: =MasterSheet_final!B11 -> Portal creation | C12: =MasterSheet_final!C11 -> Verify that able to create multiple template to the single portal | D12: =MasterSheet_final!D11 -> Pass | E12: =MasterSheet_final!E11 -> 45801 | F12: =#REF! -> #REF! | G12: =MasterSheet_final!F11 -> Nithya | H12: =IF(ISBLANK(E12)," ",WEEKNUM(E12,2)) -> 21 | I12: =if(H12=5,"27th Jan-2nd Feb", if(H12=6,"3rd Feb-9th Feb", if(H12=7,"10th Feb-16th Feb",if(H12=8,"17th Feb-23rd Feb", if(H12=9,"24th Feb-2nd March",if(H12=10,"3rd March - 9th March"," ")))))) | J12: =if(H12=5,"W1", if(H12=6,"W2", if(H12=7,"W3",if(H12=8,"W4", if(H12=9,"W5",if(H12=10,"W6"," "))))))
A13: =MasterSheet_final!A12 -> 11 | B13: =MasterSheet_final!B12 -> Portal creation | C13: =MasterSheet_final!C12 -> Verify that able to set only one default template to the the portal | D13: =MasterSheet_final!D12 -> Pass | E13: =MasterSheet_final!E12 -> 45801 | F13: =#REF! -> #REF! | G13: =MasterSheet_final!F12 -> Nithya | H13: =IF(ISBLANK(E13)," ",WEEKNUM(E13,2)) -> 21 | I13: =if(H13=5,"27th Jan-2nd Feb", if(H13=6,"3rd Feb-9th Feb", if(H13=7,"10th Feb-16th Feb",if(H13=8,"17th Feb-23rd Feb", if(H13=9,"24th Feb-2nd March",if(H13=10,"3rd March - 9th March"," ")))))) | J13: =if(H13=5,"W1", if(H13=6,"W2", if(H13=7,"W3",if(H13=8,"W4", if(H13=9,"W5",if(H13=10,"W6"," "))))))
A14: =MasterSheet_final!A13 -> 12 | B14: =MasterSheet_final!B13 -> Portal creation | C14: =MasterSheet_final!C13 -> Verify that multiple portals can be created in the tenant with same portal url but domain name should be different | D14: =MasterSheet_final!D13 -> Pass | E14: =MasterSheet_final!E13 -> 45801 | F14: =#REF! -> #REF! | G14: =MasterSheet_final!F13 -> Nithya | H14: =IF(ISBLANK(E14)," ",WEEKNUM(E14,2)) -> 21 | I14: =if(H14=5,"27th Jan-2nd Feb", if(H14=6,"3rd Feb-9th Feb", if(H14=7,"10th Feb-16th Feb",if(H14=8,"17th Feb-23rd Feb", if(H14=9,"24th Feb-2nd March",if(H14=10,"3rd March - 9th March"," ")))))) | J14: =if(H14=5,"W1", if(H14=6,"W2", if(H14=7,"W3",if(H14=8,"W4", if(H14=9,"W5",if(H14=10,"W6"," "))))))
A15: =MasterSheet_final!A14 -> 13 | B15: =MasterSheet_final!B14 -> Portal creation | C15: =MasterSheet_final!C14 -> Verify that should not able to create portal with same domain name | D15: =MasterSheet_final!D14 -> Pass | E15: =MasterSheet_final!E14 -> 45801 | F15: =#REF! -> #REF! | G15: =MasterSheet_final!F14 -> Nithya | H15: =IF(ISBLANK(E15)," ",WEEKNUM(E15,2)) -> 21 | I15: =if(H15=5,"27th Jan-2nd Feb", if(H15=6,"3rd Feb-9th Feb", if(H15=7,"10th Feb-16th Feb",if(H15=8,"17th Feb-23rd Feb", if(H15=9,"24th Feb-2nd March",if(H15=10,"3rd March - 9th March"," ")))))) | J15: =if(H15=5,"W1", if(H15=6,"W2", if(H15=7,"W3",if(H15=8,"W4", if(H15=9,"W5",if(H15=10,"W6"," "))))))
A16: =MasterSheet_final!A15 -> 14 | B16: =MasterSheet_final!B15 -> Portal creation | C16: =MasterSheet_final!C15 -> Verify that able to clone the portal | D16: =MasterSheet_final!D15 -> Pass | E16: =MasterSheet_final!E15 -> 45801 | F16: =#REF! -> #REF! | G16: =MasterSheet_final!F15 -> Nithya | H16: =IF(ISBLANK(E16)," ",WEEKNUM(E16,2)) -> 21 | I16: =if(H16=5,"27th Jan-2nd Feb", if(H16=6,"3rd Feb-9th Feb", if(H16=7,"10th Feb-16th Feb",if(H16=8,"17th Feb-23rd Feb", if(H16=9,"24th Feb-2nd March",if(H16=10,"3rd March - 9th March"," ")))))) | J16: =if(H16=5,"W1", if(H16=6,"W2", if(H16=7,"W3",if(H16=8,"W4", if(H16=9,"W5",if(H16=10,"W6"," "))))))
A17: =MasterSheet_final!A16 -> 15 | B17: =MasterSheet_final!B16 -> Portal creation | C17: =MasterSheet_final!C16 -> Verify that able to copy the portal url using the copy link icon | D17: =MasterSheet_final!D16 -> Pass | E17: =MasterSheet_final!E16 -> 45801 | F17: =#REF! -> #REF! | G17: =MasterSheet_final!F16 -> Nithya | H17: =IF(ISBLANK(E17)," ",WEEKNUM(E17,2)) -> 21 | I17: =if(H17=5,"27th Jan-2nd Feb", if(H17=6,"3rd Feb-9th Feb", if(H17=7,"10th Feb-16th Feb",if(H17=8,"17th Feb-23rd Feb", if(H17=9,"24th Feb-2nd March",if(H17=10,"3rd March - 9th March"," ")))))) | J17: =if(H17=5,"W1", if(H17=6,"W2", if(H17=7,"W3",if(H17=8,"W4", if(H17=9,"W5",if(H17=10,"W6"," "))))))
A18: =MasterSheet_final!A17 -> 16 | B18: =MasterSheet_final!B17 -> Portal creation | C18: =MasterSheet_final!C17 -> Verify that able to edit the portal and change the domain name and portal url | D18: =MasterSheet_final!D17 -> Pass | E18: =MasterSheet_final!E17 -> 45801 | F18: =#REF! -> #REF! | G18: =MasterSheet_final!F17 -> Nithya | H18: =IF(ISBLANK(E18)," ",WEEKNUM(E18,2)) -> 21 | I18: =if(H18=5,"27th Jan-2nd Feb", if(H18=6,"3rd Feb-9th Feb", if(H18=7,"10th Feb-16th Feb",if(H18=8,"17th Feb-23rd Feb", if(H18=9,"24th Feb-2nd March",if(H18=10,"3rd March - 9th March"," ")))))) | J18: =if(H18=5,"W1", if(H18=6,"W2", if(H18=7,"W3",if(H18=8,"W4", if(H18=9,"W5",if(H18=10,"W6"," "))))))
A19: =MasterSheet_final!A18 -> 17 | B19: =MasterSheet_final!B18 -> Portal creation | C19: =MasterSheet_final!C18 -> Verify that able to login into the portal which is edited (could not able to login as the old one) | D19: =MasterSheet_final!D18 -> Pass | E19: =MasterSheet_final!E18 -> 45801 | F19: =#REF! -> #REF! | G19: =MasterSheet_final!F18 -> Nithya | H19: =IF(ISBLANK(E19)," ",WEEKNUM(E19,2)) -> 21 | I19: =if(H19=5,"27th Jan-2nd Feb", if(H19=6,"3rd Feb-9th Feb", if(H19=7,"10th Feb-16th Feb",if(H19=8,"17th Feb-23rd Feb", if(H19=9,"24th Feb-2nd March",if(H19=10,"3rd March - 9th March"," ")))))) | J19: =if(H19=5,"W1", if(H19=6,"W2", if(H19=7,"W3",if(H19=8,"W4", if(H19=9,"W5",if(H19=10,"W6"," "))))))
... A143: =MasterSheet_final!A142 -> 141 | B143: =MasterSheet_final!B142 -> Admin Group | C143: =MasterSheet_final!C142 -> Verify whether the Code is autogenerated correctly when we enable the Code Convention | D143: =MasterSheet_final!D142 -> Pass | E143: =MasterSheet_final!E142 -> 45804 | F143: =#REF! -> #REF! | G143: =MasterSheet_final!F142 -> Selva | H143: =IF(ISBLANK(E143)," ",WEEKNUM(E143,2)) -> 22 | I143: =if(H143=5,"27th Jan-2nd Feb", if(H143=6,"3rd Feb-9th Feb", if(H143=7,"10th Feb-16th Feb",if(H143=8,"17th Feb-23rd Feb", if(H143=9,"24th Feb-2nd March",if(H143=10,"3rd March - 9th March"," ")))))) | J143: =if(H143=5,"W1", if(H143=6,"W2", if(H143=7,"W3",if(H143=8,"W4", if(H143=9,"W5",if(H143=10,"W6"," "))))))
A144: =#REF! -> #REF! | B144: =#REF! -> #REF! | C144: =#REF! -> #REF! | D144: =#REF! -> #REF! | E144: =#REF! -> #REF! | F144: =#REF! -> #REF! | G144: =#REF! -> #REF! | H144: =IF(ISBLANK(E144)," ",WEEKNUM(E144,2)) -> #REF! | I144: =if(H144=5,"27th Jan-2nd Feb", if(H144=6,"3rd Feb-9th Feb", if(H144=7,"10th Feb-16th Feb",if(H144=8,"17th Feb-23rd Feb", if(H144=9,"24th Feb-2nd March",if(H144=10,"3rd March - 9th March"," ")))))) -> #REF! | J144: =if(H144=5,"W1", if(H144=6,"W2", if(H144=7,"W3",if(H144=8,"W4", if(H144=9,"W5",if(H144=10,"W6"," ")))))) -> #REF!
A145: =#REF! -> #REF! | B145: =#REF! -> #REF! | C145: =#REF! -> #REF! | D145: =#REF! -> #REF! | E145: =#REF! -> #REF! | F145: =#REF! -> #REF! | G145: =#REF! -> #REF! | H145: =IF(ISBLANK(E145)," ",WEEKNUM(E145,2)) -> #REF! | I145: =if(H145=5,"27th Jan-2nd Feb", if(H145=6,"3rd Feb-9th Feb", if(H145=7,"10th Feb-16th Feb",if(H145=8,"17th Feb-23rd Feb", if(H145=9,"24th Feb-2nd March",if(H145=10,"3rd March - 9th March"," ")))))) -> #REF! | J145: =if(H145=5,"W1", if(H145=6,"W2", if(H145=7,"W3",if(H145=8,"W4", if(H145=9,"W5",if(H145=10,"W6"," ")))))) -> #REF!
A146: =#REF! -> #REF! | B146: =#REF! -> #REF! | C146: =#REF! -> #REF! | D146: =#REF! -> #REF! | E146: =#REF! -> #REF! | F146: =#REF! -> #REF! | G146: =#REF! -> #REF! | H146: =IF(ISBLANK(E146)," ",WEEKNUM(E146,2)) -> #REF! | I146: =if(H146=5,"27th Jan-2nd Feb", if(H146=6,"3rd Feb-9th Feb", if(H146=7,"10th Feb-16th Feb",if(H146=8,"17th Feb-23rd Feb", if(H146=9,"24th Feb-2nd March",if(H146=10,"3rd March - 9th March"," ")))))) -> #REF! | J146: =if(H146=5,"W1", if(H146=6,"W2", if(H146=7,"W3",if(H146=8,"W4", if(H146=9,"W5",if(H146=10,"W6"," ")))))) -> #REF!
A147: =#REF! -> #REF! | B147: =#REF! -> #REF! | C147: =#REF! -> #REF! | D147: =#REF! -> #REF! | E147: =#REF! -> #REF! | F147: =#REF! -> #REF! | G147: =#REF! -> #REF! | H147: =IF(ISBLANK(E147)," ",WEEKNUM(E147,2)) -> #REF! | I147: =if(H147=5,"27th Jan-2nd Feb", if(H147=6,"3rd Feb-9th Feb", if(H147=7,"10th Feb-16th Feb",if(H147=8,"17th Feb-23rd Feb", if(H147=9,"24th Feb-2nd March",if(H147=10,"3rd March - 9th March"," ")))))) -> #REF! | J147: =if(H147=5,"W1", if(H147=6,"W2", if(H147=7,"W3",if(H147=8,"W4", if(H147=9,"W5",if(H147=10,"W6"," ")))))) -> #REF!
A148: =MasterSheet_final!A143 -> 142 | B148: =MasterSheet_final!B143 -> Admin Group | C148: =MasterSheet_final!C143 -> Verify whether we cannot delete the Default Admin Groups | D148: =MasterSheet_final!D143 -> Pass | E148: =MasterSheet_final!E143 -> 45800 | F148: =#REF! -> #REF! | G148: =MasterSheet_final!F143 -> Selva | H148: =IF(ISBLANK(E148)," ",WEEKNUM(E148,2)) -> 21 | I148: =if(H148=5,"27th Jan-2nd Feb", if(H148=6,"3rd Feb-9th Feb", if(H148=7,"10th Feb-16th Feb",if(H148=8,"17th Feb-23rd Feb", if(H148=9,"24th Feb-2nd March",if(H148=10,"3rd March - 9th March"," ")))))) | J148: =if(H148=5,"W1", if(H148=6,"W2", if(H148=7,"W3",if(H148=8,"W4", if(H148=9,"W5",if(H148=10,"W6"," "))))))
A149: =MasterSheet_final!A144 -> 143 | B149: =MasterSheet_final!B144 -> Admin Group | C149: =MasterSheet_final!C144 -> Verify whether we can Create,Edit,Activate and Suspend a Admin Group as a Custom Admin user | D149: =MasterSheet_final!D144 -> Pass | E149: =MasterSheet_final!E144 -> 45800 | F149: =#REF! -> #REF! | G149: =MasterSheet_final!F144 -> Selva | H149: =IF(ISBLANK(E149)," ",WEEKNUM(E149,2)) -> 21 | I149: =if(H149=5,"27th Jan-2nd Feb", if(H149=6,"3rd Feb-9th Feb", if(H149=7,"10th Feb-16th Feb",if(H149=8,"17th Feb-23rd Feb", if(H149=9,"24th Feb-2nd March",if(H149=10,"3rd March - 9th March"," ")))))) | J149: =if(H149=5,"W1", if(H149=6,"W2", if(H149=7,"W3",if(H149=8,"W4", if(H149=9,"W5",if(H149=10,"W6"," "))))))
A150: =MasterSheet_final!A145 -> 144 | B150: =MasterSheet_final!B145 -> Admin Group | C150: =MasterSheet_final!C145 -> Verify whether the Admin group Access is set to the created Group based on the Logged in user | D150: =MasterSheet_final!D145 -> Pass | E150: =MasterSheet_final!E145 -> 45808 | F150: =#REF! -> #REF! | G150: =MasterSheet_final!F145 -> Selva | H150: =IF(ISBLANK(E150)," ",WEEKNUM(E150,2)) -> 22 | I150: =if(H150=5,"27th Jan-2nd Feb", if(H150=6,"3rd Feb-9th Feb", if(H150=7,"10th Feb-16th Feb",if(H150=8,"17th Feb-23rd Feb", if(H150=9,"24th Feb-2nd March",if(H150=10,"3rd March - 9th March"," ")))))) | J150: =if(H150=5,"W1", if(H150=6,"W2", if(H150=7,"W3",if(H150=8,"W4", if(H150=9,"W5",if(H150=10,"W6"," "))))))
A151: =MasterSheet_final!A146 -> 145 | B151: =MasterSheet_final!B146 -> Admin Group | C151: =MasterSheet_final!C146 -> Verify whether the Admin Group goes to unpublished state after the Valid till Date | D151: =MasterSheet_final!D146 -> Pass | E151: =MasterSheet_final!E146 -> 45800 | F151: =#REF! -> #REF! | G151: =MasterSheet_final!F146 -> Selva | H151: =IF(ISBLANK(E151)," ",WEEKNUM(E151,2)) -> 21 | I151: =if(H151=5,"27th Jan-2nd Feb", if(H151=6,"3rd Feb-9th Feb", if(H151=7,"10th Feb-16th Feb",if(H151=8,"17th Feb-23rd Feb", if(H151=9,"24th Feb-2nd March",if(H151=10,"3rd March - 9th March"," ")))))) | J151: =if(H151=5,"W1", if(H151=6,"W2", if(H151=7,"W3",if(H151=8,"W4", if(H151=9,"W5",if(H151=10,"W6"," "))))))
A152: =MasterSheet_final!A147 -> 146 | B152: =MasterSheet_final!B147 -> Learner Group | C152: =MasterSheet_final!C147 -> Verify that the admin able to access the Learner Group Create/Edit option from Quick Access | D152: =MasterSheet_final!D147 -> Pass | E152: =MasterSheet_final!E147 -> 45807 | F152: =#REF! -> #REF! | G152: =MasterSheet_final!F147 -> Selva | H152: =IF(ISBLANK(E152)," ",WEEKNUM(E152,2)) -> 22 | I152: =if(H152=5,"27th Jan-2nd Feb", if(H152=6,"3rd Feb-9th Feb", if(H152=7,"10th Feb-16th Feb",if(H152=8,"17th Feb-23rd Feb", if(H152=9,"24th Feb-2nd March",if(H152=10,"3rd March - 9th March"," ")))))) | J152: =if(H152=5,"W1", if(H152=6,"W2", if(H152=7,"W3",if(H152=8,"W4", if(H152=9,"W5",if(H152=10,"W6"," "))))))
A153: =MasterSheet_final!A148 -> 147 | B153: =MasterSheet_final!B148 -> Learner Group | C153: =MasterSheet_final!C148 -> Verify that the admin able to access the Learner Group under People module from toggle menu | D153: =MasterSheet_final!D148 -> Pass | E153: =MasterSheet_final!E148 -> 45807 | F153: =#REF! -> #REF! | G153: =MasterSheet_final!F148 -> Selva | H153: =IF(ISBLANK(E153)," ",WEEKNUM(E153,2)) -> 22 | I153: =if(H153=5,"27th Jan-2nd Feb", if(H153=6,"3rd Feb-9th Feb", if(H153=7,"10th Feb-16th Feb",if(H153=8,"17th Feb-23rd Feb", if(H153=9,"24th Feb-2nd March",if(H153=10,"3rd March - 9th March"," ")))))) | J153: =if(H153=5,"W1", if(H153=6,"W2", if(H153=7,"W3",if(H153=8,"W4", if(H153=9,"W5",if(H153=10,"W6"," "))))))
A154: =MasterSheet_final!A149 -> 148 | B154: =MasterSheet_final!B149 -> Learner Group | C154: =MasterSheet_final!C149 -> Verify that the below listed details will be displayed when admin click create learner group -Title -Code -Valid till -Attributes -Include learners and exclude learners | D154: =MasterSheet_final!D149 -> Pass | E154: =MasterSheet_final!E149 -> 45807 | F154: =#REF! -> #REF! | G154: =MasterSheet_final!F149 -> Selva | H154: =IF(ISBLANK(E154)," ",WEEKNUM(E154,2)) -> 22 | I154: =if(H154=5,"27th Jan-2nd Feb", if(H154=6,"3rd Feb-9th Feb", if(H154=7,"10th Feb-16th Feb",if(H154=8,"17th Feb-23rd Feb", if(H154=9,"24th Feb-2nd March",if(H154=10,"3rd March - 9th March"," ")))))) | J154: =if(H154=5,"W1", if(H154=6,"W2", if(H154=7,"W3",if(H154=8,"W4", if(H154=9,"W5",if(H154=10,"W6"," "))))))
A155: =MasterSheet_final!A150 -> 149 | B155: =MasterSheet_final!B150 -> Learner Group | C155: =MasterSheet_final!C150 -> Verify that admin able to create Learner Group -Create a New Role "Common Role" and Create a new admin group "Common Admin group" with role as "Common Role" -Manually add "Prabaadmin" user then login into admin site -Create a learner group | D155: =MasterSheet_final!D150 -> Pass | E155: =MasterSheet_final!E150 -> 45807 | F155: =#REF! -> #REF! | G155: =MasterSheet_final!F150 -> Selva | H155: =IF(ISBLANK(E155)," ",WEEKNUM(E155,2)) -> 22 | I155: =if(H155=5,"27th Jan-2nd Feb", if(H155=6,"3rd Feb-9th Feb", if(H155=7,"10th Feb-16th Feb",if(H155=8,"17th Feb-23rd Feb", if(H155=9,"24th Feb-2nd March",if(H155=10,"3rd March - 9th March"," ")))))) | J155: =if(H155=5,"W1", if(H155=6,"W2", if(H155=7,"W3",if(H155=8,"W4", if(H155=9,"W5",if(H155=10,"W6"," "))))))
A156: =MasterSheet_final!A151 -> 150 | B156: =MasterSheet_final!B151 -> Learner Group | C156: =MasterSheet_final!C151 -> Verify whether we can able to Create/Update/Activate/Suspend a Learner Group as a Custom Admin user | D156: =MasterSheet_final!D151 -> Pass | E156: =MasterSheet_final!E151 -> 45807 | F156: =#REF! -> #REF! | G156: =MasterSheet_final!F151 -> Selva | H156: =IF(ISBLANK(E156)," ",WEEKNUM(E156,2)) -> 22 | I156: =if(H156=5,"27th Jan-2nd Feb", if(H156=6,"3rd Feb-9th Feb", if(H156=7,"10th Feb-16th Feb",if(H156=8,"17th Feb-23rd Feb", if(H156=9,"24th Feb-2nd March",if(H156=10,"3rd March - 9th March"," ")))))) | J156: =if(H156=5,"W1", if(H156=6,"W2", if(H156=7,"W3",if(H156=8,"W4", if(H156=9,"W5",if(H156=10,"W6"," "))))))
A157: =MasterSheet_final!A152 -> 151 | B157: =MasterSheet_final!B152 -> Learner Group | C157: =MasterSheet_final!C152 -> Verify that the admin able to remove the added learner and check it displayed in exlude learners section | D157: =MasterSheet_final!D152 -> Pass | E157: =MasterSheet_final!E152 -> 45808 | F157: =#REF! -> #REF! | G157: =MasterSheet_final!F152 -> Selva | H157: =IF(ISBLANK(E157)," ",WEEKNUM(E157,2)) -> 22 | I157: =if(H157=5,"27th Jan-2nd Feb", if(H157=6,"3rd Feb-9th Feb", if(H157=7,"10th Feb-16th Feb",if(H157=8,"17th Feb-23rd Feb", if(H157=9,"24th Feb-2nd March",if(H157=10,"3rd March - 9th March"," ")))))) | J157: =if(H157=5,"W1", if(H157=6,"W2", if(H157=7,"W3",if(H157=8,"W4", if(H157=9,"W5",if(H157=10,"W6"," "))))))
A158: =MasterSheet_final!A153 -> 152 | B158: =MasterSheet_final!B153 -> Learner Group | C158: =MasterSheet_final!C153 -> Verify that the Select Domain will be selected all domains when create Learner group | D158: =MasterSheet_final!D153 -> Pass | E158: =MasterSheet_final!E153 -> 45807 | F158: =#REF! -> #REF! | G158: =MasterSheet_final!F153 -> Selva | H158: =IF(ISBLANK(E158)," ",WEEKNUM(E158,2)) -> 22 | I158: =if(H158=5,"27th Jan-2nd Feb", if(H158=6,"3rd Feb-9th Feb", if(H158=7,"10th Feb-16th Feb",if(H158=8,"17th Feb-23rd Feb", if(H158=9,"24th Feb-2nd March",if(H158=10,"3rd March - 9th March"," ")))))) | J158: =if(H158=5,"W1", if(H158=6,"W2", if(H158=7,"W3",if(H158=8,"W4", if(H158=9,"W5",if(H158=10,"W6"," "))))))
A159: =MasterSheet_final!A154 -> 153 | B159: =MasterSheet_final!B154 -> Learner Group | C159: =MasterSheet_final!C154 -> Verify that the learner will be added in backend when admin select Department attribute | D159: =MasterSheet_final!D154 -> Pass | E159: =MasterSheet_final!E154 -> 45808 | F159: =#REF! -> #REF! | G159: =MasterSheet_final!F154 -> Selva | H159: =IF(ISBLANK(E159)," ",WEEKNUM(E159,2)) -> 22 | I159: =if(H159=5,"27th Jan-2nd Feb", if(H159=6,"3rd Feb-9th Feb", if(H159=7,"10th Feb-16th Feb",if(H159=8,"17th Feb-23rd Feb", if(H159=9,"24th Feb-2nd March",if(H159=10,"3rd March - 9th March"," ")))))) | J159: =if(H159=5,"W1", if(H159=6,"W2", if(H159=7,"W3",if(H159=8,"W4", if(H159=9,"W5",if(H159=10,"W6"," "))))))
... A173: =MasterSheet_final!A168 -> 167 | B173: =MasterSheet_final!B168 -> Learner Group | C173: =MasterSheet_final!C168 -> Verify that the learner will get add in the learner group if two departments are added in the same attribute(Ex:Depart1,depart2) | D173: =MasterSheet_final!D168 -> Pass | E173: =MasterSheet_final!E168 -> 45810 | F173: =#REF! -> #REF! | G173: =MasterSheet_final!F168 -> Selva | H173: =IF(ISBLANK(E173)," ",WEEKNUM(E173,2)) -> 23 | I173: =if(H173=5,"27th Jan-2nd Feb", if(H173=6,"3rd Feb-9th Feb", if(H173=7,"10th Feb-16th Feb",if(H173=8,"17th Feb-23rd Feb", if(H173=9,"24th Feb-2nd March",if(H173=10,"3rd March - 9th March"," ")))))) | J173: =if(H173=5,"W1", if(H173=6,"W2", if(H173=7,"W3",if(H173=8,"W4", if(H173=9,"W5",if(H173=10,"W6"," "))))))
A174: =#REF! -> #REF! | B174: =#REF! -> #REF! | C174: =#REF! -> #REF! | D174: =#REF! -> #REF! | E174: =#REF! -> #REF! | F174: =#REF! -> #REF! | G174: =#REF! -> #REF! | H174: =IF(ISBLANK(E174)," ",WEEKNUM(E174,2)) -> #REF! | I174: =if(H174=5,"27th Jan-2nd Feb", if(H174=6,"3rd Feb-9th Feb", if(H174=7,"10th Feb-16th Feb",if(H174=8,"17th Feb-23rd Feb", if(H174=9,"24th Feb-2nd March",if(H174=10,"3rd March - 9th March"," ")))))) -> #REF! | J174: =if(H174=5,"W1", if(H174=6,"W2", if(H174=7,"W3",if(H174=8,"W4", if(H174=9,"W5",if(H174=10,"W6"," ")))))) -> #REF!
A175: =MasterSheet_final!A169 -> 168 | B175: =MasterSheet_final!B169 -> Learner Group | C175: =MasterSheet_final!C169 -> Verify that the Selected Domain and selected attribute,the learner will get added to the learner group Ex:User-depart1 and domain1 | D175: =MasterSheet_final!D169 -> Pass | E175: =MasterSheet_final!E169 -> 45810 | F175: =#REF! -> #REF! | G175: =MasterSheet_final!F169 -> Selva | H175: =IF(ISBLANK(E175)," ",WEEKNUM(E175,2)) -> 23 | I175: =if(H175=5,"27th Jan-2nd Feb", if(H175=6,"3rd Feb-9th Feb", if(H175=7,"10th Feb-16th Feb",if(H175=8,"17th Feb-23rd Feb", if(H175=9,"24th Feb-2nd March",if(H175=10,"3rd March - 9th March"," ")))))) | J175: =if(H175=5,"W1", if(H175=6,"W2", if(H175=7,"W3",if(H175=8,"W4", if(H175=9,"W5",if(H175=10,"W6"," "))))))
A176: =MasterSheet_final!A170 -> 169 | B176: =MasterSheet_final!B170 -> Learner Group | C176: =MasterSheet_final!C170 -> Verify that the all the learners belonging to the selected Domain will get added to the group if admin selected domain without attribute Ex: If only Domain1 is selected, the user belonging to Domain1 and users part of Domain1 will be added to the group i.e If User A belongs to Domain 1 and User B is part of Domain1 & Domain2. When a learner group is created with Domain1, both User A & B will get added to the group. | D176: =MasterSheet_final!D170 -> Pass | E176: =MasterSheet_final!E170 -> 45811 | F176: =#REF! -> #REF! | G176: =MasterSheet_final!F170 -> Selva | H176: =IF(ISBLANK(E176)," ",WEEKNUM(E176,2)) -> 23 | I176: =if(H176=5,"27th Jan-2nd Feb", if(H176=6,"3rd Feb-9th Feb", if(H176=7,"10th Feb-16th Feb",if(H176=8,"17th Feb-23rd Feb", if(H176=9,"24th Feb-2nd March",if(H176=10,"3rd March - 9th March"," ")))))) | J176: =if(H176=5,"W1", if(H176=6,"W2", if(H176=7,"W3",if(H176=8,"W4", if(H176=9,"W5",if(H176=10,"W6"," "))))))
A177: =MasterSheet_final!A171 -> 170 | B177: =MasterSheet_final!B171 -> Learner Group | C177: =MasterSheet_final!C171 -> Verify that the value will be populated for the listed below fileds if selected domain is accessible by the admin Department Organization Employment Type Role Job Role User Type Country State Language Date After Hire | D177: =MasterSheet_final!D171 -> Pass | E177: =MasterSheet_final!E171 -> 45810 | F177: =#REF! -> #REF! | G177: =MasterSheet_final!F171 -> Selva | H177: =IF(ISBLANK(E177)," ",WEEKNUM(E177,2)) -> 23 | I177: =if(H177=5,"27th Jan-2nd Feb", if(H177=6,"3rd Feb-9th Feb", if(H177=7,"10th Feb-16th Feb",if(H177=8,"17th Feb-23rd Feb", if(H177=9,"24th Feb-2nd March",if(H177=10,"3rd March - 9th March"," ")))))) | J177: =if(H177=5,"W1", if(H177=6,"W2", if(H177=7,"W3",if(H177=8,"W4", if(H177=9,"W5",if(H177=10,"W6"," "))))))
A178: =MasterSheet_final!A172 -> 171 | B178: =MasterSheet_final!B172 -> Learner Group | C178: =MasterSheet_final!C172 -> Verify that the admin able to search the learner group by using search option | D178: =MasterSheet_final!D172 -> Pass | E178: =MasterSheet_final!E172 -> 45807 | F178: =#REF! -> #REF! | G178: =MasterSheet_final!F172 -> Selva | H178: =IF(ISBLANK(E178)," ",WEEKNUM(E178,2)) -> 22 | I178: =if(H178=5,"27th Jan-2nd Feb", if(H178=6,"3rd Feb-9th Feb", if(H178=7,"10th Feb-16th Feb",if(H178=8,"17th Feb-23rd Feb", if(H178=9,"24th Feb-2nd March",if(H178=10,"3rd March - 9th March"," ")))))) | J178: =if(H178=5,"W1", if(H178=6,"W2", if(H178=7,"W3",if(H178=8,"W4", if(H178=9,"W5",if(H178=10,"W6"," "))))))
A179: =MasterSheet_final!A173 -> 172 | B179: =MasterSheet_final!B173 -> Learner Group | C179: =MasterSheet_final!C173 -> Verify that the admin able to search the learner group by voice search option | D179: =MasterSheet_final!D173 -> Pass | E179: =MasterSheet_final!E173 -> 45807 | F179: =#REF! -> #REF! | G179: =MasterSheet_final!F173 -> Selva | H179: =IF(ISBLANK(E179)," ",WEEKNUM(E179,2)) -> 22 | I179: =if(H179=5,"27th Jan-2nd Feb", if(H179=6,"3rd Feb-9th Feb", if(H179=7,"10th Feb-16th Feb",if(H179=8,"17th Feb-23rd Feb", if(H179=9,"24th Feb-2nd March",if(H179=10,"3rd March - 9th March"," ")))))) | J179: =if(H179=5,"W1", if(H179=6,"W2", if(H179=7,"W3",if(H179=8,"W4", if(H179=9,"W5",if(H179=10,"W6"," "))))))
A180: =MasterSheet_final!A174 -> 173 | B180: =MasterSheet_final!B174 -> Learner Group | C180: =MasterSheet_final!C174 -> Verify that the status filter will display the results based on the selection(Active,Suspended and Draft) | D180: =MasterSheet_final!D174 -> Pass | E180: =MasterSheet_final!E174 -> 45807 | F180: =#REF! -> #REF! | G180: =MasterSheet_final!F174 -> Selva | H180: =IF(ISBLANK(E180)," ",WEEKNUM(E180,2)) -> 22 | I180: =if(H180=5,"27th Jan-2nd Feb", if(H180=6,"3rd Feb-9th Feb", if(H180=7,"10th Feb-16th Feb",if(H180=8,"17th Feb-23rd Feb", if(H180=9,"24th Feb-2nd March",if(H180=10,"3rd March - 9th March"," ")))))) | J180: =if(H180=5,"W1", if(H180=6,"W2", if(H180=7,"W3",if(H180=8,"W4", if(H180=9,"W5",if(H180=10,"W6"," "))))))
A181: =MasterSheet_final!A175 -> 174 | B181: =MasterSheet_final!B175 -> Learner Group | C181: =MasterSheet_final!C175 -> Verify that the department filter working correctly | D181: =MasterSheet_final!D175 -> Pass | E181: =MasterSheet_final!E175 -> 45807 | F181: =#REF! -> #REF! | G181: =MasterSheet_final!F175 -> Selva | H181: =IF(ISBLANK(E181)," ",WEEKNUM(E181,2)) -> 22 | I181: =if(H181=5,"27th Jan-2nd Feb", if(H181=6,"3rd Feb-9th Feb", if(H181=7,"10th Feb-16th Feb",if(H181=8,"17th Feb-23rd Feb", if(H181=9,"24th Feb-2nd March",if(H181=10,"3rd March - 9th March"," ")))))) | J181: =if(H181=5,"W1", if(H181=6,"W2", if(H181=7,"W3",if(H181=8,"W4", if(H181=9,"W5",if(H181=10,"W6"," "))))))
A182: =MasterSheet_final!A176 -> 175 | B182: =MasterSheet_final!B176 -> Learner Group | C182: =MasterSheet_final!C176 -> Verify that the organization filter working correctly | D182: =MasterSheet_final!D176 -> Pass | E182: =MasterSheet_final!E176 -> 45807 | F182: =#REF! -> #REF! | G182: =MasterSheet_final!F176 -> Selva | H182: =IF(ISBLANK(E182)," ",WEEKNUM(E182,2)) -> 22 | I182: =if(H182=5,"27th Jan-2nd Feb", if(H182=6,"3rd Feb-9th Feb", if(H182=7,"10th Feb-16th Feb",if(H182=8,"17th Feb-23rd Feb", if(H182=9,"24th Feb-2nd March",if(H182=10,"3rd March - 9th March"," ")))))) | J182: =if(H182=5,"W1", if(H182=6,"W2", if(H182=7,"W3",if(H182=8,"W4", if(H182=9,"W5",if(H182=10,"W6"," "))))))
A183: =MasterSheet_final!A177 -> 176 | B183: =MasterSheet_final!B177 -> Learner Group | C183: =MasterSheet_final!C177 -> Verify that the Employment Type filter working correctly | D183: =MasterSheet_final!D177 -> Pass | E183: =MasterSheet_final!E177 -> 45807 | F183: =#REF! -> #REF! | G183: =MasterSheet_final!F177 -> Selva | H183: =IF(ISBLANK(E183)," ",WEEKNUM(E183,2)) -> 22 | I183: =if(H183=5,"27th Jan-2nd Feb", if(H183=6,"3rd Feb-9th Feb", if(H183=7,"10th Feb-16th Feb",if(H183=8,"17th Feb-23rd Feb", if(H183=9,"24th Feb-2nd March",if(H183=10,"3rd March - 9th March"," ")))))) | J183: =if(H183=5,"W1", if(H183=6,"W2", if(H183=7,"W3",if(H183=8,"W4", if(H183=9,"W5",if(H183=10,"W6"," "))))))
A184: =MasterSheet_final!A178 -> 177 | B184: =MasterSheet_final!B178 -> Learner Group | C184: =MasterSheet_final!C178 -> Verify that the Role filter working correctly | D184: =MasterSheet_final!D178 -> Pass | E184: =MasterSheet_final!E178 -> 45807 | F184: =#REF! -> #REF! | G184: =MasterSheet_final!F178 -> Selva | H184: =IF(ISBLANK(E184)," ",WEEKNUM(E184,2)) -> 22 | I184: =if(H184=5,"27th Jan-2nd Feb", if(H184=6,"3rd Feb-9th Feb", if(H184=7,"10th Feb-16th Feb",if(H184=8,"17th Feb-23rd Feb", if(H184=9,"24th Feb-2nd March",if(H184=10,"3rd March - 9th March"," ")))))) | J184: =if(H184=5,"W1", if(H184=6,"W2", if(H184=7,"W3",if(H184=8,"W4", if(H184=9,"W5",if(H184=10,"W6"," "))))))
A185: =MasterSheet_final!A179 -> 178 | B185: =MasterSheet_final!B179 -> Learner Group | C185: =MasterSheet_final!C179 -> Verify that the JobRole filter working correctly | D185: =MasterSheet_final!D179 -> Pass | E185: =MasterSheet_final!E179 -> 45807 | F185: =#REF! -> #REF! | G185: =MasterSheet_final!F179 -> Selva | H185: =IF(ISBLANK(E185)," ",WEEKNUM(E185,2)) -> 22 | I185: =if(H185=5,"27th Jan-2nd Feb", if(H185=6,"3rd Feb-9th Feb", if(H185=7,"10th Feb-16th Feb",if(H185=8,"17th Feb-23rd Feb", if(H185=9,"24th Feb-2nd March",if(H185=10,"3rd March - 9th March"," ")))))) | J185: =if(H185=5,"W1", if(H185=6,"W2", if(H185=7,"W3",if(H185=8,"W4", if(H185=9,"W5",if(H185=10,"W6"," "))))))
A186: =#REF! -> #REF! | B186: =#REF! -> #REF! | C186: =#REF! -> #REF! | D186: =#REF! -> #REF! | E186: =#REF! -> #REF! | F186: =#REF! -> #REF! | G186: =#REF! -> #REF! | H186: =IF(ISBLANK(E186)," ",WEEKNUM(E186,2)) -> #REF! | I186: =if(H186=5,"27th Jan-2nd Feb", if(H186=6,"3rd Feb-9th Feb", if(H186=7,"10th Feb-16th Feb",if(H186=8,"17th Feb-23rd Feb", if(H186=9,"24th Feb-2nd March",if(H186=10,"3rd March - 9th March"," ")))))) -> #REF! | J186: =if(H186=5,"W1", if(H186=6,"W2", if(H186=7,"W3",if(H186=8,"W4", if(H186=9,"W5",if(H186=10,"W6"," ")))))) -> #REF!
A187: =MasterSheet_final!A180 -> 179 | B187: =MasterSheet_final!B180 -> Learner Group | C187: =MasterSheet_final!C180 -> Verify that the UserType filter working correctly | D187: =MasterSheet_final!D180 -> Pass | E187: =MasterSheet_final!E180 -> 45807 | F187: =#REF! -> #REF! | G187: =MasterSheet_final!F180 -> Selva | H187: =IF(ISBLANK(E187)," ",WEEKNUM(E187,2)) -> 22 | I187: =if(H187=5,"27th Jan-2nd Feb", if(H187=6,"3rd Feb-9th Feb", if(H187=7,"10th Feb-16th Feb",if(H187=8,"17th Feb-23rd Feb", if(H187=9,"24th Feb-2nd March",if(H187=10,"3rd March - 9th March"," ")))))) | J187: =if(H187=5,"W1", if(H187=6,"W2", if(H187=7,"W3",if(H187=8,"W4", if(H187=9,"W5",if(H187=10,"W6"," "))))))
A188: =MasterSheet_final!A181 -> 180 | B188: =MasterSheet_final!B181 -> Learner Group | C188: =MasterSheet_final!C181 -> Verify that the Country filter working correctly | D188: =MasterSheet_final!D181 -> Pass | E188: =MasterSheet_final!E181 -> 45807 | F188: =#REF! -> #REF! | G188: =MasterSheet_final!F181 -> Selva | H188: =IF(ISBLANK(E188)," ",WEEKNUM(E188,2)) -> 22 | I188: =if(H188=5,"27th Jan-2nd Feb", if(H188=6,"3rd Feb-9th Feb", if(H188=7,"10th Feb-16th Feb",if(H188=8,"17th Feb-23rd Feb", if(H188=9,"24th Feb-2nd March",if(H188=10,"3rd March - 9th March"," ")))))) | J188: =if(H188=5,"W1", if(H188=6,"W2", if(H188=7,"W3",if(H188=8,"W4", if(H188=9,"W5",if(H188=10,"W6"," "))))))
A189: =MasterSheet_final!A182 -> 181 | B189: =MasterSheet_final!B182 -> Learner Group | C189: =MasterSheet_final!C182 -> Verify that the State filter working correctly | D189: =MasterSheet_final!D182 -> Pass | E189: =MasterSheet_final!E182 -> 45808 | F189: =#REF! -> #REF! | G189: =MasterSheet_final!F182 -> Selva | H189: =IF(ISBLANK(E189)," ",WEEKNUM(E189,2)) -> 22 | I189: =if(H189=5,"27th Jan-2nd Feb", if(H189=6,"3rd Feb-9th Feb", if(H189=7,"10th Feb-16th Feb",if(H189=8,"17th Feb-23rd Feb", if(H189=9,"24th Feb-2nd March",if(H189=10,"3rd March - 9th March"," ")))))) | J189: =if(H189=5,"W1", if(H189=6,"W2", if(H189=7,"W3",if(H189=8,"W4", if(H189=9,"W5",if(H189=10,"W6"," "))))))
A190: =MasterSheet_final!A183 -> 182 | B190: =MasterSheet_final!B183 -> Learner Group | C190: =MasterSheet_final!C183 -> Verify that the Language filter working correctly | D190: =MasterSheet_final!D183 -> Pass | E190: =MasterSheet_final!E183 -> 45808 | F190: =#REF! -> #REF! | G190: =MasterSheet_final!F183 -> Selva | H190: =IF(ISBLANK(E190)," ",WEEKNUM(E190,2)) -> 22 | I190: =if(H190=5,"27th Jan-2nd Feb", if(H190=6,"3rd Feb-9th Feb", if(H190=7,"10th Feb-16th Feb",if(H190=8,"17th Feb-23rd Feb", if(H190=9,"24th Feb-2nd March",if(H190=10,"3rd March - 9th March"," ")))))) | J190: =if(H190=5,"W1", if(H190=6,"W2", if(H190=7,"W3",if(H190=8,"W4", if(H190=9,"W5",if(H190=10,"W6"," "))))))
A191: =MasterSheet_final!A184 -> 183 | B191: =MasterSheet_final!B184 -> Learner Group | C191: =MasterSheet_final!C184 -> Verify that the Date After Hire filter working correctly | D191: =MasterSheet_final!D184 -> Pass | E191: =MasterSheet_final!E184 -> 45808 | F191: =#REF! -> #REF! | G191: =MasterSheet_final!F184 -> Selva | H191: =IF(ISBLANK(E191)," ",WEEKNUM(E191,2)) -> 22 | I191: =if(H191=5,"27th Jan-2nd Feb", if(H191=6,"3rd Feb-9th Feb", if(H191=7,"10th Feb-16th Feb",if(H191=8,"17th Feb-23rd Feb", if(H191=9,"24th Feb-2nd March",if(H191=10,"3rd March - 9th March"," ")))))) | J191: =if(H191=5,"W1", if(H191=6,"W2", if(H191=7,"W3",if(H191=8,"W4", if(H191=9,"W5",if(H191=10,"W6"," "))))))
A192: =MasterSheet_final!A185 -> 184 | B192: =MasterSheet_final!B185 -> Learner Group | C192: =MasterSheet_final!C185 -> Verify that the multiple filter combinations are working correctly | D192: =MasterSheet_final!D185 -> Pass | E192: =MasterSheet_final!E185 -> 45808 | F192: =#REF! -> #REF! | G192: =MasterSheet_final!F185 -> Selva | H192: =IF(ISBLANK(E192)," ",WEEKNUM(E192,2)) -> 22 | I192: =if(H192=5,"27th Jan-2nd Feb", if(H192=6,"3rd Feb-9th Feb", if(H192=7,"10th Feb-16th Feb",if(H192=8,"17th Feb-23rd Feb", if(H192=9,"24th Feb-2nd March",if(H192=10,"3rd March - 9th March"," ")))))) | J192: =if(H192=5,"W1", if(H192=6,"W2", if(H192=7,"W3",if(H192=8,"W4", if(H192=9,"W5",if(H192=10,"W6"," "))))))
A193: =MasterSheet_final!A186 -> 185 | B193: =MasterSheet_final!B186 -> Learner Group | C193: =MasterSheet_final!C186 -> Verify that the Clear and Apply button are working correctly | D193: =MasterSheet_final!D186 -> Pass | E193: =MasterSheet_final!E186 -> 45807 | F193: =#REF! -> #REF! | G193: =MasterSheet_final!F186 -> Selva | H193: =IF(ISBLANK(E193)," ",WEEKNUM(E193,2)) -> 22 | I193: =if(H193=5,"27th Jan-2nd Feb", if(H193=6,"3rd Feb-9th Feb", if(H193=7,"10th Feb-16th Feb",if(H193=8,"17th Feb-23rd Feb", if(H193=9,"24th Feb-2nd March",if(H193=10,"3rd March - 9th March"," ")))))) | J193: =if(H193=5,"W1", if(H193=6,"W2", if(H193=7,"W3",if(H193=8,"W4", if(H193=9,"W5",if(H193=10,"W6"," "))))))
A194: =MasterSheet_final!A187 -> 186 | B194: =MasterSheet_final!B187 -> Learner Group | C194: =MasterSheet_final!C187 -> Verify that the Saved filters are working correctly | D194: =MasterSheet_final!D187 -> Pass | E194: =MasterSheet_final!E187 -> 45808 | F194: =#REF! -> #REF! | G194: =MasterSheet_final!F187 -> Selva | H194: =IF(ISBLANK(E194)," ",WEEKNUM(E194,2)) -> 22 | I194: =if(H194=5,"27th Jan-2nd Feb", if(H194=6,"3rd Feb-9th Feb", if(H194=7,"10th Feb-16th Feb",if(H194=8,"17th Feb-23rd Feb", if(H194=9,"24th Feb-2nd March",if(H194=10,"3rd March - 9th March"," ")))))) | J194: =if(H194=5,"W1", if(H194=6,"W2", if(H194=7,"W3",if(H194=8,"W4", if(H194=9,"W5",if(H194=10,"W6"," "))))))
A195: =MasterSheet_final!A188 -> 187 | B195: =MasterSheet_final!B188 -> Learner Group | C195: =MasterSheet_final!C188 -> Verfiy that the Sorts are working correctly(A-Z,Z-A,New-OLD,OLD-New) | D195: =MasterSheet_final!D188 -> Pass | E195: =MasterSheet_final!E188 -> 45807 | F195: =#REF! -> #REF! | G195: =MasterSheet_final!F188 -> Selva | H195: =IF(ISBLANK(E195)," ",WEEKNUM(E195,2)) -> 22 | I195: =if(H195=5,"27th Jan-2nd Feb", if(H195=6,"3rd Feb-9th Feb", if(H195=7,"10th Feb-16th Feb",if(H195=8,"17th Feb-23rd Feb", if(H195=9,"24th Feb-2nd March",if(H195=10,"3rd March - 9th March"," ")))))) | J195: =if(H195=5,"W1", if(H195=6,"W2", if(H195=7,"W3",if(H195=8,"W4", if(H195=9,"W5",if(H195=10,"W6"," "))))))
A196: =MasterSheet_final!A189 -> 188 | B196: =MasterSheet_final!B189 -> Learner Group | C196: =MasterSheet_final!C189 -> Verify that the Export is working with all three format(PDF,EXCL and CSV),check data will be displayed in all three format | D196: =MasterSheet_final!D189 -> Pass | E196: =MasterSheet_final!E189 -> 45808 | F196: =#REF! -> #REF! | G196: =MasterSheet_final!F189 -> Selva | H196: =IF(ISBLANK(E196)," ",WEEKNUM(E196,2)) -> 22 | I196: =if(H196=5,"27th Jan-2nd Feb", if(H196=6,"3rd Feb-9th Feb", if(H196=7,"10th Feb-16th Feb",if(H196=8,"17th Feb-23rd Feb", if(H196=9,"24th Feb-2nd March",if(H196=10,"3rd March - 9th March"," ")))))) | J196: =if(H196=5,"W1", if(H196=6,"W2", if(H196=7,"W3",if(H196=8,"W4", if(H196=9,"W5",if(H196=10,"W6"," "))))))
A197: =MasterSheet_final!A190 -> 189 | B197: =MasterSheet_final!B190 -> Learner Group | C197: =MasterSheet_final!C190 -> Verfiy that the Load More is displayed if more than five records created in the list | D197: =MasterSheet_final!D190 -> Pass | E197: =MasterSheet_final!E190 -> 45807 | F197: =#REF! -> #REF! | G197: =MasterSheet_final!F190 -> Selva | H197: =IF(ISBLANK(E197)," ",WEEKNUM(E197,2)) -> 22 | I197: =if(H197=5,"27th Jan-2nd Feb", if(H197=6,"3rd Feb-9th Feb", if(H197=7,"10th Feb-16th Feb",if(H197=8,"17th Feb-23rd Feb", if(H197=9,"24th Feb-2nd March",if(H197=10,"3rd March - 9th March"," ")))))) | J197: =if(H197=5,"W1", if(H197=6,"W2", if(H197=7,"W3",if(H197=8,"W4", if(H197=9,"W5",if(H197=10,"W6"," "))))))
A198: =#REF! -> #REF! | B198: =#REF! -> #REF! | C198: =#REF! -> #REF! | D198: =#REF! -> #REF! | E198: =#REF! -> #REF! | F198: =#REF! -> #REF! | G198: =#REF! -> #REF! | H198: =IF(ISBLANK(E198)," ",WEEKNUM(E198,2)) -> #REF! | I198: =if(H198=5,"27th Jan-2nd Feb", if(H198=6,"3rd Feb-9th Feb", if(H198=7,"10th Feb-16th Feb",if(H198=8,"17th Feb-23rd Feb", if(H198=9,"24th Feb-2nd March",if(H198=10,"3rd March - 9th March"," ")))))) -> #REF! | J198: =if(H198=5,"W1", if(H198=6,"W2", if(H198=7,"W3",if(H198=8,"W4", if(H198=9,"W5",if(H198=10,"W6"," ")))))) -> #REF!
A199: =#REF! -> #REF! | B199: =#REF! -> #REF! | C199: =#REF! -> #REF! | D199: =#REF! -> #REF! | E199: =#REF! -> #REF! | F199: =#REF! -> #REF! | G199: =#REF! -> #REF! | H199: =IF(ISBLANK(E199)," ",WEEKNUM(E199,2)) -> #REF! | I199: =if(H199=5,"27th Jan-2nd Feb", if(H199=6,"3rd Feb-9th Feb", if(H199=7,"10th Feb-16th Feb",if(H199=8,"17th Feb-23rd Feb", if(H199=9,"24th Feb-2nd March",if(H199=10,"3rd March - 9th March"," ")))))) -> #REF! | J199: =if(H199=5,"W1", if(H199=6,"W2", if(H199=7,"W3",if(H199=8,"W4", if(H199=9,"W5",if(H199=10,"W6"," ")))))) -> #REF!
A200: =#REF! -> #REF! | B200: =#REF! -> #REF! | C200: =#REF! -> #REF! | D200: =#REF! -> #REF! | E200: =#REF! -> #REF! | F200: =#REF! -> #REF! | G200: =#REF! -> #REF! | H200: =IF(ISBLANK(E200)," ",WEEKNUM(E200,2)) -> #REF! | I200: =if(H200=5,"27th Jan-2nd Feb", if(H200=6,"3rd Feb-9th Feb", if(H200=7,"10th Feb-16th Feb",if(H200=8,"17th Feb-23rd Feb", if(H200=9,"24th Feb-2nd March",if(H200=10,"3rd March - 9th March"," ")))))) -> #REF! | J200: =if(H200=5,"W1", if(H200=6,"W2", if(H200=7,"W3",if(H200=8,"W4", if(H200=9,"W5",if(H200=10,"W6"," ")))))) -> #REF!
A201: =#REF! -> #REF! | B201: =#REF! -> #REF! | C201: =#REF! -> #REF! | D201: =#REF! -> #REF! | E201: =#REF! -> #REF! | F201: =#REF! -> #REF! | G201: =#REF! -> #REF! | H201: =IF(ISBLANK(E201)," ",WEEKNUM(E201,2)) -> #REF! | I201: =if(H201=5,"27th Jan-2nd Feb", if(H201=6,"3rd Feb-9th Feb", if(H201=7,"10th Feb-16th Feb",if(H201=8,"17th Feb-23rd Feb", if(H201=9,"24th Feb-2nd March",if(H201=10,"3rd March - 9th March"," ")))))) -> #REF! | J201: =if(H201=5,"W1", if(H201=6,"W2", if(H201=7,"W3",if(H201=8,"W4", if(H201=9,"W5",if(H201=10,"W6"," ")))))) -> #REF!
A202: =#REF! -> #REF! | B202: =#REF! -> #REF! | C202: =#REF! -> #REF! | D202: =#REF! -> #REF! | E202: =#REF! -> #REF! | F202: =#REF! -> #REF! | G202: =#REF! -> #REF! | H202: =IF(ISBLANK(E202)," ",WEEKNUM(E202,2)) -> #REF! | I202: =if(H202=5,"27th Jan-2nd Feb", if(H202=6,"3rd Feb-9th Feb", if(H202=7,"10th Feb-16th Feb",if(H202=8,"17th Feb-23rd Feb", if(H202=9,"24th Feb-2nd March",if(H202=10,"3rd March - 9th March"," ")))))) -> #REF! | J202: =if(H202=5,"W1", if(H202=6,"W2", if(H202=7,"W3",if(H202=8,"W4", if(H202=9,"W5",if(H202=10,"W6"," ")))))) -> #REF!
A203: =MasterSheet_final!A191 -> 190 | B203: =MasterSheet_final!B191 -> Learner Group | C203: =MasterSheet_final!C191 -> Verify that the created records are displayed when click loadmore | D203: =MasterSheet_final!D191 -> Pass | E203: =MasterSheet_final!E191 -> 45807 | F203: =#REF! -> #REF! | G203: =MasterSheet_final!F191 -> Selva | H203: =IF(ISBLANK(E203)," ",WEEKNUM(E203,2)) -> 22 | I203: =if(H203=5,"27th Jan-2nd Feb", if(H203=6,"3rd Feb-9th Feb", if(H203=7,"10th Feb-16th Feb",if(H203=8,"17th Feb-23rd Feb", if(H203=9,"24th Feb-2nd March",if(H203=10,"3rd March - 9th March"," ")))))) | J203: =if(H203=5,"W1", if(H203=6,"W2", if(H203=7,"W3",if(H203=8,"W4", if(H203=9,"W5",if(H203=10,"W6"," "))))))
A204: =MasterSheet_final!A192 -> 191 | B204: =MasterSheet_final!B192 -> Learner Group | C204: =MasterSheet_final!C192 -> Verfiy that the admin able to Suspend the Learner group and check associated learner groups access will be removed Verify that admin able to delet the Learner Group if admin suspended the learner group | D204: =MasterSheet_final!D192 -> Pass | E204: =MasterSheet_final!E192 -> 45811 | F204: =#REF! -> #REF! | G204: =MasterSheet_final!F192 -> Selva | H204: =IF(ISBLANK(E204)," ",WEEKNUM(E204,2)) -> 23 | I204: =if(H204=5,"27th Jan-2nd Feb", if(H204=6,"3rd Feb-9th Feb", if(H204=7,"10th Feb-16th Feb",if(H204=8,"17th Feb-23rd Feb", if(H204=9,"24th Feb-2nd March",if(H204=10,"3rd March - 9th March"," ")))))) | J204: =if(H204=5,"W1", if(H204=6,"W2", if(H204=7,"W3",if(H204=8,"W4", if(H204=9,"W5",if(H204=10,"W6"," "))))))
A205: =MasterSheet_final!A193 -> 192 | B205: =MasterSheet_final!B193 -> Learner Group | C205: =MasterSheet_final!C193 -> Verify that the admin will not allow to suspend the learner group if associated learner groups are attached with compliance course or tp | D205: =MasterSheet_final!D193 -> Pass | E205: =MasterSheet_final!E193 -> 45811 | F205: =#REF! -> #REF! | G205: =MasterSheet_final!F193 -> Selva | H205: =IF(ISBLANK(E205)," ",WEEKNUM(E205,2)) -> 23 | I205: =if(H205=5,"27th Jan-2nd Feb", if(H205=6,"3rd Feb-9th Feb", if(H205=7,"10th Feb-16th Feb",if(H205=8,"17th Feb-23rd Feb", if(H205=9,"24th Feb-2nd March",if(H205=10,"3rd March - 9th March"," ")))))) | J205: =if(H205=5,"W1", if(H205=6,"W2", if(H205=7,"W3",if(H205=8,"W4", if(H205=9,"W5",if(H205=10,"W6"," "))))))
A206: =MasterSheet_final!A194 -> 193 | B206: =MasterSheet_final!B194 -> Learner Group | C206: =MasterSheet_final!C194 -> Verfiy that the unathourised learners able to view the course or tp in learner ui if associated learner group is suspended | D206: =MasterSheet_final!D194 -> Pass | E206: =MasterSheet_final!E194 -> 45811 | F206: =#REF! -> #REF! | G206: =MasterSheet_final!F194 -> Selva | H206: =IF(ISBLANK(E206)," ",WEEKNUM(E206,2)) -> 23 | I206: =if(H206=5,"27th Jan-2nd Feb", if(H206=6,"3rd Feb-9th Feb", if(H206=7,"10th Feb-16th Feb",if(H206=8,"17th Feb-23rd Feb", if(H206=9,"24th Feb-2nd March",if(H206=10,"3rd March - 9th March"," ")))))) | J206: =if(H206=5,"W1", if(H206=6,"W2", if(H206=7,"W3",if(H206=8,"W4", if(H206=9,"W5",if(H206=10,"W6"," "))))))
A207: =MasterSheet_final!A195 -> 194 | B207: =MasterSheet_final!B195 -> Learner Group | C207: =MasterSheet_final!C195 -> Verify that the admin ll not view any records which is created by other admin,records should not visible admin who doest not have access on any records | D207: =MasterSheet_final!D195 -> Pass | E207: =MasterSheet_final!E195 -> 45811 | F207: =#REF! -> #REF! | G207: =MasterSheet_final!F195 -> Selva | H207: =IF(ISBLANK(E207)," ",WEEKNUM(E207,2)) -> 23 | I207: =if(H207=5,"27th Jan-2nd Feb", if(H207=6,"3rd Feb-9th Feb", if(H207=7,"10th Feb-16th Feb",if(H207=8,"17th Feb-23rd Feb", if(H207=9,"24th Feb-2nd March",if(H207=10,"3rd March - 9th March"," ")))))) | J207: =if(H207=5,"W1", if(H207=6,"W2", if(H207=7,"W3",if(H207=8,"W4", if(H207=9,"W5",if(H207=10,"W6"," "))))))
A208: =MasterSheet_final!A196 -> 195 | B208: =MasterSheet_final!B196 -> Learner Group | C208: =MasterSheet_final!C196 -> Verify that the admin able to edit the learner group and check able to update the page | D208: =MasterSheet_final!D196 -> Pass | E208: =MasterSheet_final!E196 -> 45807 | F208: =#REF! -> #REF! | G208: =MasterSheet_final!F196 -> Selva | H208: =IF(ISBLANK(E208)," ",WEEKNUM(E208,2)) -> 22 | I208: =if(H208=5,"27th Jan-2nd Feb", if(H208=6,"3rd Feb-9th Feb", if(H208=7,"10th Feb-16th Feb",if(H208=8,"17th Feb-23rd Feb", if(H208=9,"24th Feb-2nd March",if(H208=10,"3rd March - 9th March"," ")))))) | J208: =if(H208=5,"W1", if(H208=6,"W2", if(H208=7,"W3",if(H208=8,"W4", if(H208=9,"W5",if(H208=10,"W6"," "))))))
A209: =MasterSheet_final!A197 -> 196 | B209: =MasterSheet_final!B197 -> Learner Group | C209: =MasterSheet_final!C197 -> Verify that the admin will allow to delete the learner group after suspend | D209: =MasterSheet_final!D197 -> Pass | E209: =MasterSheet_final!E197 -> 45807 | F209: =#REF! -> #REF! | G209: =MasterSheet_final!F197 -> Selva | H209: =IF(ISBLANK(E209)," ",WEEKNUM(E209,2)) -> 22 | I209: =if(H209=5,"27th Jan-2nd Feb", if(H209=6,"3rd Feb-9th Feb", if(H209=7,"10th Feb-16th Feb",if(H209=8,"17th Feb-23rd Feb", if(H209=9,"24th Feb-2nd March",if(H209=10,"3rd March - 9th March"," ")))))) | J209: =if(H209=5,"W1", if(H209=6,"W2", if(H209=7,"W3",if(H209=8,"W4", if(H209=9,"W5",if(H209=10,"W6"," "))))))
A210: =MasterSheet_final!A198 -> 197 | B210: =MasterSheet_final!B198 -> Learner Group | C210: =MasterSheet_final!C198 -> Verify that the admin able to suspend the learner group in edit /list | D210: =MasterSheet_final!D198 -> Pass | E210: =MasterSheet_final!E198 -> 45807 | F210: =#REF! -> #REF! | G210: =MasterSheet_final!F198 -> Selva | H210: =IF(ISBLANK(E210)," ",WEEKNUM(E210,2)) -> 22 | I210: =if(H210=5,"27th Jan-2nd Feb", if(H210=6,"3rd Feb-9th Feb", if(H210=7,"10th Feb-16th Feb",if(H210=8,"17th Feb-23rd Feb", if(H210=9,"24th Feb-2nd March",if(H210=10,"3rd March - 9th March"," ")))))) | J210: =if(H210=5,"W1", if(H210=6,"W2", if(H210=7,"W3",if(H210=8,"W4", if(H210=9,"W5",if(H210=10,"W6"," "))))))
A211: =MasterSheet_final!A199 -> 198 | B211: =MasterSheet_final!B199 -> Learner Group | C211: =MasterSheet_final!C199 -> Verify that the Update and Discard button will be enabled when update any value in the edit page | D211: =MasterSheet_final!D199 -> Pass | E211: =MasterSheet_final!E199 -> 45807 | F211: =#REF! -> #REF! | G211: =MasterSheet_final!F199 -> Selva | H211: =IF(ISBLANK(E211)," ",WEEKNUM(E211,2)) -> 22 | I211: =if(H211=5,"27th Jan-2nd Feb", if(H211=6,"3rd Feb-9th Feb", if(H211=7,"10th Feb-16th Feb",if(H211=8,"17th Feb-23rd Feb", if(H211=9,"24th Feb-2nd March",if(H211=10,"3rd March - 9th March"," ")))))) | J211: =if(H211=5,"W1", if(H211=6,"W2", if(H211=7,"W3",if(H211=8,"W4", if(H211=9,"W5",if(H211=10,"W6"," "))))))
A212: =MasterSheet_final!A200 -> 199 | B212: =MasterSheet_final!B200 -> Learner Group | C212: =MasterSheet_final!C200 -> Verify that the admin will not allow to update the Default learner group | D212: =MasterSheet_final!D200 -> Pass | E212: =MasterSheet_final!E200 -> 45807 | F212: =#REF! -> #REF! | G212: =MasterSheet_final!F200 -> Selva | H212: =IF(ISBLANK(E212)," ",WEEKNUM(E212,2)) -> 22 | I212: =if(H212=5,"27th Jan-2nd Feb", if(H212=6,"3rd Feb-9th Feb", if(H212=7,"10th Feb-16th Feb",if(H212=8,"17th Feb-23rd Feb", if(H212=9,"24th Feb-2nd March",if(H212=10,"3rd March - 9th March"," ")))))) | J212: =if(H212=5,"W1", if(H212=6,"W2", if(H212=7,"W3",if(H212=8,"W4", if(H212=9,"W5",if(H212=10,"W6"," "))))))
A213: =MasterSheet_final!A201 -> 200 | B213: =MasterSheet_final!B201 -> Learner Group | C213: =MasterSheet_final!C201 -> Verify whether the Learner Group goes to Unpublished state after the Valid till date | D213: =MasterSheet_final!D201 -> Pass | E213: =MasterSheet_final!E201 -> 45811 | F213: =#REF! -> #REF! | G213: =MasterSheet_final!F201 -> Selva | H213: =IF(ISBLANK(E213)," ",WEEKNUM(E213,2)) -> 23 | I213: =if(H213=5,"27th Jan-2nd Feb", if(H213=6,"3rd Feb-9th Feb", if(H213=7,"10th Feb-16th Feb",if(H213=8,"17th Feb-23rd Feb", if(H213=9,"24th Feb-2nd March",if(H213=10,"3rd March - 9th March"," ")))))) | J213: =if(H213=5,"W1", if(H213=6,"W2", if(H213=7,"W3",if(H213=8,"W4", if(H213=9,"W5",if(H213=10,"W6"," "))))))
A214: =MasterSheet_final!A202 -> 201 | B214: =MasterSheet_final!B202 -> Learner Group | C214: =MasterSheet_final!C202 -> Verify that created Learner Group in one tenant should not display in another tenant | D214: =MasterSheet_final!D202 -> Pass | E214: =MasterSheet_final!E202 -> 45811 | F214: =#REF! -> #REF! | G214: =MasterSheet_final!F202 -> Selva | H214: =IF(ISBLANK(E214)," ",WEEKNUM(E214,2)) -> 23 | I214: =if(H214=5,"27th Jan-2nd Feb", if(H214=6,"3rd Feb-9th Feb", if(H214=7,"10th Feb-16th Feb",if(H214=8,"17th Feb-23rd Feb", if(H214=9,"24th Feb-2nd March",if(H214=10,"3rd March - 9th March"," ")))))) | J214: =if(H214=5,"W1", if(H214=6,"W2", if(H214=7,"W3",if(H214=8,"W4", if(H214=9,"W5",if(H214=10,"W6"," "))))))
... A243: =MasterSheet_final!A231 -> 230 | B243: =MasterSheet_final!B231 -> Organization | C243: =MasterSheet_final!C231 -> Verify able to create and edit the organization from toggle menu bar and quick access | D243: =MasterSheet_final!D231 -> Pass | E243: =MasterSheet_final!E231 -> 45797 | F243: =#REF! -> #REF! | G243: =MasterSheet_final!F231 -> Manikandan | H243: =IF(ISBLANK(E243)," ",WEEKNUM(E243,2)) -> 21 | I243: =if(H243=5,"27th Jan-2nd Feb", if(H243=6,"3rd Feb-9th Feb", if(H243=7,"10th Feb-16th Feb",if(H243=8,"17th Feb-23rd Feb", if(H243=9,"24th Feb-2nd March",if(H243=10,"3rd March - 9th March"," ")))))) | J243: =if(H243=5,"W1", if(H243=6,"W2", if(H243=7,"W3",if(H243=8,"W4", if(H243=9,"W5",if(H243=10,"W6"," "))))))
A244: =#REF! -> #REF! | B244: =#REF! -> #REF! | C244: =#REF! -> #REF! | D244: =#REF! -> #REF! | E244: =#REF! -> #REF! | F244: =#REF! -> #REF! | G244: =#REF! -> #REF! | H244: =IF(ISBLANK(E244)," ",WEEKNUM(E244,2)) -> #REF! | I244: =if(H244=5,"27th Jan-2nd Feb", if(H244=6,"3rd Feb-9th Feb", if(H244=7,"10th Feb-16th Feb",if(H244=8,"17th Feb-23rd Feb", if(H244=9,"24th Feb-2nd March",if(H244=10,"3rd March - 9th March"," ")))))) -> #REF! | J244: =if(H244=5,"W1", if(H244=6,"W2", if(H244=7,"W3",if(H244=8,"W4", if(H244=9,"W5",if(H244=10,"W6"," ")))))) -> #REF!
A245: =MasterSheet_final!A232 -> 231 | B245: =MasterSheet_final!B232 -> Organization | C245: =MasterSheet_final!C232 -> Verify and check the newly created Organization will be accessible to all the admin groups by default in the access section | D245: =MasterSheet_final!D232 -> Pass | E245: =MasterSheet_final!E232 -> 45797 | F245: =#REF! -> #REF! | G245: =MasterSheet_final!F232 -> Manikandan | H245: =IF(ISBLANK(E245)," ",WEEKNUM(E245,2)) -> 21 | I245: =if(H245=5,"27th Jan-2nd Feb", if(H245=6,"3rd Feb-9th Feb", if(H245=7,"10th Feb-16th Feb",if(H245=8,"17th Feb-23rd Feb", if(H245=9,"24th Feb-2nd March",if(H245=10,"3rd March - 9th March"," ")))))) | J245: =if(H245=5,"W1", if(H245=6,"W2", if(H245=7,"W3",if(H245=8,"W4", if(H245=9,"W5",if(H245=10,"W6"," "))))))
A246: =MasterSheet_final!A233 -> 232 | B246: =MasterSheet_final!B233 -> Organization | C246: =MasterSheet_final!C233 -> Verify able to create, Edit and Delete an organization | D246: =MasterSheet_final!D233 -> Pass | E246: =MasterSheet_final!E233 -> 45797 | F246: =#REF! -> #REF! | G246: =MasterSheet_final!F233 -> Manikandan | H246: =IF(ISBLANK(E246)," ",WEEKNUM(E246,2)) -> 21 | I246: =if(H246=5,"27th Jan-2nd Feb", if(H246=6,"3rd Feb-9th Feb", if(H246=7,"10th Feb-16th Feb",if(H246=8,"17th Feb-23rd Feb", if(H246=9,"24th Feb-2nd March",if(H246=10,"3rd March - 9th March"," ")))))) | J246: =if(H246=5,"W1", if(H246=6,"W2", if(H246=7,"W3",if(H246=8,"W4", if(H246=9,"W5",if(H246=10,"W6"," "))))))
A247: =MasterSheet_final!A234 -> 233 | B247: =MasterSheet_final!B234 -> Organization | C247: =MasterSheet_final!C234 -> Verify and check after created the organization the following success message need to be displayed " Title of the organization” has been Created Successfully". | D247: =MasterSheet_final!D234 -> Pass | E247: =MasterSheet_final!E234 -> 45797 | F247: =#REF! -> #REF! | G247: =MasterSheet_final!F234 -> Manikandan | H247: =IF(ISBLANK(E247)," ",WEEKNUM(E247,2)) -> 21 | I247: =if(H247=5,"27th Jan-2nd Feb", if(H247=6,"3rd Feb-9th Feb", if(H247=7,"10th Feb-16th Feb",if(H247=8,"17th Feb-23rd Feb", if(H247=9,"24th Feb-2nd March",if(H247=10,"3rd March - 9th March"," ")))))) | J247: =if(H247=5,"W1", if(H247=6,"W2", if(H247=7,"W3",if(H247=8,"W4", if(H247=9,"W5",if(H247=10,"W6"," "))))))
A248: =MasterSheet_final!A235 -> 234 | B248: =MasterSheet_final!B235 -> Organization | C248: =MasterSheet_final!C235 -> Verify unable to create the organization with same name the following message needs to be displayed "Name already Exists”. | D248: =MasterSheet_final!D235 -> Pass | E248: =MasterSheet_final!E235 -> 45797 | F248: =#REF! -> #REF! | G248: =MasterSheet_final!F235 -> Manikandan | H248: =IF(ISBLANK(E248)," ",WEEKNUM(E248,2)) -> 21 | I248: =if(H248=5,"27th Jan-2nd Feb", if(H248=6,"3rd Feb-9th Feb", if(H248=7,"10th Feb-16th Feb",if(H248=8,"17th Feb-23rd Feb", if(H248=9,"24th Feb-2nd March",if(H248=10,"3rd March - 9th March"," ")))))) | J248: =if(H248=5,"W1", if(H248=6,"W2", if(H248=7,"W3",if(H248=8,"W4", if(H248=9,"W5",if(H248=10,"W6"," "))))))
A249: =MasterSheet_final!A236 -> 235 | B249: =MasterSheet_final!B236 -> Organization | C249: =MasterSheet_final!C236 -> -Verify able to create an organization type as Internal -Ensure In user creation page after setting the organization the organization type need to change as Internal | D249: =MasterSheet_final!D236 -> Pass | E249: =MasterSheet_final!E236 -> 45797 | F249: =#REF! -> #REF! | G249: =MasterSheet_final!F236 -> Manikandan | H249: =IF(ISBLANK(E249)," ",WEEKNUM(E249,2)) -> 21 | I249: =if(H249=5,"27th Jan-2nd Feb", if(H249=6,"3rd Feb-9th Feb", if(H249=7,"10th Feb-16th Feb",if(H249=8,"17th Feb-23rd Feb", if(H249=9,"24th Feb-2nd March",if(H249=10,"3rd March - 9th March"," ")))))) | J249: =if(H249=5,"W1", if(H249=6,"W2", if(H249=7,"W3",if(H249=8,"W4", if(H249=9,"W5",if(H249=10,"W6"," "))))))
A250: =MasterSheet_final!A237 -> 236 | B250: =MasterSheet_final!B237 -> Organization | C250: =MasterSheet_final!C237 -> - To Verify able to create an organization type as External - In user creation page after setting the organization the organization type need to change as External | D250: =MasterSheet_final!D237 -> Pass | E250: =MasterSheet_final!E237 -> 45797 | F250: =#REF! -> #REF! | G250: =MasterSheet_final!F237 -> Manikandan | H250: =IF(ISBLANK(E250)," ",WEEKNUM(E250,2)) -> 21 | I250: =if(H250=5,"27th Jan-2nd Feb", if(H250=6,"3rd Feb-9th Feb", if(H250=7,"10th Feb-16th Feb",if(H250=8,"17th Feb-23rd Feb", if(H250=9,"24th Feb-2nd March",if(H250=10,"3rd March - 9th March"," ")))))) | J250: =if(H250=5,"W1", if(H250=6,"W2", if(H250=7,"W3",if(H250=8,"W4", if(H250=9,"W5",if(H250=10,"W6"," "))))))
A251: =MasterSheet_final!A238 -> 237 | B251: =MasterSheet_final!B238 -> Organization | C251: =MasterSheet_final!C238 -> To Verify the created organizations are listing in various domains | D251: =MasterSheet_final!D238 -> Pass | E251: =MasterSheet_final!E238 -> 45800 | F251: =#REF! -> #REF! | G251: =MasterSheet_final!F238 -> Manikandan | H251: =IF(ISBLANK(E251)," ",WEEKNUM(E251,2)) -> 21 | I251: =if(H251=5,"27th Jan-2nd Feb", if(H251=6,"3rd Feb-9th Feb", if(H251=7,"10th Feb-16th Feb",if(H251=8,"17th Feb-23rd Feb", if(H251=9,"24th Feb-2nd March",if(H251=10,"3rd March - 9th March"," ")))))) | J251: =if(H251=5,"W1", if(H251=6,"W2", if(H251=7,"W3",if(H251=8,"W4", if(H251=9,"W5",if(H251=10,"W6"," "))))))
A252: =MasterSheet_final!A239 -> 238 | B252: =MasterSheet_final!B239 -> Organization | C252: =MasterSheet_final!C239 -> To Verify the created organizations will be displayed in user creation page and group creation. | D252: =MasterSheet_final!D239 -> Pass | E252: =MasterSheet_final!E239 -> 45804 | F252: =#REF! -> #REF! | G252: =MasterSheet_final!F239 -> Manikandan | H252: =IF(ISBLANK(E252)," ",WEEKNUM(E252,2)) -> 22 | I252: =if(H252=5,"27th Jan-2nd Feb", if(H252=6,"3rd Feb-9th Feb", if(H252=7,"10th Feb-16th Feb",if(H252=8,"17th Feb-23rd Feb", if(H252=9,"24th Feb-2nd March",if(H252=10,"3rd March - 9th March"," ")))))) | J252: =if(H252=5,"W1", if(H252=6,"W2", if(H252=7,"W3",if(H252=8,"W4", if(H252=9,"W5",if(H252=10,"W6"," "))))))
A253: =MasterSheet_final!A240 -> 239 | B253: =MasterSheet_final!B240 -> Organization | C253: =MasterSheet_final!C240 -> - To Verify that able to add a parent organization (Test org) - The created organization should associated as a child to (Test org) | D253: =MasterSheet_final!D240 -> Pass | E253: =MasterSheet_final!E240 -> 45797 | F253: =#REF! -> #REF! | G253: =MasterSheet_final!F240 -> Manikandan | H253: =IF(ISBLANK(E253)," ",WEEKNUM(E253,2)) -> 21 | I253: =if(H253=5,"27th Jan-2nd Feb", if(H253=6,"3rd Feb-9th Feb", if(H253=7,"10th Feb-16th Feb",if(H253=8,"17th Feb-23rd Feb", if(H253=9,"24th Feb-2nd March",if(H253=10,"3rd March - 9th March"," ")))))) | J253: =if(H253=5,"W1", if(H253=6,"W2", if(H253=7,"W3",if(H253=8,"W4", if(H253=9,"W5",if(H253=10,"W6"," "))))))
A254: =MasterSheet_final!A241 -> 240 | B254: =MasterSheet_final!B241 -> Organization | C254: =MasterSheet_final!C241 -> To Verify and check when the code convention is off ,should allow to enter the code manually | D254: =MasterSheet_final!D241 -> Pass | E254: =MasterSheet_final!E241 -> 45797 | F254: =#REF! -> #REF! | G254: =MasterSheet_final!F241 -> Manikandan | H254: =IF(ISBLANK(E254)," ",WEEKNUM(E254,2)) -> 21 | I254: =if(H254=5,"27th Jan-2nd Feb", if(H254=6,"3rd Feb-9th Feb", if(H254=7,"10th Feb-16th Feb",if(H254=8,"17th Feb-23rd Feb", if(H254=9,"24th Feb-2nd March",if(H254=10,"3rd March - 9th March"," ")))))) | J254: =if(H254=5,"W1", if(H254=6,"W2", if(H254=7,"W3",if(H254=8,"W4", if(H254=9,"W5",if(H254=10,"W6"," "))))))
A255: =MasterSheet_final!A242 -> 241 | B255: =MasterSheet_final!B242 -> Organization | C255: =MasterSheet_final!C242 -> To Verify and check when the code convention is off , if entered the existing code the following error message should be thrown "Code already Exists". | D255: =MasterSheet_final!D242 -> Pass | E255: =MasterSheet_final!E242 -> 45804 | F255: =#REF! -> #REF! | G255: =MasterSheet_final!F242 -> Manikandan | H255: =IF(ISBLANK(E255)," ",WEEKNUM(E255,2)) -> 22 | I255: =if(H255=5,"27th Jan-2nd Feb", if(H255=6,"3rd Feb-9th Feb", if(H255=7,"10th Feb-16th Feb",if(H255=8,"17th Feb-23rd Feb", if(H255=9,"24th Feb-2nd March",if(H255=10,"3rd March - 9th March"," ")))))) | J255: =if(H255=5,"W1", if(H255=6,"W2", if(H255=7,"W3",if(H255=8,"W4", if(H255=9,"W5",if(H255=10,"W6"," "))))))
A256: =MasterSheet_final!A243 -> 242 | B256: =MasterSheet_final!B243 -> Organization | C256: =MasterSheet_final!C243 -> To Verify and check able to create the same code in multi tenant scenario. | D256: =MasterSheet_final!D243 -> Pass | E256: =MasterSheet_final!E243 -> 45808 | F256: =#REF! -> #REF! | G256: =MasterSheet_final!F243 -> Manikandan | H256: =IF(ISBLANK(E256)," ",WEEKNUM(E256,2)) -> 22 | I256: =if(H256=5,"27th Jan-2nd Feb", if(H256=6,"3rd Feb-9th Feb", if(H256=7,"10th Feb-16th Feb",if(H256=8,"17th Feb-23rd Feb", if(H256=9,"24th Feb-2nd March",if(H256=10,"3rd March - 9th March"," ")))))) | J256: =if(H256=5,"W1", if(H256=6,"W2", if(H256=7,"W3",if(H256=8,"W4", if(H256=9,"W5",if(H256=10,"W6"," "))))))
A257: =MasterSheet_final!A244 -> 243 | B257: =MasterSheet_final!B244 -> Organization | C257: =MasterSheet_final!C244 -> To Verify and check if the code convention is turned ON the code will be auto generated | D257: =MasterSheet_final!D244 -> Pass | E257: =MasterSheet_final!E244 -> 45800 | F257: =#REF! -> #REF! | G257: =MasterSheet_final!F244 -> Manikandan | H257: =IF(ISBLANK(E257)," ",WEEKNUM(E257,2)) -> 21 | I257: =if(H257=5,"27th Jan-2nd Feb", if(H257=6,"3rd Feb-9th Feb", if(H257=7,"10th Feb-16th Feb",if(H257=8,"17th Feb-23rd Feb", if(H257=9,"24th Feb-2nd March",if(H257=10,"3rd March - 9th March"," ")))))) | J257: =if(H257=5,"W1", if(H257=6,"W2", if(H257=7,"W3",if(H257=8,"W4", if(H257=9,"W5",if(H257=10,"W6"," "))))))
A258: =#REF! -> #REF! | B258: =#REF! -> #REF! | C258: =#REF! -> #REF! | D258: =#REF! -> #REF! | E258: =#REF! -> #REF! | F258: =#REF! -> #REF! | G258: =#REF! -> #REF! | H258: =IF(ISBLANK(E258)," ",WEEKNUM(E258,2)) -> #REF! | I258: =if(H258=5,"27th Jan-2nd Feb", if(H258=6,"3rd Feb-9th Feb", if(H258=7,"10th Feb-16th Feb",if(H258=8,"17th Feb-23rd Feb", if(H258=9,"24th Feb-2nd March",if(H258=10,"3rd March - 9th March"," ")))))) -> #REF! | J258: =if(H258=5,"W1", if(H258=6,"W2", if(H258=7,"W3",if(H258=8,"W4", if(H258=9,"W5",if(H258=10,"W6"," ")))))) -> #REF!
A259: =#REF! -> #REF! | B259: =#REF! -> #REF! | C259: =#REF! -> #REF! | D259: =#REF! -> #REF! | E259: =#REF! -> #REF! | F259: =#REF! -> #REF! | G259: =#REF! -> #REF! | H259: =IF(ISBLANK(E259)," ",WEEKNUM(E259,2)) -> #REF! | I259: =if(H259=5,"27th Jan-2nd Feb", if(H259=6,"3rd Feb-9th Feb", if(H259=7,"10th Feb-16th Feb",if(H259=8,"17th Feb-23rd Feb", if(H259=9,"24th Feb-2nd March",if(H259=10,"3rd March - 9th March"," ")))))) -> #REF! | J259: =if(H259=5,"W1", if(H259=6,"W2", if(H259=7,"W3",if(H259=8,"W4", if(H259=9,"W5",if(H259=10,"W6"," ")))))) -> #REF!
A260: =MasterSheet_final!A245 -> 244 | B260: =MasterSheet_final!B245 -> Organization | C260: =MasterSheet_final!C245 -> To Verify and check in parent organization field type 3 letters all the organization will be listed as ascending order | D260: =MasterSheet_final!D245 -> Pass | E260: =MasterSheet_final!E245 -> 45804 | F260: =#REF! -> #REF! | G260: =MasterSheet_final!F245 -> Manikandan | H260: =IF(ISBLANK(E260)," ",WEEKNUM(E260,2)) -> 22 | I260: =if(H260=5,"27th Jan-2nd Feb", if(H260=6,"3rd Feb-9th Feb", if(H260=7,"10th Feb-16th Feb",if(H260=8,"17th Feb-23rd Feb", if(H260=9,"24th Feb-2nd March",if(H260=10,"3rd March - 9th March"," ")))))) | J260: =if(H260=5,"W1", if(H260=6,"W2", if(H260=7,"W3",if(H260=8,"W4", if(H260=9,"W5",if(H260=10,"W6"," "))))))
A261: =MasterSheet_final!A246 -> 245 | B261: =MasterSheet_final!B246 -> Organization | C261: =MasterSheet_final!C246 -> To Verify and check the child organization action icon and active user action will be disabled in creation page when there is no child organisation and active users are not there for the organisation | D261: =MasterSheet_final!D246 -> Pass | E261: =MasterSheet_final!E246 -> 45797 | F261: =#REF! -> #REF! | G261: =MasterSheet_final!F246 -> Manikandan | H261: =IF(ISBLANK(E261)," ",WEEKNUM(E261,2)) -> 21 | I261: =if(H261=5,"27th Jan-2nd Feb", if(H261=6,"3rd Feb-9th Feb", if(H261=7,"10th Feb-16th Feb",if(H261=8,"17th Feb-23rd Feb", if(H261=9,"24th Feb-2nd March",if(H261=10,"3rd March - 9th March"," ")))))) | J261: =if(H261=5,"W1", if(H261=6,"W2", if(H261=7,"W3",if(H261=8,"W4", if(H261=9,"W5",if(H261=10,"W6"," "))))))
A262: =MasterSheet_final!A247 -> 246 | B262: =MasterSheet_final!B247 -> Organization | C262: =MasterSheet_final!C247 -> To Verify admin can delete the child organization without active users | D262: =MasterSheet_final!D247 -> Pass | E262: =MasterSheet_final!E247 -> 45797 | F262: =#REF! -> #REF! | G262: =MasterSheet_final!F247 -> Manikandan | H262: =IF(ISBLANK(E262)," ",WEEKNUM(E262,2)) -> 21 | I262: =if(H262=5,"27th Jan-2nd Feb", if(H262=6,"3rd Feb-9th Feb", if(H262=7,"10th Feb-16th Feb",if(H262=8,"17th Feb-23rd Feb", if(H262=9,"24th Feb-2nd March",if(H262=10,"3rd March - 9th March"," ")))))) | J262: =if(H262=5,"W1", if(H262=6,"W2", if(H262=7,"W3",if(H262=8,"W4", if(H262=9,"W5",if(H262=10,"W6"," "))))))
A263: =MasterSheet_final!A248 -> 247 | B263: =MasterSheet_final!B248 -> Organization | C263: =MasterSheet_final!C248 -> To Verify admin cannot delete the child organization with active users | D263: =MasterSheet_final!D248 -> Pass | E263: =MasterSheet_final!E248 -> 45797 | F263: =#REF! -> #REF! | G263: =MasterSheet_final!F248 -> Manikandan | H263: =IF(ISBLANK(E263)," ",WEEKNUM(E263,2)) -> 21 | I263: =if(H263=5,"27th Jan-2nd Feb", if(H263=6,"3rd Feb-9th Feb", if(H263=7,"10th Feb-16th Feb",if(H263=8,"17th Feb-23rd Feb", if(H263=9,"24th Feb-2nd March",if(H263=10,"3rd March - 9th March"," ")))))) | J263: =if(H263=5,"W1", if(H263=6,"W2", if(H263=7,"W3",if(H263=8,"W4", if(H263=9,"W5",if(H263=10,"W6"," "))))))
A264: =MasterSheet_final!A249 -> 248 | B264: =MasterSheet_final!B249 -> Organization | C264: =MasterSheet_final!C249 -> To Verify and check after deleting the organization the following message needs to be displayed "Name of the organization” has been deleted Successfully". | D264: =MasterSheet_final!D249 -> Pass | E264: =MasterSheet_final!E249 -> 45797 | F264: =#REF! -> #REF! | G264: =MasterSheet_final!F249 -> Manikandan | H264: =IF(ISBLANK(E264)," ",WEEKNUM(E264,2)) -> 21 | I264: =if(H264=5,"27th Jan-2nd Feb", if(H264=6,"3rd Feb-9th Feb", if(H264=7,"10th Feb-16th Feb",if(H264=8,"17th Feb-23rd Feb", if(H264=9,"24th Feb-2nd March",if(H264=10,"3rd March - 9th March"," ")))))) | J264: =if(H264=5,"W1", if(H264=6,"W2", if(H264=7,"W3",if(H264=8,"W4", if(H264=9,"W5",if(H264=10,"W6"," "))))))
...

Sheet Pivot Table 6

Sheet Dashboard
Z2: =Y2/$AG$2 -> 0 | AH2: =AG2-R7 -> 4698
Y3: =if(isblank(X3), $AF$1,X3+Y2) | Z3: =if(isblank(Y3),"",Y3/$AG$2)
Y4: =if(isblank(X4), $AF$1,X4+Y3) | Z4: =if(isblank(Y4),"",Y4/$AG$2)
Y5: =if(isblank(X5), $AF$1,X5+Y4) | Z5: =if(isblank(Y5),"",Y5/$AG$2)
Y6: =if(isblank(X6), $AF$1,X6+Y5) | Z6: =if(isblank(Y6),"",Y6/$AG$2)
Y7: =if(isblank(X7), $AF$1,X7+Y6) | Z7: =if(isblank(Y7),"",Y7/$AG$2)
Y8: =if(isblank(X8), $AF$1,X8+Y7) | Z8: =if(isblank(Y8),"",Y8/$AG$2)
Y9: =if(isblank(X9), $AF$1,X9+Y8) | Z9: =if(isblank(Y9),"",Y9/$AG$2)
Y10: =if(isblank(X10), $AF$1,X10+Y9) | Z10: =if(isblank(Y10),"",Y10/$AG$2)
Y11: =if(isblank(X11), $AF$1,X11+Y10) | Z11: =if(isblank(Y11),"",Y11/$AG$2)
Y12: =if(isblank(X12), $AF$1,X12+Y11) | Z12: =if(isblank(Y12),"",Y12/$AG$2)
Y13: =if(isblank(X13), $AF$1,X13+Y12) | Z13: =if(isblank(Y13),"",Y13/$AG$2)
Y14: =if(isblank(X14), $AF$1,X14+Y13) | Z14: =if(isblank(Y14),"",Y14/$AG$2)
... Y17: =if(isblank(X17), $AF$1,X17+Y16) | Z17: =if(isblank(Y17),"",Y17/$AG$2)
Y18: =if(isblank(W18), $AF$1,Y18+Y17)

Sheet MasterSheet_final
A1: S No | B1: Module | C1: Scenario | D1: Status | E1: Executed on | F1: Resource | G1: Jira Ticket#
A2: 1 | B2: Tenant creation | C2: Verify that able to create a new tenant for Lite, Mid and Complex editions | D2: Pass | E2: 45801 | F2: Nithya
A3: 2 | B3: Tenant creation | C3: Verify that able to login into the new tenant | D3: Pass | E3: 45801 | F3: Nithya
A4: 3 | B4: Tenant creation | C4: Verify that data from existing tenant should not be visible in the new tenant | D4: Pass | E4: 45801 | F4: Nithya
A5: 4 | B5: Tenant creation | C5: Verify all the modules are visible in the newly created tenants | D5: Pass | E5: 45801 | F5: Nithya
A6: 5 | B6: Tenant creation | C6: Verify that the default learner portal is created for the newly created tenants | D6: Pass | E6: 45801 | F6: Nithya
A7: 6 | B7: Portal creation | C7: Verify that able to create a new portal to the tenant | D7: Pass | E7: 45801 | F7: Nithya
A8: 7 | B8: Portal creation | C8: Verifty that able to login into the newly created portal | D8: Pass | E8: 45801 | F8: Nithya
A9: 8 | B9: Portal creation | C9: Verify that able to create template to the newly created portal | D9: Pass | E9: 45801 | F9: Nithya
A10: 9 | B10: Portal creation | C10: Verify that a default portal is created automatically while creating a new portal | D10: Pass | E10: 45801 | F10: Nithya
A11: 10 | B11: Portal creation | C11: Verify that able to create multiple template to the single portal | D11: Pass | E11: 45801 | F11: Nithya
A12: 11 | B12: Portal creation | C12: Verify that able to set only one default template to the the portal | D12: Pass | E12: 45801 | F12: Nithya
A13: 12 | B13: Portal creation | C13: Verify that multiple portals can be created in the tenant with same portal url but domain name should be different | D13: Pass | E13: 45801 | F13: Nithya
... A264: 263 | B264: Organization | C264: To Verify that admin can able to export the child organizations | D264: Pass | E264: 45798 | F264: Manikandan
A265: 264 | B265: Organization | C265: To Verify the export sheet contains Name, User Name, Email ID, Job Title, User Type, Manager Name, Association Type, added on | D265: Pass | E265: 45798
A266: 265 | B266: Organization | C266: To Verify that the child organization action is disabled when the count is zero | D266: Pass | E266: 45798 | F266: Manikandan
A267: 266 | B267: Organization | C267: To Verify the association type shows whether it is mapped with primary or other organization | D267: Pass | E267: 45800 | F267: Manikandan
A268: 267 | B268: Organization | C268: To Verify the suspend icon is available for the who has edit permission | D268: Pass | E268: 45797 | F268: Manikandan
A269: 268 | B269: Organization | C269: -To Verify suspend an organization which has active users -Will display message Suspending the organization will remove all users associated with it, would you like to proceed? | D269: Pass | E269: 45798 | F269: Manikandan
A270: 269 | B270: Organization | C270: -To Verify click yes on suspend alert popup box - The users should get unmapped | D270: Pass | E270: 45797 | F270: Manikandan
A271: 270 | B271: Organization | C271: -To Verify suspend an organization which has child organizations -Will display message Suspending the parent organization will make its associated child organization to will move one level higher, would you like to proceed? | D271: Pass | E271: 45797 | F271: Manikandan
A272: 271 | B272: Organization | C272: -To Verify suspend an organization which has child organizations -The child organization will be moved on one level up | D272: Pass | E272: 45797 | F272: Manikandan
A273: 272 | B273: Organization | C273: To Verify the created organizations are not listing in other Tenant which is not having access | D273: Pass | E273: 45811 | F273: Manikandan
A274: 273 | B274: Organization | C274: To Verify that update button should not be enabled in edit page untill the admin edits it | D274: Pass | E274: 45804 | F274: Manikandan
A275: 274 | B275: Organization | C275: To Verify that discard button should not be enabled in edit page untill the admin edits it | D275: Pass | E275: 45797 | F275: Manikandan
A276: 275 | B276: Organization | C276: To Verify that save button will be enabled only if all the mandatory fields are filled. | D276: Pass | E276: 45797 | F276: Manikandan
A277: 276 | B277: Organization | C277: "-To Verify after clicking save the access pop up box should get opened with the message -This organization will be assigned to 'All Learners' group and the admin groups that you're part of. Please validate your decision. - And Yes, proceed and No, modify the access buttons should be listed in the pop up box" | D277: Pass | E277: 45797 | F277: Manikandan
... A417: 416 | B417: User | C417: Verify that user should be landed in Collaboration hub page when having both instructor and Manager role | D417: Pass | E417: 45800 | F417: Manikandan
A418: 417 | C418: Verify that user should be landed in Admin page when having admin access alone and also with instructor and Manager role | D418: Pass | E418: 45800 | F418: Manikandan
A419: 418 | B419: User | C419: Verify that uploaded profile image is showing in Learner and Admin side after user logged in | D419: Pass | E419: 45800 | F419: Manikandan
A420: 419 | B420: User | C420: Verify that Associated Learner and Admin groups are showing correctly for which the user is part of domain | D420: Pass | E420: 45812 | F420: Manikandan
A421: 420 | B421: User | C421: Verify that One profile link is generated successfully after the user is created | D421: Pass | E421: 45800 | F421: Manikandan
A422: 421 | B422: User | C422: Verify that able to view the One profile summary page with the generated link | D422: Pass | E422: 45800 | F422: Manikandan
A423: 422 | B423: User | C423: Verify that the Custom fields can be added in to the user page as Mandatory and Non-mandatory | D423: Pass | E423: 45801 | F423: Manikandan
A424: 423 | B424: User | C424: Verify that could not able to save or update the user unless the Mandatory custom field is filled | D424: Pass | E424: 45801 | F424: Manikandan
A425: 424 | B425: User | C425: Verify that if only the admin who has access to the user is able to view or edit that user. | D425: Pass | E425: 45800 | F425: Manikandan
A426: 425 | B426: User | C426: Verify that suspended users cannot able to login | D426: Pass | E426: 45800 | F426: Manikandan
A427: 426 | B427: User | C427: Verify that could not able to remove the instructor role when the user is having upcoming ILT / VC classess | D427: Pass | E427: 45800 | F427: Manikandan
A428: 427 | B428: User | C428: Verify that able to add direct and other Manager to the user | D428: Pass | E428: 45800 | F428: Manikandan
A429: 428 | B429: User | C429: Verify that should not able to add the direct Manager as other Manager | D429: Pass | E429: 45800 | F429: Manikandan
A430: 429 | B430: User | C430: Verify that user enrollments are showing correctly while clicking on Enrollments | D430: Pass | E430: 45800 | F430: Manikandan
... A461: 460 | B461: User | C461: Verify and check the hire date by default it should be highlighted as present date and can be select any past,present and future dates with the Format: MM/DD/YYYY | D461: Pass | E461: 45805 | F461: Manikandan
A462: 461 | B462: User | C462: Verify and check for the instructor role user the Webex username and WebEx password field will be visible. | D462: Unable to test | F462: Manikandan
A463: 462 | B463: User | C463: Verify and check for the manger role the Webex username field and WebEx password will be Hidden. | D463: Unable to test | F463: Manikandan
A464: 463 | B464: User | C464: Verify and check the Salesforce orginization ID will be visible when the salesforce is enabled and Sync User Enollements Level is selected as User | D464: Unable to test | F464: Manikandan
A465: 464 | B465: User | C465: Verify and check the Salesforce orginization ID will not be visible when the salesforce is enabled and Sync User Enollements Level is selected as organization | D465: Unable to test | F465: Manikandan
A466: 465 | B466: User | C466: Verify and check the Salesforce user sync unable to edit , If the admin selects a salesforce organization id from the drop down, this checkbox will be selected | D466: Unable to test | F466: Manikandan
A467: 466 | B467: User | C467: Verify and check the supported profile picture format can upload" SVG, JPEG, PNG, or JPG". | D467: Pass | E467: 45811 | F467: Manikandan
A468: 467 | B468: User | C468: Verify and check if uploaded unsupported profile picture format the following warning message should be thrown "The uploaded picture is not in the specified format. Please reupload the picture.". | D468: Pass | E468: 45811 | F468: Manikandan
A469: 468 | B469: User | C469: Verify and check after clicking on discard button, they will be redirected to the listing page. | D469: Pass | E469: 45800 | F469: Manikandan
A470: 469 | B470: User | C470: Verify and check based on the selected organization, the portal name field will be auto updated | D470: Pass | E470: 45803 | F470: Manikandan
A471: 470 | B471: User | C471: Verify and check based on the selected organization, the portal name field will be auto updated and can be modifiable(add/remove the portals) | D471: Pass | E471: 45803 | F471: Manikandan
A472: 471 | B472: User | C472: Verify and check clicking on the copy icon will copy the One-profile URL of the specific learner and that link should work in new tab | D472: Pass | E472: 45800 | F472: Manikandan
A473: 472 | B473: User | C473: Verify and check if more than 10 associated groups are attached the scroll bar should be display. | D473: Pass | E473: 45800 | F473: Manikandan
A474: 473 | B474: Login Page | C474: Verify user able to login into admin and learner site | D474: Pass | E474: 45800 | F474: Manikandan
A475: 474 | B475: Login Page | C475: Verify error message validation without entering the username/password/Captcha | D475: Pass | E475: 45800 | F475: Manikandan
A476: 475 | B476: Login Page | C476: Verify that Admin/Learner User able to login by entering following mandatory fields username ,password and captcha | D476: Pass | E476: 45800 | F476: Manikandan
A477: 476 | B477: Login Page | C477: Verify error message validation without entering the username | D477: Pass | E477: 45800 | F477: Manikandan
A478: 477 | B478: Login Page | C478: Verify error message validation without entering the password | D478: Pass | E478: 45800 | F478: Manikandan
... A963: 962 | B963: Colloboration Hub | C963: Verify whether the Load More Functionality is working correctly | D963: Pass | E963: 45808 | F963: Tamil
A964: 963 | B964: Colloboration Hub | C964: Verify whether the Certification Readiness graph is displaying the results correctly | D964: Unable to test | F964: Tamil
A965: 964 | B965: Colloboration Hub | C965: Verify whether the Certification not MET is displaying the results correctly | D965: Pass | E965: 45808 | F965: Tamil
A966: 965 | B966: Colloboration Hub | C966: Verify whether the Learning Progress - By Team Members is displaying the results correctly | D966: Pass | E966: 45808 | F966: Tamil
A967: 966 | B967: Colloboration Hub | C967: Verify whether the Learning History is getting opened when we click on View Learning | D967: Pass | E967: 45808 | F967: Tamil
A968: 967 | B968: Colloboration Hub | C968: Verify whether the MeetNow opens the meeting with the Subordinate | D968: Unable to test | F968: Tamil
A969: 968 | B969: Colloboration Hub | C969: Verify whether the Leaderboard displays the user points badges and Completions correctly | D969: Unable to test | F969: Tamil
A970: 969 | B970: Colloboration Hub | C970: Verify whether the Search and Filter is working correctly in My Team Section | D970: Pass | E970: 45810 | F970: Tamil
A971: 970 | B971: Colloboration Hub | C971: Verify whether the Search is working correctly in the LeaderBoard | D971: Unable to test | F971: Tamil
A972: 971 | B972: Assessment | C972: Verify the Admin able to create Assessment and check its getting displayed with respective tabs like Draft,Published and Unpublished tabs | D972: Pass | E972: 45797 | F972: Anuradha
A973: 972 | B973: Assessment | C973: Verify the admin able to create assessment with question creation on the fly | D973: Pass | E973: 45797 | F973: Anuradha
A974: 973 | B974: Assessment | C974: Verify whether the textbox are marked as red color when the mandatory fields are not filled | D974: Pass | E974: 45797 | F974: Anuradha
A975: 974 | B975: Assessment | C975: Verify the admin able to create assessment and try to add questions using import question | D975: Pass | E975: 45797 | F975: Anuradha
A976: 975 | B976: Assessment | C976: Verify the admin able to create assessment with question creation with sections | D976: Pass | E976: 45797 | F976: Anuradha
A977: 976 | B977: Assessment | C977: Verify the admin able to create assessment with question creation on the fly,check created questions are displayed in question list page | D977: Pass | E977: 45797 | F977: Anuradha
A978: 977 | B978: Assessment | C978: Verify that the Custom Admin user has the ability to publish and unpublish the assessment. | D978: Pass | E978: 45797 | F978: Anuradha
A979: 978 | B979: Assessment | C979: Verify the admin able to view the associated trainings will be displayed in listing page(assessment will be associated with Course/Training Plan) | D979: Pass | E979: 45797 | F979: Anuradha
A980: 979 | B980: Assessment | C980: Verify the admin will not allow to delete the questions which is associated with assessment | D980: Pass | E980: 45797 | F980: Anuradha
A981: 980 | B981: Assessment | C981: Verify the admin able to clone the assessment | D981: Pass | E981: 45797 | F981: Anuradha
A982: 981 | B982: Assessment | C982: Verify the admin able to clone the sections | D982: Pass | E982: 45797 | F982: Anuradha
A983: 982 | B983: Assessment | C983: Verify able to clone the assessment multiple times | D983: Pass | E983: 45797 | F983: Anuradha
... A1000: 999 | B1000: Assessment | C1000: Verify the Assessment attempt will be displayed in course and tp edit page when admin attached the assessment with attempt set | D1000: Pass | E1000: 45797 | F1000: Anuradha
A1001: 1000 | B1001: Assessment | C1001: Verify the Assessment passing score in learner side,Admin created assessment with passs percentage as 50 and No. Of Questions To Display as 4 Questions: q1-20 score q2-20 score q3-20 score q4-20 score q5-20 score q6-20 score Admin created course then attach this assessment Admin created TP then attach this assessment Course: case1:Verify the learner enrolled the course and launch the assessment then completed two questions correctly,check assessment score getting displayed in completion certification case2:Verify the learner enrolled the course and launch the assessment then completed two questions correctly,check assessment score getting displayed in admin enrollment page case3:Verify the learner enrolled the course and launch the assessment then completed all questions incorrectly,check learner will be moved enrolled to incomplete status due to assessment failed case4:Verify the learner page only 4 questions are getting displayed in the assessment under course Case5:Verify the no of question to display at the section level TP: case1:Verify the learner enrolled the TP and launch the assessment then completed two questions correctly,check assessment score getting displayed in completion certification case2:Verify the learner enrolled the TP and launch the assessment then completed two questions correctly,check assessment score getting displayed in admin enrollment page case3:Verify the learner enrolled the TP and launch the assessment then completed all questions incorrectly,check learner will be moved enrolled to incomplete status due to assessment failed case4:Verify the learner page only 4 questions are getting displayed in the assessment under course Case5:Verify the no of question to display at the section level | D1001: Fail | E1001: 45798 | F1001: Anuradha | G1001: IRIS-3860
A1002: 1001 | B1002: Assessment | C1002: Verify the assessment for course if set required for attached questions under assessment in learner side | D1002: Pass | E1002: 45797 | F1002: Anuradha
A1003: 1002 | B1003: Assessment | C1003: Verify whether the Change Log is getting captured for any action in the Creation and Updation page Assessment page | D1003: Pass | E1003: 45797 | F1003: Anuradha
A1004: 1003 | B1004: Assessment | C1004: Verify that the value in the number of questions field does not exceed the total number of questions in the assessment. | D1004: Pass | E1004: 45797 | F1004: Anuradha
A1005: 1004 | B1005: Assessment | C1005: Verify that all questions in the assessment are used when no value is specified in the number of questions field, and no validation is necessary. | D1005: Pass | E1005: 45797 | F1005: Anuradha
A1006: 1005 | B1006: Assessment | C1006: Verify validation of the number of questions specified by the admin against total and required questions in the assessment. If the specified value exceeds the total number of questions, an error message is displayed: "The number of questions cannot exceed the total number of questions in the assessment." If the specified value is less than the total number of required questions, an error message is displayed: "The number of questions cannot be less than the total number of required questions." If the specified value is between the total number of questions and the total number of required questions, the assessment is saved or published successfully. | D1006: Pass | E1006: 45813 | F1006: Anuradha
A1007: 1006 | B1007: Assessment | C1007: Verify if the admin has not provided a value in the number of questions field. In this scenario, the following error message should be displayed, insisting the admin provide a value: "The number of questions to be displayed cannot be less than the total required questions." | D1007: Pass | E1007: 45813 | F1007: Anuradha
A1008: 1007 | B1008: Assessment | C1008: Verify that the "Number of questions to be displayed at the assessment level" field will be greyed out as soon as the admin creates a section. | D1008: Pass | E1008: 45813 | F1008: Anuradha
A1009: 1008 | B1009: Assessment | C1009: Verify that if the admin provides the number of questions for one section, it is mandatory to provide the number of questions for all sections. | D1009: Pass | E1009: 45813 | F1009: Anuradha
A1010: 1009 | B1010: Assessment | C1010: Verify that the total of all the values provided in the number of questions per section is displayed as the "number of questions" to be displayed at the assessment level. | D1010: Pass | E1010: 45813 | F1010: Anuradha
A1011: 1010 | B1011: Assessment | C1011: Verify that when questions are marked as required in each section, the number of required questions is automatically captured in the "Number of questions per section" field. | D1011: Pass | E1011: 45813 | F1011: Anuradha
A1012: 1011 | B1012: Assessment | C1012: Verify that when the admin manually enters the value for the "number of questions per section," and there are required questions, the admin will not be allowed to provide a value that is less than or greater than the specified required value. | D1012: Pass | E1012: 45813 | F1012: Anuradha
A1013: 1012 | B1013: Assessment | C1013: Verify that when no values are entered in the "Number of questions" field for the sections, all questions in those sections are considered for the assessment. | D1013: Pass | E1013: 45813 | F1013: Anuradha
... A1100: 1099 | B1100: Content | C1100: Verify whether able to preview the content from the edit content page and content listing page for the versioned content Verify preview for all the below content types - AICC - TINCAN - Scorm (scrom 2004, scorm1.2, multi-scorm, scorm from cloud, pink-elephant) - url (YouTube, Vimeo, Hosted mp4, or Brightcove, AICC, SCORM 2004, SCORM 1.2) - pdf - ppt (PPS, PPSX, PPT, PPTX) - Doc (DOC, DOCX, TXT) - Excel (XLS, XLSX) - audio (MP3 extension, ACC, M4A) - Image (JPEG, JPG, PNG) - video (MP4 extension, WEBM, MOV) | D1100: Pass | E1100: 45811 | F1100: Anuradha
A1101: 1100 | B1101: Content | C1101: Verify whether the content version notification is triggred to the learners when new version is created | D1101: Fail | E1101: 45811 | F1101: Anuradha | G1101: EAT1-1011
A1102: 1101 | B1102: Content | C1102: Verify the version history is displayed in the edit content page once the versions are created. It should be in non-editable mode for published content | D1102: Pass | E1102: 45811 | F1102: Anuradha
A1103: 1102 | B1103: Content | C1103: Verify the version history is displayed in the edit content page once the versions are created. It should be in editable mode for drafted content | D1103: Pass | E1103: 45811 | F1103: Anuradha
A1104: 1103 | B1104: Content | C1104: Verify whether content is versioned for the respective attached course in learner side (cron job) | D1104: Pass | E1104: 45811 | F1104: Anuradha
A1105: 1104 | B1105: Content | C1105: Verfiy whether transfer learner to other version button is enabled only when Content is associated to the class, Learners are enrolled in the class and Content has more than one version | D1105: Pass | E1105: 45811 | F1105: Anuradha
...

Sheet TO_do
A1: S No | B1: Module | C1: Scenario | D1: Status | E1: Executed on | F1: Resource | G1: Jira Ticket#
A2: 1 | B2: Tenant creation | C2: Verify that able to create a new tenant for Lite, Mid and Complex editions
A3: 2 | B3: Tenant creation | C3: Verify that able to login into the new tenant
A4: 3 | B4: Tenant creation | C4: Verify that data from existing tenant should not be visible in the new tenant
A5: 4 | B5: Tenant creation | C5: Verify all the modules are visible in the newly created tenants
A6: 5 | B6: Tenant creation | C6: Verify that the default learner portal is created for the newly created tenants
A7: 6 | B7: Portal creation | C7: Verify that able to create a new portal to the tenant
A8: 7 | B8: Portal creation | C8: Verifty that able to login into the newly created portal
A9: 8 | B9: Portal creation | C9: Verify that able to create template to the newly created portal
A10: 9 | B10: Portal creation | C10: Verify that a default portal is created automatically while creating a new portal
A11: 10 | B11: Portal creation | C11: Verify that able to create multiple template to the single portal
A12: 11 | B12: Portal creation | C12: Verify that able to set only one default template to the the portal
A13: 12 | B13: Portal creation | C13: Verify that multiple portals can be created in the tenant with same portal url but domain name should be different
... A26: 25 | B26: Portal creation | C26: Verify that the created portals are showing in the switch portal section of Admin home page and learner home page
A27: 26 | B27: Admin Role | C27: Verify able to create a admin role with all the privilages | D27: Pass | E27: 45941
A28: 27 | B28: Admin Role | C28: Verify the search functionality is working correctly | D28: Pass | E28: 45941
A29: 28 | B29: Admin Role | C29: Verify whether we can edit a admin Role | D29: Pass | E29: 45941
A30: 29 | B30: Admin Role | C30: Verify whether we can delete admin Role it is not mapped to any entity | D30: Pass | E30: 45941
A31: 30 | B31: Admin Role | C31: Verify whether the deleted roles are not listing in the List page | D31: Pass | E31: 45941
A32: 31 | B32: Admin Role | C32: Verify whether we cannot delete admin Role it is mapped to any entity | D32: Pass | E32: 45941
A33: 32 | B33: Admin Role | C33: Verify whether all the modules are displayed when we click on Privilage icon | D33: Pass | E33: 45941
A34: 33 | B34: Admin Role | C34: Verify whether name of the admin role acts as a mandatory field | D34: Pass | E34: 45941
A35: 34 | B35: Admin Role | C35: Verify while clicking on Delete privilage for any module will enable View, Create and Edit | D35: Pass | E35: 45941
A36: 35 | B36: Admin Role | C36: Verify whether the Admin Role created in one tenant is not visible in another tenant | D36: Pass | E36: 45941
A37: 36 | B37: Admin Role | C37: Verify whether the Sort function is working correctly | D37: Pass | E37: 45941
A38: 37 | B38: Admin Role | C38: Verify whether the Export function is working correctly (Export as CSV, PDF and Excel) | D38: Pass | E38: 45941
... A44: 43 | B44: Admin Role | C44: Verify whether the Edit and delete icon is in disabled state for Custom Admin Role | D44: Pass | E44: 45941
A45: 44 | B45: Admin Role | C45: Verify whether the Save and Close button works correctly | D45: Pass
A46: 45 | B46: Admin Role | C46: Verify whether we can edit the privilages for the Admin role created by Customer | D46: Pass
A47: 46 | B47: Admin Role | C47: Verify whether it does not allow to edit a default admin role (E1 Super Admin) | D47: Pass
A48: 47 | B48: Admin Role | C48: Verify whether we can able to view a module when the view permission is only given | D48: Pass
A49: 48 | B49: Admin Role | C49: Verify whether we can able to Create and View a module when the Create and view permission is only given | D49: Pass
A50: 49 | B50: Admin Role | C50: Verify whether we can able to Create, view, edit a module when the Create, view, edit permission is only given | D50: Pass
A51: 50 | B51: Admin Role | C51: Verify whether we can able to Create, edit , view,delete a module when the delete permission is given | D51: Pass
A52: 51 | B52: Admin Role | C52: Verify for the following scenerio for all the module privileges - User 1 is attached to a admin group1 and the role privilage is Course Create - User 1 is also a part of admin group2 which has Course Create and Edit privilages - When we login as user 1 we can able to Create and Edit couse | D52: Pass
A53: 52 | B53: Admin Role | C53: Verify whether the Survey module is displayed in all the Creation page when Learing Module - Enable Survey module - Disable | D53: Pass
A54: 53 | B54: Admin Role | C54: Verify whether the Assessment module is displayed in all the Creation page when Learing Module - Enable Assessment module - Disable | D54: Pass
A55: 54 | B55: Admin Role | C55: Verify whether the Skills module is displayed in all the Creation page when Learing Module - Enable Skills module - Disable | D55: Pass
A56: 55 | B56: Admin Role | C56: Verify whether the Observation Checklist module is displayed in all the Creation page when Learing Module - Enable OJT module - Disable | D56: Pass
... A58: 57 | B58: Admin Role | C58: Verify whether the Discussion module is displayed in all the Creation page when Learing Module - Enable Discussion module - Disable | D58: Pass
A59: 58 | B59: Admin Role | C59: Verify whether the CEU module is displayed in all the Creation page when Learing Module - Enable CEU module - Disable
A60: 59 | B60: Admin Role | C60: Verify whether the warning message is getting displayed when we click on the delete button when the Admin Role is assigned to any Admin Group
A61: 60 | B61: Admin Role | C61: Verify the user created with the specific admin role, login as created user Ensure user is given privilages for which the admin based on the specific role. Reports - Pass Manage - Inprogress
A62: 61 | B62: Admin Role | C62: Verify the user created with the Course admin role, Attach it to the Admin Group Attach the user to the Admin Group While logging in only the Course Privileges should be displayed
A63: 62 | B63: Admin Role | C63: Verify the user created with the Training Plan admin role, login as created user
A64: 63 | B64: Admin Role | C64: Verify the user created with the Content admin role, login as created user
A65: 64 | B65: Admin Role | C65: Verify the user created with the Dynamic Sharable Link admin role, login as created user
A66: 65 | B66: Admin Role | C66: Verify the user created with the Learning Assignment admin role, login as created user
A67: 66 | B67: Admin Role | C67: Verify the user created with the Assessment admin role, login as created user
A68: 67 | B68: Admin Role | C68: Verify the user created with the Assessment Questions admin role, login as created user
A69: 68 | B69: Admin Role | C69: Verify by keeping Assessment Question privilege alone to a Admin Role Create Assessment should not be displayed in the Assessment Listing page
A70: 69 | B70: Admin Role | C70: Verify by keeping Survey Question privilege alone to a Admin Role Create Survey should not be displayed in the Survey Listing page
... A93: 92 | B93: Admin Role | C93: Verify the Creation,updation of all the modules after creating a admin role and logging in as a user
A94: 93 | B94: Admin Group | C94: Verify whether we can able to create a Admin Group | D94: Pass
A95: 94 | B95: Admin Group | C95: Verify whether the Title for the Admin Group is unique
A96: 95 | B96: Admin Group | C96: Verify whether we can search for a user based on Username and Name
A97: 96 | B97: Admin Group | C97: Verify whether the users selected is getting added to the Added users section
A98: 97 | B98: Admin Group | C98: Verify whether the Activate, Save as draft buttons are working correctly
A99: 98 | B99: Admin Group | C99: Verify whether the Save and Discard buttons are working correctly
A100: 99 | B100: Admin Group | C100: Verify whether we can suspend a admin group | D100: Pass
A101: 100 | B101: Admin Group | C101: Verify whether we can edit a admin group | D101: Pass
A102: 101 | B102: Admin Group | C102: Verify whether we can activate a admin group | D102: Pass
A103: 102 | B103: Admin Group | C103: Verify only active users can be added to the admin group
A104: 103 | B104: Admin Group | C104: Verify whether the Deleted users are not getting displayed in Added users
A105: 104 | B105: Admin Group | C105: Verify whether the suspended users is not getting displayed in the Select Users section of Admin Group
A106: 105 | B106: Admin Group | C106: Verify whethert the deleted users is not getting displayed in the Select Users section of Admin Group
A107: 106 | B107: Admin Group | C107: Verify whether the users gets removed from the Admin Group when the user gets suspended or deleted
A108: 107 | B108: Admin Group | C108: Verify whether the results are getting fetched correctly while searching the user based on Name, User Name
A109: 108 | B109: Admin Group | C109: Verify whether the Already added users are not getting displayed in Select users
A110: 109 | B110: Admin Group | C110: Verify whether the admin can suspend admin group when it is attached to any entity but cannot delete the admin group
A111: 110 | B111: Admin Group | C111: Verify whether the users added to the admin group acts as the privilages given in the admin group
A112: 111 | B112: Admin Group | C112: Verify whether admin group created in one portal is not getting displayed in the another portal
A113: 112 | B113: Admin Group | C113: Verify whether the entity which is not having the portal access the admin group should not be displayed
A114: 113 | B114: Admin Group | C114: Verify that the admin able to create Admin Group for only Mid and Complex edition
... A138: 137 | B138: Admin Group | C138: Verify whether it does not allow to suspend a default admin Group(For eg : Super Admin E1 )
A139: 138 | B139: Admin Group | C139: Verify whether it allows to suspend the Admin Group created by Customer | D139: Pass
A140: 139 | B140: Admin Group | C140: part of two groups(people and enrollment) remove the admin group then the privilege should get display
A141: 140 | B141: Admin Group | C141: Verify whether the Access button is in disabled state for Suspended Admin Group
A142: 141 | B142: Admin Group | C142: Verify whether the Code is autogenerated correctly when we enable the Code Convention
A143: 142 | B143: Admin Group | C143: Verify whether we cannot delete the Default Admin Groups
A144: 143 | B144: Admin Group | C144: Verify whether we can Create,Edit,Activate and Suspend a Admin Group as a Custom Admin user
A145: 144 | B145: Admin Group | C145: Verify whether the Admin group Access is set to the created Group based on the Logged in user
A146: 145 | B146: Admin Group | C146: Verify whether the Admin Group goes to unpublished state after the Valid till Date
A147: 146 | B147: Learner Group | C147: Verify that the admin able to access the Learner Group Create/Edit option from Quick Access
A148: 147 | B148: Learner Group | C148: Verify that the admin able to access the Learner Group under People module from toggle menu
A149: 148 | B149: Learner Group | C149: Verify that the below listed details will be displayed when admin click create learner group -Title -Code -Valid till -Attributes -Include learners and exclude learners
A150: 149 | B150: Learner Group | C150: Verify that admin able to create Learner Group -Create a New Role "Common Role" and Create a new admin group "Common Admin group" with role as "Common Role" -Manually add "Prabaadmin" user then login into admin site -Create a learner group
A151: 150 | B151: Learner Group | C151: Verify whether we can able to Create/Update/Activate/Suspend a Learner Group as a Custom Admin user
... A401: 400 | B401: Metadata people - All sections | C401: Verify and check the clicking delete icon the following message needs to be displayed“Are you sure you want to delete the object name".
A402: 401 | B402: User | C402: Verify that able to create a user with all the fields | D402: Pass
A403: 402 | B403: User | C403: Verify that able to create a user with instructor role alone | D403: Pass
A404: 403 | B404: User | C404: Verify that able to create a user with Manager role alone | D404: Pass
A405: 404 | B405: User | C405: Verity that able to create a user with Instructor and Manager role | D405: Pass
A406: 405 | B406: User | C406: Verify that should not able to create a user with no domain | D406: Pass
A407: 406 | B407: User | C407: Verify that able to login as a created user in Learner side | D407: Pass
A408: 407 | B408: User | C408: Verify that you should not be able to assign a suspended user as a Manager to user | D408: Pass
A409: 408 | B409: User | C409: Verify that you should not be able to assign a suspended user as a Instructor to a class | D409: Pass
A410: 409 | B410: User | C410: Verify that able to login as a created user in Admin side when the user is having admin access
A411: 410 | B411: User | C411: Verify that should not able to create same user in different domain | D411: Pass
A412: 411 | B412: User | C412: Verify that able to login in different domain where the user is having access | D412: Pass
...

Sheet Sheet43
A1: 4982
D2: High | E2: Medium | F2: Low
A3: 38 | B3: Failed | C3: =A3/A1 -> 0.0076274589 | D3: 0 | E3: 0.0025 | F3: 0.005
D4: 0 | E4: =E3*A1 -> 12.455 | F4: =F3*A1 -> 24.91
A5: 4944 | B5: Passed

Sheet Reports
A1: Survey Report | B1: Verify that the course displays in the Training Title section after completing the survey.
B2: Verify that when dates are selected but start and end times are not entered, the "Generate Report" button remains disabled.
B3: Verify that users are displayed based on the selected date and Time.
B4: Verify the export functionality of the report(e.g., CSV, Excel, PDF)
B5: Verify that the "Generate Report" button is enabled without entering the start date and end date.
B6: When a date is selected, the "Generate Report" button should remain disabled unless both the start and end times are filled.
B7: Verify that past and future ILT, VC, and E-learning sessions,after adding a survey and completion criteria, are able to generate reports.
A8: Assessment Report | B8: Verify that the course displays in the Training Title section after completing the Assessment.
B9: Verify that when dates are selected but start and end times are not entered, the "Generate Report" button remains disabled.
B10: Verify that users are displayed based on the selected date and Time.
B11: Verify the export functionality of the report(e.g., CSV, Excel, PDF).
B12: Verify that the "Generate Report" button is enabled without entering the start date and end date.
B13: When a date is selected, the "Generate Report" button should remain disabled unless both the start and end times are filled.
B14: Verify that past and future ILT, VC, and E-learning sessions,after adding a Assessment and completion criteria, are able to generate reports.

Sheet Agile_pivot
A1: #REF! | Y1: #REF! | AM1: #REF!
T2: Status
S3: Executed on | T3: Fail | U3: Hold | V3: Pass
S4: 45684 | T4: 23 | U4: 1 | V4: 49
S5: 45685 | T5: 15 | U5: 1 | V5: 61

Sheet Merge_Tickets_17.9
A1: Ticket No | B1: Summary | C1: Assignee | D1: Reporter | E1: Validated by | F1: Status | G1: Comments | H1: QA Resource | I1: Trunk Status | K1: Trunk Comments
A2: IRIS-3826 | B2: Dashboard>>Issues in Learner Playlist section | C2: Santhosh Phadmanabhan | D2: Selvakumar | E2: Selvakumar | F2: Pass | H2: Selva
A3: IRIS-4071 | B3: When cloning ILT classes in bulk, after checking for conflicts and clicking the 'Save' button, no success message is displayed, even though the classes are successfully cloned | C3: Divyasree TK | D3: Vijayaraja S | F3: Pass | H3: Nithya
A4: IRIS-4121 | B4: Learner >> Interaction studio >> Click here cannot redirect to Next Tab | C4: Subin Rajan | D4: Pragatheeshwaran V | H4: NA
A5: IRIS-4118 | B5: Interaction Studio->The H5P content created is not appearing on the Iris content page. | C5: Subin Rajan | D5: Arivazhagan Pachamuthu | E5: Arivazhagan Pachamuthu | F5: Pass | H5: NA
A6: IRIS-4220 | B6: Organisation Export result issue | C6: Manideep kumar | D6: Rajeshwari M | H6: Nithya
A7: IRIS-4168 | B7: Build 22.17 Issues - Learning path creation success message is incorrect. | C7: Archana G | D7: Archana G | E7: Sudha | F7: Partial | G7: Publishing the priced LP still displays the same message "Changing the price will impact the order and cancellation. Details update successfully" | H7: Duplicate
A8: IRIS-4161 | B8: Build 22.17 Issues - When you add a content while creating a course and then delete it , the page redirects to content listing page. | C8: Tamilvanan S | D8: Archana G | E8: Sudha | F8: Pass | H8: Tamil
A9: IRIS-4182 | B9: Prod issue- When admin updates the course title, database still shows the old title in the master_title field. | C9: sundarapandianp | D9: Dhivya Dharshini C | E9: Sudha | F9: Pass | H9: Duplicate
A10: IRIS-4163 | B10: Build 22.17 Issues - While creating a Learning path, when we modify the access, the default admin group and learner groups a not shown. | C10: Tamilvanan S | D10: Archana G | E10: Sudha | F10: Fail | G10: Still access is blank when doing "Modify Access" in the Learning Path | H10: Tamil
A11: IRIS-4166 | B11: Build 22.17 Issues - Content Description is missing and unpublish button is not enabled for previously published contents. | C11: anuradhab | D11: Archana G | E11: Sudha | F11: Fail | G11: Randomly checked the last content in the QA enviornment and the Description was blank. | H11: anuradhab
A12: IRIS-4172 | B12: Prod issue- Some random SCORM contents are encountering a 'Not Found code 404' error when previewed in the admin site and while launching in the learner site. | C12: anuradhab | D12: Dhivya Dharshini C | E12: Sudha | F12: Pass | H12: anuradhab
A13: IRIS-4193 | B13: Prod Issue - Issue with Optional Enrollments Being Marked as Mandatory in Course/Training Plan | C13: Ramesh K | D13: Sudha Balaji | E13: Sudha | F13: Partial | G13: Issue addressed for enrollments from admin. As a learner the enrollment is still marked as mandatory | H13: Duplicate
A14: IRIS-4173 | B14: Prod issue- While toggling from the learner site to the admin site encountering 'Internal server error 500'. This issue is inconsistent. | C14: Selva | D14: Dhivya Dharshini C | E14: Sudha | F14: Pass | G14: During the course of validation we did not encounter this issue even once, so this can be treated resolved. | H14: Selva
A15: IRIS-4176 | B15: Prod issue- Prerequisite issues | C15: Selvakumar | D15: Dhivya Dharshini C | E15: Sudha | F15: Pass | H15: Selva
A16: IRIS-3621 | B16: Metadata Library - All the languages other than English displayed in the base tenant are not showing in the newly created tenants | C16: Bharath | D16: nithyas | E16: nithyas | F16: Hold | G16: Tenant creation is not working - Ayyappan fixing | H16: nithyas
A17: IRIS-3888 | B17: In announcement screen it shows in JSON format in Change log | C17: Sunil Kumar Girdhar | D17: Vijayaraja S | F17: Pass | H17: Bala | I17: Hold | K17: Old values are updated as expected with text format and new values are getting updated according to the field update
A18: IRIS-4174 | B18: The ILT class is not getting canceled when the min seats are not occupied | C18: sundarapandianp | D18: Selvakumar | E18: Selvakumar | F18: Hold | G18: Cron is not working in QA - Unable to test this ticket | H18: Selva
A19: IRIS-4157 | B19: Enrolled count is shown as zero in the enrollment section though the TP has active enrollments. | C19: Sudha Balaji | D19: Dhivya Dharshini C | E19: Sudha | F19: Pass | H19: Bala | I19: Closed | K19: Enrolled count of Tp courses are displayed as expected either enroll from learner and admin side
A20: IRIS-4181 | B20: Learner->The Terms and Conditions popup is not appearing for admin users when they land on the learner site for the first time. | C20: Mathivanan S | D20: Arivazhagan Pachamuthu | E20: Arivazhagan Pachamuthu | F20: Pass | H20: Arivu
A21: IRIS-3901 | B21: course listing page as the course has multiple instances, clicking on the respective icon, a message gets displayed as 'No matching result found.' | C21: sharmiladevir | D21: Vijayaraja S | F21: Pass | H21: Bala | I21: Closed | K21: It displays the mult instance classes when I click the respective icon in the Multi instance class by loading
A22: IRIS-4167 | B22: Future date announcements are not visible on the Learner side | C22: Edwin Andrews | D22: Tamilvanan S | E22: Tamilvanan | F22: Pass | H22: Tamilvanan S | I22: Closed
A23: IRIS-4160 | B23: Prod issue- When a course is set to hide in catalog status, users who are already enrolled, completed and in progress status unable to see the class and its content | C23: Vadivel M | D23: Dhivya Dharshini C | E23: Sudha | F23: Pass | H23: Divya
A24: IRIS-3934 | B24: Learner>>Create Survey>>The save as draft is not enabled when entering the survey title. | C24: Tamilvanan S | D24: Tamilvanan S | E24: Tamilvanan | F24: Pass | H24: Tamilvanan S | I24: Closed | K24: New ticket has been created EAT1-938
A25: IRIS-4133 | B25: Admin->Training Plan->In the Training Plan, the filter disappears from the UI when navigating to either the Edit Certification page or the Edit Learning Path page. | C25: Santhosh Phadmanabhan | D25: Arivazhagan Pachamuthu | E25: Arivazhagan Pachamuthu | F25: Pass | H25: Arivu
A26: IRIS-4103 | B26: Preference >> Learner UI >> Giving CEU targets In Learner Site is Not fetching. | C26: Indhumathy Prathaban | D26: Pragatheeshwaran V | H26: Divya
A27: IRIS-4183 | B27: Learner->TP->Content Player->Multiple times, the spinner and 'No Results Found' message are displayed along with empty space, before the actual content loads | C27: sharmiladevir | D27: Arivazhagan Pachamuthu | E27: Arivazhagan Pachamuthu | F27: Reopened | H27: Arivu
A28: IRIS-4053 | B28: UI Overlap in Manage Enrollments: Search & Sort Options Overlap Filters | C28: Vadivel Chinnasamy | D28: Vijayaraja S | F28: Pass | H28: Divya
A29: IRIS-4085 | B29: Learner UI - Login Issue (400 Bad Request) | C29: Ayyappan Sekar | D29: Ramesh Subramanian | H29: Mani
A30: EAT1-559 | B30: Issues with cron migration | C30: Manideep kumar | D30: Syed Thanveer J | E30: Sudha | F30: NA | G30: Need to validate during the next migration. | H30: Selva
A31: EAT1-500 | B31: Admin>Content>Incorrect preview of content is displayed in preview when the content is versioned | C31: anuradhab | D31: anuradha | E31: anuradhab | F31: Re-opened | G31: Reported issue is fixed for url type content only. The same need to be fixed for other content types | H31: anuradha
A32: EAT1-553 | B32: Learner>Course Enrollment>There is an enrollment section displayed in the course details page when the course is already enrolled by the learner | C32: anuradhab | D32: Mohan | E32: anuradhab | F32: Pass | H32: anuradha
A33: EAT1-497 | B33: Expiry>>Class details is not displaying in details page for the following scenario | C33: Prabavathi | D33: Vadivel M | E33: Selvakumar | H33: Selva
A34: IRIS-4102 | B34: In the One-Profile Page, the Expiration Date of the completed course is not displaying. | C34: Sharmila | D34: Vijayaraja | F34: Pass | H34: Tamil | K34: Validated this issue, still expiration date of the completed course is not displaying on PTP summary
A35: IRIS-3891 | B35: Instructor checklist is also showing to the learner. | C35: Arunkumar | D35: Vijayaraja | F35: Pass | H35: Selva
A36: IRIS-4196 | B36: The completion certificate is not working properly in AAAE Production Environment. | C36: Ashutosh | D36: Dhineshkumar | E36: Sudha | F36: Pass | H36: Mani
A37: EAT1-388 | B37: Learner - Content player - Duration tracker for Brightcove content is incorrect in size | C37: Vadivelc | D37: Nithya | E37: nithyas | H37: Nithya
A38: EAT1-542 | B38: Issues in Dynamic Sharable Link | C38: Vadivel M | D38: Selvakumar | E38: Selvakumar | F38: Pass | H38: Selva
A39: IRIS-3283 | B39: Order>> Is allowing to create and approve the order without entering Country and state | C39: Bharath | D39: Nithya | E39: nithyas | F39: Re-opened | H39: Nithya
A40: IRIS-3820 | B40: Learner - Content player - Post assessment resume functionality need to to be developed | C40: Ramesh K | D40: Nithya | E40: nithyas | H40: Nithya
A41: IRIS-4146 | B41: 66 Degrees IRIS - Assessment Image issue | C41: Ashutosh | D41: Archana G | E41: Sudha | F41: Pass | H41: Mani
A42: IRIS-4190 | B42: Unable to preview "66way Quiz" Assessment in 66 Degrees in both Admin & Learner site | C42: Nazeer | D42: Archana G | E42: Sudha | F42: Pass | G42: Migration script ran in production and that resolved the issue | H42: Bala | I42: Closed | K42: New ticket has been created EAT1-951
A43: IRIS-4195 | B43: User is unable to view the complete course details page when clicked on title on the learner side. | C43: Prakash | D43: Archana G | E43: Sudha | F43: Pass | H43: Divya
A44: IRIS-4185 | B44: UI issue occurs when we export a PDF File in the Admin Group Edit page | C44: Vadivelc | D44: Selvakumar | E44: Selvakumar | F44: Pass | H44: Mani
A45: IRIS-2900 | B45: Learner>>Location name is displayed in catalog and my learning filter instead of state and country | C45: Tamilvanan S | D45: Prabavathi | E45: Tamilvanan | F45: Re-opened | H45: Tamil
A46: IRIS-4213 | B46: Learning Path>>Enforce Sequencing is not working | C46: Praburaj | D46: Rajeshwari M | E46: Rajeshwari M | F46: Pass | H46: Tamil

Sheet Merge_Tickets_17.14
A1: Ticket No | B1: Summary | C1: Assignee | D1: Reporter | E1: Validated by | F1: Status | G1: Comments | H1: QA Resource | I1: Trunk Status | J1: Trunk Comments
B2: https://expertusone.atlassian.net/browse/IRIS-4282 | H2: Team
B3: https://expertusone.atlassian.net/browse/EAT1-747-SSO | H3: Arivu
B4: https://expertusone.atlassian.net/browse/IRIS-4286-Overdue | H4: Anuradha

Sheet Sheet37
A1: UR - Instructor Enhancement - EAT1-635 | B1: Verify the When the admin selects the ‘Instructor Survey’ checkbox, they can mark ‘Consider for Completion’ yes or not.
A2: UR - Instructor Enhancement - EAT1-635 | B2: Verify If the “Consider for Completion” is enabled for an Instructor Survey,check the if admin try to mark complete without completing the survey Error Message - “In order to start marking attendance, the Instructor needs to submit the survey.” with an OK button.
A3: UR - Instructor Enhancement - EAT1-635 | B3: Verify the “Consider for Completion” is not enabled, then the survey becomes optional. Attendance can be marked even without completing the survey.
A4: UR - Instructor Enhancement - EAT1-635 | B4: Verify the “Consider for Completion” is not enabled, then the survey becomes optional. Attendance can be marked even without completing the survey.
A5: UR - Instructor Enhancement - EAT1-635 | B5: Verify the the Instructor Survey should not be shown to learners.
A6: UR - Instructor Enhancement - EAT1-635 | B6: Verify the multiple survey can be attached as an ‘Instructor Survey’.
A7: UR - Instructor Enhancement - EAT1-635 | B7: Verify if there is more than one instructor handling the class, the survey should be shown to all the instructors. Once any one of the instructors submits the survey
A8: UR - Instructor Enhancement - EAT1-635 | B8: Verify the Notification for Instructor Survey is attached with the class
A9: UR - Instructor Enhancement - EAT1-635 | B9: Verify the instructor is able to proceed with survey completion through Notification Link
A10: UR - Instructor Enhancement - EAT1-635 | B10: Verify the Error Message for Attendance Restriction with Multiple Admins
A11: UR - Instructor Enhancement - EAT1-636 | B11: Verify the Session Details for Single Session Class "Month, Date, Year, Session Start Time - Session End Time (Session Time Zone)
A12: UR - Instructor Enhancement - EAT1-636 | B12: Verify the session count will be displayed for each class
... A17: UR - Instructor Enhancement - EAT1-636 | B17: Verify the ILT class location for each session, and the "Show in My Timezone" option

Sheet After Release
A1: S No | B1: Issue | C1: Severity | D1: Reporter
A2: 1 | B2: Edit icon tooltip not working properly in Instance class edit | C2: Low | D2: Tamil
A3: 2 | B3: Metadata lib>>catalog duplicate name issue | C3: Low | D3: Tamil
A4: 3 | B4: Complete by dropdown in course>>when we select compliance then complete by dropdown automatically selected later removed the compliance that time complete by rule still remains selected | C4: Low | D4: Tamil

Sheet Resolved Tickets_EA-1.23.6.0
A1: Issue key | B1: Summary | C1: Assignee | D1: Reporter | E1: Status | F1: Fix versions
A2: EAT1-922 | B2: Learning Assignment - Learning assignment module is not visible in Toggle Menu and Quick access | D2: nithyas
A3: EAT1-914 | B3: Learner->Learner Able to Upload Files Despite 'Add Files by Learner' Option Being Disabled | C3: Prakash R | D3: Balasundar
A4: EAT1-909 | B4: Equivalence - Should not allow setting the same course as both an Equivalence and a Pre-requisite | C4: Prakash R | D4: nithyas
A5: EAT1-906 | B5: Learner->Captcha Misconfiguration in Sign-In Popup | C5: arunkumarr | D5: Balasundar
A6: EAT1-900 | B6: Enrollments - View/update status page keeps loading and no success message is displayed upon enrollment | C6: Prakash R | D6: nithyas
A7: EAT1-898 | B7: Admin>>All Modules>>Code not auto-generated despite "Enabled Site-Level Code Convention". | C7: Hemalatha S | D7: anuradhab
A8: EAT1-883 | B8: Prod Track->Learner Page->As a learner, while purchasing the order using specific methods, getting an error even though the order is created. | C8: Prakash R | D8: Balasundar
A9: EAT1-878 | B9: 66 Degrees IRIS - TP Structure issue when user enrolled via auto-registration | C9: Ramesh K | D9: Archana G
A10: EAT1-673 | B10: Collaboration Hub>External Training>View functionality is not working as expected | C10: arunkumarr | D10: anuradhab

Sheet Basic Notifications

Sheet Skills
A1: 3367 | B1: Skills Login | C1: To verify Signin and Signout with proper error message validation | G1: NA
A2: 3368 | B2: Skills Library | C2: To verify able to add,edit,delete and update the skill | G2: NA
A3: 3369 | B3: Skills Library | C3: To verify able to add,edit and update the skill | G3: NA
A4: 3370 | B4: Skills Library | C4: To verify allow to enter the code field when code convention is off | G4: NA | H4: IRIS-3326 -not implemented
A5: 3371 | B5: Skills Library | C5: To verify should not allow to enter the code field when code convention is on | G5: NA | H5: IRIS-3326 -not implemented
A6: 3372 | B6: Skills Library | C6: To verify should not allow to delete the skill once mapped to the course | G6: NA
A7: 3373 | B7: Skills Library | C7: To verify and check clicking delete skill for mapped course throw warning message | G7: NA
A8: 3374 | B8: Skills Library | C8: To verify and choose category in mapped category field should be auto filled with x mark icon | G8: NA
A9: 3375 | B9: Skills Library | C9: To verify and check skills mapped courses should display in the Course/TP associated | G9: NA
A10: 3376 | B10: Skills Library | C10: To verify and check Dissocaite all should unmapped all the courses and jobroles which is associated to the skill. | G10: NA
A11: 3378 | B11: Skills Library | C11: To Verify and check JobRole can be disassociate with the skill | G11: NA
A12: 3379 | B12: Skills Library | C12: To Verify and check search functionality in Skills Filter | G12: NA
A13: 3380 | B13: Skills Library | C13: To Verify and check multi select option in Skills Filter | G13: NA
A14: 3381 | B14: Skills Library | C14: To Verify and check admin user gets error message in red color for adding existing Skill Name | G14: NA
A15: 3382 | B15: Skills Library | C15: To Verify and check SHOW MORE Option will be displayed in capital with chevron-down icon for more than 15 records in the alphabet | G15: NA
A16: 3383 | B16: Skills Jobroles | C16: To Verify and check Edit Job Role opens with two section “Select skills to Map” and “Mapped skills”. | G16: NA
A17: 3384 | B17: Skills Jobroles | C17: To Verify and check search functionality in Job Role Filter | G17: NA
... A27: 3394 | B27: Skills course mapping | C27: To Verify and check map selected skills button | G27: NA
A28: 3395 | B28: Skills course mapping | C28: To Verify and check mapped skills can display the proficiency list | G28: NA | H28: EA-1.1.21.11
A29: 3397 | B29: Skills course mapping | C29: To Verify and check mapped skills can can be deleted after clicking x mark icon | G29: NA | H29: EA-1.1.21.11
A30: 3398 | B30: Skills course mapping | C30: To Verify and check the save and close button in course edit screen | G30: NA | H30: EA-1.1.21.11
A31: 3399 | B31: Skills course mapping | C31: To Verify and check while clicking + icon the mapped skills should listed | G31: NA
A32: 3400 | B32: Skills course mapping | C32: To Verify and check filters by training type and training mapping combinations | G32: NA
A33: 3401 | B33: Skills course mapping | C33: To Verify and check filters clear and apply button | G33: NA
A34: 3402 | B34: Skills course mapping | C34: To Verify and check the search and sort functionality | G34: NA
A35: 3403 | B35: Skills course mapping | C35: To Verify and check Course in the Filter | G35: NA
A36: 3404 | B36: Skills course mapping | C36: To Verify and check Certification in the Filter | G36: NA
A37: 3405 | B37: Skills course mapping | C37: To Verify and check Learning Path in the Filter | G37: NA
A38: 3406 | B38: Skills course mapping | C38: To Verify and check Training with skill in the Filter | G38: NA
A39: 3407 | B39: Skills course mapping | C39: To Verify and check Training without skill in the Filter | G39: NA
A40: 3408 | B40: Skill categories and proficiency model | C40: To Verify and check create,edit,delete,cancel the category | G40: NA
A41: 3409 | B41: Skill categories and proficiency model | C41: To Verify and check the mapped skill category should not allow to delete? | G41: NA
A42: 3410 | B42: Skill categories and proficiency model | C42: To Verify and check the skill categories in search field | G42: NA | H42: IRIS-4013
A43: 3411 | B43: Skill categories and proficiency model | C43: To Verify allow to enter the proficiency model name and options to add and reflect in the skills course mapped category screen | G43: NA
A44: 3412 | B44: Skill categories and proficiency model | C44: Check whether the Admin can create one proficiency model in the system and can add upto ten levels associated with it can create 2 proficiency level mandatory | G44: NA
A45: 3413 | B45: Skill categories and proficiency model | C45: To Verify and check for the option 1 and 2 the delete icon should not display | G45: NA
A46: 3414 | B46: Skills report | C46: Check whether the three radio buttons "By Skill", "By Job Role", "By Course" are displaying when clicking on Skills Report and need to activate | G46: NA | H46: IRIS-3311
A47: 3415 | B47: Skills report | C47: To verify and check By skill the Skill name,assigned learners,met,not met,met % of learners count need to display | G47: NA | H47: IRIS-3311
A48: 3416 | B48: Skills report | C48: To verify and check By skill the Skill name,assigned learners,met,not met,met % of learners count need to display | G48: NA | H48: IRIS-3311
A49: 3417 | B49: Skills report | C49: To verify and check whether Records in the “Assigned” category is including only the number of learners for whom the respective skill is assigned as a part of their skill requirement. | G49: NA | H49: IRIS-3311
A50: 3418 | B50: Skills report | C50: Check whether the Records in the “Met” category is who met the respective skill as a part of their skill. | G50: NA | H50: IRIS-3311
A51: 3419 | B51: Skills report | C51: To check and verify the export as csv,pdf,Excel. | G51: NA
A52: 3420 | B52: Skills report | C52: To verify and check the search functionality | G52: NA | H52: IRIS-3311
A53: 3421 | B53: Skills report | C53: To verify and check the sort the each colum as 0 to 100% | G53: NA | H53: IRIS-3311
A54: 3422 | B54: Skills report | C54: BY SKILL: Check if the Skill Name, Assigned, Met, Not Met, Met%Age is displaying in By skill Table header | G54: NA | H54: IRIS-3311
A55: 3423 | B55: Skills report | C55: Check if the Skill Met%Age is been calculated based on Met/Assigned * 100 | G55: NA | H55: IRIS-3311
A56: 3424 | B56: Skills report | C56: Check if the Skill Not Met value is displaying in the table if the learner does not met the respective skill | G56: NA | H56: IRIS-3311
A57: 3425 | B57: Skills report | C57: BY JOBROLE: Check if the Job Role, Skill Name, Assigned, Met, Not Met, Met%Age is displaying in By Job Role Table header | G57: NA | H57: IRIS-3311
A58: 3426 | B58: Skills report | C58: Check if the Job Role Met%Age is been calculated based on Met/Assigned * 100 | G58: NA | H58: IRIS-3311
A59: 3427 | B59: Skills report | C59: Check if the Job Role Not Met value is displaying in the table if the learner does not met the respective skill | G59: NA | H59: IRIS-3311
A60: 3428 | B60: Skills report | C60: BY COURSE: Check if the Job Role, Skill Name, Assigned, Met, Not Met, Met%Age is displaying properly when activating on By Course radio button | G60: NA | H60: IRIS-3311
A61: 3429 | B61: Skills report | C61: Check if the Course/Training Plan Met%Age is been calculated based on Met/Assigned * 100 | G61: NA | H61: IRIS-3311
A62: 3430 | B62: Skills report | C62: Check if the Course/Training Plan Not Met value is displaying in the table if the learner does not met the respective skill | G62: NA | H62: IRIS-3311
A63: 3431 | B63: Skills dashboard | C63: Check whether if the learner is adding to the Met Criteria if learner met all the skills which is present in job role | G63: NA | H63: IRIS-3310,3311,3320
... A106: 3474 | B106: Skill Individual Learner Stats | C106: Check whether when clicking on the shaded region displays the number of skills under the specific category in a table below the chart | G106: NA | H106: IRIS-3310,3311,3320
B107: Skill categories and proficiency model | C107: To Verify and check for proficiency model allow to delete the option3 | G107: NA | H107: IRIS-4013
A108: 3475 | B108: Skills Tenant and Portal | C108: To verify and check the created organization in one tenant should not visible to another skills tenant | G108: NA | H108: portal level courses not listed(performance issue)
A109: 3476 | B109: Skills Tenant and Portal | C109: To verify and check the created organization in one portal should not visible to another skills portal | G109: NA | H109: portal level courses not listed(performance issue)

Sheet UR_Instructor
A2: 1 | B2: UR - Instructor Enhancement - EAT1-564 | C2: Displaying 'From' and 'To' Fields When 'Date' Option is Selected
A3: 2 | B3: UR - Instructor Enhancement - EAT1-564 | C3: Displaying 'Past' and 'Future' Fields When 'Days' Option is Selected
A4: 3 | B4: UR - Instructor Enhancement - EAT1-564 | C4: Applying Past Value to Calculate 'From' Date
A5: 4 | B5: UR - Instructor Enhancement - EAT1-564 | C5: Applying Future Value to Calculate 'To' Date
A6: 5 | B6: UR - Instructor Enhancement - EAT1-564 | C6: Applying Both Past and Future Values to Calculate Date Range
A7: 6 | B7: UR - Instructor Enhancement - EAT1-564 | C7: Example Scenario with Specific Past and Future Values
A8: 7 | B8: UR - Instructor Enhancement - EAT1-564 | C8: Validation for Numeric Input in 'Past' and 'Future' Fields
A10: 8 | B10: UR - Instructor Ehancement - EAT1-634 | C10: Verify the File Indicator Visibility for Learner with Files
A11: 9 | B11: UR - Instructor Ehancement - EAT1-634 | C11: Verify the File Indicator Visibility for Learner without Files
A12: 10 | B12: UR - Instructor Ehancement - EAT1-634 | C12: Verify the file upload access
A13: 11 | B13: UR - Instructor Ehancement - EAT1-634 | C13: Verify the Update and Deletion of files
A14: 12 | B14: UR - Instructor Ehancement - EAT1-634 | C14: Adding Files
... A117: 107 | B117: UR - File Indicator - EAT1-689 | C117: Handling Large File List During Search/Filter

Sheet Sheet13
A1: S. No | B1: Content | C1: Scenarios | D1: Status | E1: Executed Date | F1: Build Version | G1: Resource | H1: Jira Ticket# | I1: Status 1 | J1: Comments
B2: MP4 Content | C2: Verify that a course can be created with a single MP4 content. | D2: Pass | G2: Nithya
B3: MP4 Content | C3: Verify that the course with attached MP4 content can be enrolled by the learner | D3: Pass | G3: Nithya
B4: MP4 Content | C4: Verify that the MP4 content can be launched from the catalog details page. | D4: Pass | G4: Nithya
B5: MP4 Content | C5: Verify that the MP4 content can be launched from My Learning. | D5: Pass | G5: Nithya
B6: MP4 Content | C6: Verify that the course moves to the Completed tab upon content completion. | D6: Pass | G6: Nithya
B7: MP4 Content | C7: Verify that a course can be created with a single MP4 content and a pre-assessment. | D7: Pass | G7: Nithya
B8: MP4 Content | C8: Verify that the course with attached MP4 content and pre-assessment can be enrolled. | D8: Pass | G8: Nithya
B9: MP4 Content | C9: Verify that the MP4 content cannot be launched from the catalog details page without taking the pre-assessment. | D9: Pass | G9: Nithya
B10: MP4 Content | C10: Verify that the MP4 content cannot be launched from My Learning without taking the pre-assessment. | D10: Pass | G10: Nithya
B11: MP4 Content | C11: Verify that the pre-assessment can be taken and answered. | D11: Pass | G11: Nithya
B12: MP4 Content | C12: Verify that the MP4 content can be taken and the course completed even if the pre-assessment is failed. | D12: Pass | G12: Nithya
B13: MP4 Content | C13: Verify that a course can be created with MP4 content and a post-assessment. | D13: Pass | G13: Nithya
... B35: MP4 Content | C35: Verify that course should move to completed tab after passing the Post assessment | D35: Pass | G35: Nithya
B37: MP4 Content | C37: Verify that able to create a course with MP4 content and OJT | G37: Nithya
B38: MP4 Content | C38: Verify that learner can able to enroll the course which is having MP4 content and OJT | G38: Nithya
B39: MP4 Content | C39: Verify that learner can launch the OJT before MP4 content | G39: Nithya
B40: MP4 Content | C40: Verfiy that course should not move to completed by taking only the OJT which is attached with content alone | G40: Nithya
B41: MP4 Content | C41: Verity that course should move to completed tab after taking the MP4 content and OJT | G41: Nithya
B43: MP4 Content | C43: Verify that able to create a course with MP4 Content and E-signature | G43: Nithya
B44: MP4 Content | C44: Verify that learner can enroll the course with MP4 content and E-signature | G44: Nithya
B45: MP4 Content | C45: Verify learner cannot able to take the E-signature until completing the MP4 content | G45: Nithya
B46: MP4 Content | C46: Verify that learner can able to complete the course after submit the E-signature | G46: Nithya
B48: MP4 Content | C48: Verify that able to create a course with pre-assessment, post-assessment, MP4 content, survey, OJT and E-signature | G48: Nithya
B49: MP4 Content | C49: Verify that learner can able to enroll the course which is having pre-assessment, post assessment, MP4 content, Survey, OJT and E-signature | G49: Nithya
B50: MP4 Content | C50: Verify that learner can launch the OJT without taking the pre-assessment, post assessment but course should not move to completed tab until E-signature is submitted | G50: Nithya
... B70: MP4 Content | C70: Verify that learner can skip the pre-assessment and content when testout is enabled for MP4 content | G70: Nithya
B71: MP4 Content
B72: MP4 Content | C72: Verify that able to create a course with MP4 content with post assessment and Survey consider for completion rule enabled | G72: Nithya
B73: MP4 Content | C73: Verify that able to enroll to the course with MP4 content with post assessment and Survey consider for completion rule enabled | G73: Nithya
B74: MP4 Content | C74: Verify that the course should not move to the completed tab when learner pass the post assessment until the survey has been taken | G74: Nithya
B75: MP4 Content | C75: Verify that the course should move to the incompleted tab when learner fail the post assessment without taking the survey | G75: Nithya
B77: AICC Content | C77: Verify that a course can be created with a single AICC content.
B78: AICC Content | C78: Verify that the course with attached AICC content can be enrolled by the learner
B79: AICC Content | C79: Verify that the AICC content can be launched from the catalog details page.
B80: AICC Content | C80: Verify that the AICC content can be launched from My Learning.
B81: AICC Content | C81: Verify that the course moves to the Completed tab upon content completion.
B83: AICC Content | C83: Verify that a course can be created with a single AICC content and a pre-assessment.
B84: AICC Content | C84: Verify that the course with attached AICC content and pre-assessment can be enrolled.
B85: AICC Content | C85: Verify that the AICC content cannot be launched from the catalog details page without taking the pre-assessment.
B86: AICC Content | C86: Verify that the AICC content cannot be launched from My Learning without taking the pre-assessment.
B87: AICC Content | C87: Verify that the pre-assessment can be taken and answered.
B88: AICC Content | C88: Verify that the AICC content can be taken and the course completed even if the pre-assessment is failed.
B90: AICC Content | C90: Verify that a course can be created with AICC content and a post-assessment.
... B152: AICC Content | C152: Verify that the course should move to the incompleted tab when learner fail the post assessment without taking the survey
B154: MP3 Content | C154: Verify that a course can be created with a single MP3 content. | D154: Pass | G154: Nithya
B155: MP3 Content | C155: Verify that the course with attached MP3 content can be enrolled by the learner | D155: Pass | G155: Nithya
B156: MP3 Content | C156: Verify that the MP3 content can be launched from the catalog details page. | D156: Pass | G156: Nithya
B157: MP3 Content | C157: Verify that the MP3 content can be launched from My Learning. | D157: Pass | G157: Nithya
B158: MP3 Content | C158: Verify that the course moves to the Completed tab upon content completion. | D158: Pass | G158: Nithya
B160: MP3 Content | C160: Verify that a course can be created with a single MP3 content and a pre-assessment. | D160: Pass | G160: Nithya
B161: MP3 Content | C161: Verify that the course with attached MP3 content and pre-assessment can be enrolled. | D161: Pass | G161: Nithya
B162: MP3 Content | C162: Verify that the MP3 content cannot be launched from the catalog details page without taking the pre-assessment. | D162: Pass | G162: Nithya
B163: MP3 Content | C163: Verify that the MP3 content cannot be launched from My Learning without taking the pre-assessment. | D163: Pass | G163: Nithya
B164: MP3 Content | C164: Verify that the pre-assessment can be taken and answered. | D164: Pass | G164: Nithya
B165: MP3 Content | C165: Verify that the MP3 content can be taken and the course completed even if the pre-assessment is failed. | D165: Pass | G165: Nithya
B167: MP3 Content | C167: Verify that a course can be created with MP3 content and a post-assessment. | D167: Pass | G167: Nithya
... B170: MP3 Content | C170: Verify that the course moves to the Incomplete tab when the user fails the post-assessment. | D170: Pass | G170: Nithya
B172: MP3 Content | C172: Verify that a course can be created with MP3 content, pre-assessment, and post-assessment.
B173: MP3 Content | C173: Verify that the course with attached MP3 content, post-assessment, and pre-assessment can be enrolled.
B174: MP3 Content | C174: Verify that the MP3 content and post-assessment cannot be launched from the catalog details page without taking the pre-assessment.
B175: MP3 Content | C175: Verify that the learner can complete the course by taking the MP3 content, pre-assessment, and passing the post-assessment from the catalog details page.
B176: MP3 Content | C176: Verify that the percentage is calculated correctly for the content and assessment. For example, if a course includes a pre-assessment, post-assessment, and content, and the user completes the pre-assessment and content, the progress should be marked as "in progress" with 67%.
B177: MP3 Content | C177: Verify that the course moves to the Incomplete tab if the learner takes the MP3 content, pre-assessment, and fails the post-assessment from the catalog details page.
B179: MP3 Content | C179: Verify that able to create a course with pre-assessment, post-assessment, MP3 content, and survey
B180: MP3 Content | C180: Verify that the course with attached MP3 content, post-assessment, and pre-assessment and survey can be enrolled by the learner
B181: MP3 Content | C181: Verify that the MP3 content, post-assessment, survey cannot be launched from the catalog details page without taking the pre-assessment.
B182: MP3 Content | C182: Verify that the learner can complete the course by taking the MP3 content, pre-assessment, and passing the post-assessment from the catalog details page, survey cannot be considered for completion
B183: MP3 Content | C183: Verify that the course moves to the Incomplete tab if the learner takes the MP3 content, pre-assessment, and fails the post-assessment from the catalog details page
B185: MP3 Content | C185: Verify that able to create a course with pre-assessment, post-assessment, MP3 content, survey, OJT
... B195: MP3 Content | C195: Verity that course should move to completed tab after taking the MP3 content and OJT
B196: MP3 Content
B197: MP3 Content | C197: Verify that able to create a course with MP3 Content and E-signature
B198: MP3 Content | C198: Verify that learner can enroll the course with MP3 content and E-signature
B199: MP3 Content | C199: Verify learner cannot able to take the E-signature until completing the MP3 content
B200: MP3 Content | C200: Verify that learner can able to complete the course after taking the E-signature
B202: MP3 Content | C202: Verify that able to create a course with pre-assessment, post-assessment, MP3 content, survey, OJT and E-signature
B203: MP3 Content | C203: Verify that learner can able to enroll the course which is having pre-assessment, post assessment, MP3 content, Survey, OJT and E-signature
B204: MP3 Content | C204: Verify that learner can launch the OJT without taking the pre-assessment, post assessment but course should not move to completed tab
B205: MP3 Content | C205: Verify that course should not move to completed tab when user take pre-assessment, post assessment, MP3 content, survey unless completing the OJT
B206: MP3 Content | C206: Verify that course should move to completed tab after passing the Post assessment and submit the E-signature
B208: MP3 Content | C208: Verify that able to create a course with Multiple MP3 content into the course without enforce sequencing enabled
B209: MP3 Content | C209: Verify that the learner can able to enroll the course with MP3 multiple contents
B210: MP3 Content | C210: Verify that learner cannot take the content in any order, should take only the sequencial order
... B306: XAPI Content | C306: Verify that the course should move to the incompleted tab when learner fail the post assessment without taking the survey
B308: Youtube Content | C308: Verify that a course can be created with a single Youtube content. | G308: Selva
B309: Youtube Content | C309: Verify that the course with attached Youtube content can be enrolled by the learner | G309: Selva
B310: Youtube Content | C310: Verify that the Youtube content can be launched from the catalog details page. | G310: Selva
B311: Youtube Content | C311: Verify that the Youtube content can be launched from My Learning. | G311: Selva
B312: Youtube Content | C312: Verify that the course moves to the Completed tab upon content completion. | G312: Selva
G313: Selva
B314: Youtube Content | C314: Verify that a course can be created with a single Youtube content and a pre-assessment. | G314: Selva
B315: Youtube Content | C315: Verify that the course with attached Youtube content and pre-assessment can be enrolled. | G315: Selva
B316: Youtube Content | C316: Verify that the Youtube content cannot be launched from the catalog details page without taking the pre-assessment. | G316: Selva
B317: Youtube Content | C317: Verify that the Youtube content cannot be launched from My Learning without taking the pre-assessment. | G317: Selva
B318: Youtube Content | C318: Verify that the pre-assessment can be taken and answered. | G318: Selva
B319: Youtube Content | C319: Verify that the Youtube content can be taken and the course completed even if the pre-assessment is failed. | G319: Selva
G320: Selva
B321: Youtube Content | C321: Verify that a course can be created with Youtube content and a post-assessment. | G321: Selva
B322: Youtube Content | C322: Verify that the learner can launch the content from the catalog details page but cannot take the post-assessment until the content is completed. | G322: Selva
...

Sheet All
A1: =IFERROR(__xludf.DUMMYFUNCTION("QUERY({Contentplayer!A1:G700; AgileFeatures!A2:H2305 ; MasterSheet_final!A2:F6027})"),"#VALUE!") -> #VALUE! | H1: week no | I1: Week | J1: T
H2: =IF(ISBLANK(E2)," ",WEEKNUM(E2,2)) | I2: =if(H2=30,"23th July-28th July", if(H2=31,"29th July-4th Aug", if(H2=32,"5th Aug-11th Aug",if(H2=33,"12th Aug-18th Aug", if(H2=34,"19th Aug-25th Aug",if(H2=35,"26th Aug - 1st Sep"," ")))))) | J2: =if(H2=30,"W1", if(H2=31,"W2", if(H2=32,"W3",if(H2=33,"W4", if(H2=34,"W5",if(H2=35,"W6"," "))))))
H3: =IF(ISBLANK(E3)," ",WEEKNUM(E3,2)) | I3: =if(H3=30,"23th July-28th July", if(H3=31,"29th July-4th Aug", if(H3=32,"5th Aug-11th Aug",if(H3=33,"12th Aug-18th Aug", if(H3=34,"19th Aug-25th Aug",if(H3=35,"26th Aug - 1st Sep"," ")))))) | J3: =if(H3=30,"W1", if(H3=31,"W2", if(H3=32,"W3",if(H3=33,"W4", if(H3=34,"W5",if(H3=35,"W6"," "))))))
H4: =IF(ISBLANK(E4)," ",WEEKNUM(E4,2)) | I4: =if(H4=30,"23th July-28th July", if(H4=31,"29th July-4th Aug", if(H4=32,"5th Aug-11th Aug",if(H4=33,"12th Aug-18th Aug", if(H4=34,"19th Aug-25th Aug",if(H4=35,"26th Aug - 1st Sep"," ")))))) | J4: =if(H4=30,"W1", if(H4=31,"W2", if(H4=32,"W3",if(H4=33,"W4", if(H4=34,"W5",if(H4=35,"W6"," "))))))
H5: =IF(ISBLANK(E5)," ",WEEKNUM(E5,2)) | I5: =if(H5=30,"23th July-28th July", if(H5=31,"29th July-4th Aug", if(H5=32,"5th Aug-11th Aug",if(H5=33,"12th Aug-18th Aug", if(H5=34,"19th Aug-25th Aug",if(H5=35,"26th Aug - 1st Sep"," ")))))) | J5: =if(H5=30,"W1", if(H5=31,"W2", if(H5=32,"W3",if(H5=33,"W4", if(H5=34,"W5",if(H5=35,"W6"," "))))))
H6: =IF(ISBLANK(E6)," ",WEEKNUM(E6,2)) | I6: =if(H6=30,"23th July-28th July", if(H6=31,"29th July-4th Aug", if(H6=32,"5th Aug-11th Aug",if(H6=33,"12th Aug-18th Aug", if(H6=34,"19th Aug-25th Aug",if(H6=35,"26th Aug - 1st Sep"," ")))))) | J6: =if(H6=30,"W1", if(H6=31,"W2", if(H6=32,"W3",if(H6=33,"W4", if(H6=34,"W5",if(H6=35,"W6"," "))))))
H7: =IF(ISBLANK(E7)," ",WEEKNUM(E7,2)) | I7: =if(H7=30,"23th July-28th July", if(H7=31,"29th July-4th Aug", if(H7=32,"5th Aug-11th Aug",if(H7=33,"12th Aug-18th Aug", if(H7=34,"19th Aug-25th Aug",if(H7=35,"26th Aug - 1st Sep"," ")))))) | J7: =if(H7=30,"W1", if(H7=31,"W2", if(H7=32,"W3",if(H7=33,"W4", if(H7=34,"W5",if(H7=35,"W6"," "))))))
H8: =IF(ISBLANK(E8)," ",WEEKNUM(E8,2)) | I8: =if(H8=30,"23th July-28th July", if(H8=31,"29th July-4th Aug", if(H8=32,"5th Aug-11th Aug",if(H8=33,"12th Aug-18th Aug", if(H8=34,"19th Aug-25th Aug",if(H8=35,"26th Aug - 1st Sep"," ")))))) | J8: =if(H8=30,"W1", if(H8=31,"W2", if(H8=32,"W3",if(H8=33,"W4", if(H8=34,"W5",if(H8=35,"W6"," "))))))
H9: =IF(ISBLANK(E9)," ",WEEKNUM(E9,2)) | I9: =if(H9=30,"23th July-28th July", if(H9=31,"29th July-4th Aug", if(H9=32,"5th Aug-11th Aug",if(H9=33,"12th Aug-18th Aug", if(H9=34,"19th Aug-25th Aug",if(H9=35,"26th Aug - 1st Sep"," ")))))) | J9: =if(H9=30,"W1", if(H9=31,"W2", if(H9=32,"W3",if(H9=33,"W4", if(H9=34,"W5",if(H9=35,"W6"," "))))))
H10: =IF(ISBLANK(E10)," ",WEEKNUM(E10,2)) | I10: =if(H10=30,"23th July-28th July", if(H10=31,"29th July-4th Aug", if(H10=32,"5th Aug-11th Aug",if(H10=33,"12th Aug-18th Aug", if(H10=34,"19th Aug-25th Aug",if(H10=35,"26th Aug - 1st Sep"," ")))))) | J10: =if(H10=30,"W1", if(H10=31,"W2", if(H10=32,"W3",if(H10=33,"W4", if(H10=34,"W5",if(H10=35,"W6"," "))))))
H11: =IF(ISBLANK(E11)," ",WEEKNUM(E11,2)) | I11: =if(H11=30,"23th July-28th July", if(H11=31,"29th July-4th Aug", if(H11=32,"5th Aug-11th Aug",if(H11=33,"12th Aug-18th Aug", if(H11=34,"19th Aug-25th Aug",if(H11=35,"26th Aug - 1st Sep"," ")))))) | J11: =if(H11=30,"W1", if(H11=31,"W2", if(H11=32,"W3",if(H11=33,"W4", if(H11=34,"W5",if(H11=35,"W6"," "))))))
H12: =IF(ISBLANK(E12)," ",WEEKNUM(E12,2)) | I12: =if(H12=30,"23th July-28th July", if(H12=31,"29th July-4th Aug", if(H12=32,"5th Aug-11th Aug",if(H12=33,"12th Aug-18th Aug", if(H12=34,"19th Aug-25th Aug",if(H12=35,"26th Aug - 1st Sep"," ")))))) | J12: =if(H12=30,"W1", if(H12=31,"W2", if(H12=32,"W3",if(H12=33,"W4", if(H12=34,"W5",if(H12=35,"W6"," "))))))
H13: =IF(ISBLANK(E13)," ",WEEKNUM(E13,2)) | I13: =if(H13=30,"23th July-28th July", if(H13=31,"29th July-4th Aug", if(H13=32,"5th Aug-11th Aug",if(H13=33,"12th Aug-18th Aug", if(H13=34,"19th Aug-25th Aug",if(H13=35,"26th Aug - 1st Sep"," ")))))) | J13: =if(H13=30,"W1", if(H13=31,"W2", if(H13=32,"W3",if(H13=33,"W4", if(H13=34,"W5",if(H13=35,"W6"," "))))))
... H5144: =IF(ISBLANK(E5144)," ",WEEKNUM(E5144,2)) | I5144: =if(H5144=30,"23th July-28th July", if(H5144=31,"29th July-4th Aug", if(H5144=32,"5th Aug-11th Aug",if(H5144=33,"12th Aug-18th Aug", if(H5144=34,"19th Aug-25th Aug",if(H5144=35,"26th Aug - 1st Sep"," ")))))) | J5144: =if(H5144=30,"W1", if(H5144=31,"W2", if(H5144=32,"W3",if(H5144=33,"W4", if(H5144=34,"W5",if(H5144=35,"W6"," "))))))

Sheet Sheet21
A1: Epic Link Summary | B1: Summary | C1: Reporter | D1: Custom field (Severity) | E1: Issue key
A2: Course | B2: Admin>>Registration end date should not be mandatory for course | C2: prabavathi | D2: Major | E2: IRIS-4038
A3: User Bulk upload | B3: Admin-->User Bulk Upload-->Unable to create user in admin ui through bulk upload as the Execution job is not processed in DB | C3: anuradhab | D3: Major | E3: IRIS-3995
A4: Privacy Policy | B4: Learner>>Terms and conditions popup is not getting displayed for the new user. | C4: Priyadharshini Ponnusamy | D4: Major | E4: IRIS-3967
A5: Learner UI Development | B5: Learner->Content Player->Error message is displayed, when we launch the AICC content for the second time, from the different browser/Private | C5: Arivazhagan Pachamuthu | D5: Major | E5: IRIS-3964
A6: Learner UI Development | B6: Learner>>Unable to complete the observation checklist. | C6: Priyadharshini Ponnusamy | D6: Major | E6: IRIS-3959
A7: Site settings | B7: Portal - Issues in the Export file and Search filter | C7: nithyas | D7: Major | E7: IRIS-3958
A8: Bulk upload - Course / TP | B8: Admin-->Bulk Upload-->Unable to enroll learners to the course and the course within the training plan through bulk upload | C8: anuradhab | D8: Major | E8: IRIS-3957
A9: Learner Group | B9: Learner Group - Super admin group access is getting not set for default Learner groups | C9: nithyas | D9: Major | E9: IRIS-3953
A10: Manage Enrollment | B10: Admin-->Instructor is unable to mark "No Show" for the learner | C10: anuradhab | D10: Major | E10: IRIS-3903
A11: Learner UI Development | B11: Learner - Compliance course is visible to users who are not part of the group with access to the course | C11: nithyas | D11: Major | E11: IRIS-3870
A12: Transfer enrollment - Course | B12: Admin>>Transfer Enrollment - Course>>After transferring users, the user is still present in the original class | C12: Priyadharshini Ponnusamy | D12: Major | E12: IRIS-3868
... A189: Course | B189: Compliance Expiry>>The Course is not moving to Expired status after the validity date or days | C189: Selvakumar | D189: Moderate | E189: IRIS-3838

Sheet Selva
A1: 1 | B1: Assessment | C1: Verify the Admin able to create Assessment and check its getting displayed with respective tabs like Draft,Published and Unpublished tabs
A2: 2 | B2: Assessment | C2: Verify the admin able to create assessment with question creation on the fly
A3: 3 | B3: Assessment | C3: Verify whether the textbox are marked as red color when the mandatory fields are not filled | D3: Ticket
A4: 4 | B4: Assessment | C4: Verify the admin able to create assessment and try to add questions using import question
A5: 5 | B5: Assessment | C5: Verify the admin able to create assessment with question creation with sections
A6: 6 | B6: Assessment | C6: Verify the admin able to create assessment with question creation on the fly,check created questions are displayed in question list page
A7: 7 | B7: Assessment | C7: Verify that the Custom Admin user has the ability to publish and unpublish the assessment. | D7: Ticket
A8: 8 | B8: Assessment | C8: Verify the admin able to view the associated trainings will be displayed in listing page(assessment will be associated with Course/Training Plan)
A9: 9 | B9: Assessment | C9: Verify the admin will not allow to delete the questions which is associated with assessment
A10: 10 | B10: Assessment | C10: Verify the admin able to clone the assessment
A11: 11 | B11: Assessment | C11: Verify the admin able to clone the sections
A12: 12 | B12: Assessment | C12: Verify able to clone the assessment multiple times | D12: Ticket
A13: 13 | B13: Assessment | C13: Verify and check the slected langugae should display after edit
A14: 14 | B14: Assessment | C14: Verify the admin able to save the assessment question after edit
A15: 15 | B15: Assessment | C15: Verify whether it allows to edit only one question at a time in the Assessment Edit page | D15: Ticket
A16: 16 | B16: Assessment | C16: Verify whether the Save Draft gets enabled after entering the Assessment Title | D16: New case
A17: 17 | B17: Assessment | C17: Verify the admin able to delet the drafted and unpublished assessment
A18: 18 | B18: Assessment | C18: Verify that the Deleted training should not be displayed in the Assessment Listing page>>No of training | D18: Ticket
A19: 19 | B19: Assessment | C19: Verify the re-order in the assessment
A20: 20 | B20: Assessment | C20: Verify the update question
A21: 21 | B21: Assessment | C21: Verify the search,filters ,delete functionalitys
A22: 22 | B22: Assessment | C22: Verify whether the Export functionality works correctly in the Assessment Listing page | D22: New case
A23: 23 | B23: Assessment | C23: Verify all types question can be created under the assessment
A24: 24 | B24: Assessment | C24: Verify all types question can be created in the questions list page
A25: 25 | B25: Assessment | C25: Verify the admin will not allow to publish the assessment without questions
A26: 26 | B26: Assessment | C26: Verify whether we cannot able to create a question without adding the mandatory fields in the Question Creation page | D26: Ticket
A27: 27 | B27: Assessment | C27: Verify the Created Assessment will be displayed for course and tp edit page
A28: 28 | B28: Assessment | C28: Verify the Admin created Assessment with "No fo attempts" as 10
A29: 29 | B29: Assessment | C29: Verify the Assessment attempt will be displayed in course and tp edit page when admin attached the assessment with attempt set
A30: 30 | B30: Assessment | C30: Verify the Assessment passing score in learner side,Admin created assessment with passs percentage as 50 and No. Of Questions To Display as 4 Questions: q1-20 score q2-20 score q3-20 score q4-20 score q5-20 score q6-20 score Admin created course then attach this assessment Admin created TP then attach this assessment Course: case1:Verify the learner enrolled the course and launch the assessment then completed two questions correctly,check assessment score getting displayed in completion certification case2:Verify the learner enrolled the course and launch the assessment then completed two questions correctly,check assessment score getting displayed in admin enrollment page case3:Verify the learner enrolled the course and launch the assessment then completed all questions incorrectly,check learner will be moved enrolled to incomplete status due to assessment failed case4:Verify the learner page only 4 questions are getting displayed in the assessment under course Case5:Verify the no of question to display at the section level TP: case1:Verify the learner enrolled the TP and launch the assessment then completed two questions correctly,check assessment score getting displayed in completion certification case2:Verify the learner enrolled the TP and launch the assessment then completed two questions correctly,check assessment score getting displayed in admin enrollment page case3:Verify the learner enrolled the TP and launch the assessment then completed all questions incorrectly,check learner will be moved enrolled to incomplete status due to assessment failed case4:Verify the learner page only 4 questions are getting displayed in the assessment under course Case5:Verify the no of question to display at the section level
A31: 31 | B31: Assessment | C31: Verify the assessment for course if set required for attached questions under assessment in learner side
A32: 32 | B32: Assessment | C32: Verify whether the Change Log is getting captured for any action in the Creation and Updation page Assessment page | D32: New Case
A33: 33 | B33: Assessment | C33: Verify that the value in the number of questions field does not exceed the total number of questions in the assessment. | D33: New Case
A34: 34 | B34: Assessment | C34: Verify that all questions in the assessment are used when no value is specified in the number of questions field, and no validation is necessary. | D34: New Case
A35: 35 | B35: Assessment | C35: Verify validation of the number of questions specified by the admin against total and required questions in the assessment. If the specified value exceeds the total number of questions, an error message is displayed: "The number of questions cannot exceed the total number of questions in the assessment." If the specified value is less than the total number of required questions, an error message is displayed: "The number of questions cannot be less than the total number of required questions." If the specified value is between the total number of questions and the total number of required questions, the assessment is saved or published successfully. | D35: New Case
A36: 36 | B36: Assessment | C36: Verify if the admin has not provided a value in the number of questions field. In this scenario, the following error message should be displayed, insisting the admin provide a value: "The number of questions to be displayed cannot be less than the total required questions." | D36: New Case
A37: 37 | B37: Assessment | C37: Verify that the "Number of questions to be displayed at the assessment level" field will be greyed out as soon as the admin creates a section. | D37: New Case
A38: 38 | B38: Assessment | C38: Verify that if the admin provides the number of questions for one section, it is mandatory to provide the number of questions for all sections. | D38: New Case
A39: 39 | B39: Assessment | C39: Verify that the total of all the values provided in the number of questions per section is displayed as the "number of questions" to be displayed at the assessment level. | D39: New Case
A40: 40 | B40: Assessment | C40: Verify that when questions are marked as required in each section, the number of required questions is automatically captured in the "Number of questions per section" field. | D40: New Case
A41: 41 | B41: Assessment | C41: Verify that when the admin manually enters the value for the "number of questions per section," and there are required questions, the admin will not be allowed to provide a value that is less than or greater than the specified required value. | D41: New Case
A42: 42 | B42: Assessment | C42: Verify that when no values are entered in the "Number of questions" field for the sections, all questions in those sections are considered for the assessment. | D42: New Case
A43: 43 | B43: Assessment | C43: Verify by creating the following question types and attaching it to the Assessment - Radio Button - Dropdown - Checkbox - Image - Checkbox - Image - Radio Button | D43: New Case
B44: Survey - Admin
A45: 1820 | B45: Survey | C45: Verify the Admin able to create survey and check its getting displayed with respective tabs like Draft,Published and Unbilished tabs
A46: 1821 | B46: Survey | C46: Verify the admin able to create survey with question creation on the fly
A47: 1822 | B47: Survey | C47: Verify whether the Save Draft button gets enabled after entering the title | D47: New Case
A48: 1823 | B48: Survey | C48: Verify that the Custom Admin user has the ability to publish and unpublish the Survey . | D48: Ticket
A49: 1824 | B49: Survey | C49: Verify the admin able to create survey and try to add using import question
A50: 1825 | B50: Survey | C50: Verify the admin able to create survey with question creation with sections
A51: 1826 | B51: Survey | C51: Verify the admin able to create survey with question creation on the fly,check created questions are displayed in questions listing page
A52: 1827 | B52: Survey | C52: Verify the admin able to view the associated trainings will be displayed in listing page(survey will be associated with Course/Training Plan)
A53: 1828 | B53: Survey | C53: Verify the admin will not allow to delete the questions which is associated with survey
A54: 1829 | B54: Survey | C54: Verify the admin will not allow to delete the survey which is associated with training | D54: Ticket
A55: 1830 | B55: Survey | C55: Verify the admin able to clone the survey
A56: 1831 | B56: Survey | C56: Verify the admin able to clone the sections of the survey
A57: 1832 | B57: Survey | C57: Verify the admin able to delet the drafted and unpublished survey
A58: 1833 | B58: Survey | C58: Verify and edit the survey after update
A59: 1834 | B59: Survey | C59: Verify the re-order in the survey
A60: 1835 | B60: Survey | C60: Verify the search,filters ,delete functionalitys
A61: 1836 | B61: Survey | C61: Verify all types question can be created under the survey
A62: 1838 | B62: Survey | C62: Verify that the Questions are imported correctly after clicking on Import Questions | D62: Ticket
A63: 1839 | B63: Survey | C63: Verify all types question can be created in the survey questions listing page
A64: 1840 | B64: Survey | C64: Verify the admin will not allow to publish the survey without questions
A65: 1841 | B65: Survey | C65: Verify the Created survey will be displayed for course and TP edit page
A66: 1842 | B66: Survey | C66: Verify whether the Export functionality is working correctly | D66: New Case
A67: 1843 | B67: Survey | C67: Veify and check the code convention enabled the survey auto code will be generate
A68: 1844 | B68: Survey | C68: Veify and check the code convention disabled should allow to enter the code in the survey
A69: 1845 | B69: Survey | C69: Verify and check the voice search functionality
A70: 1846 | B70: Survey | C70: Verify and check for the warning messages to create a survey without mandatory fields
A71: 1847 | B71: Survey | C71: Verify that should not able to create a survey without selecting the domain
A72: 1848 | B72: Survey | C72: Verify and check the search by keywords the respective survey should be getting listed
A73: 1849 | B73: Survey | C73: Verify whether all the fields are getting retained after cloning the Survey | D73: Ticket
A74: 1850 | B74: Survey | C74: Verify whether the change log is captured correctly for all Creation and Updation actions | D74: New Case
A75: 1851 | B75: Survey | C75: Verify whether we can able to create a question of the following types Radio button Dropdown Checkbox Grid Radio Button Grid Checkbox Short Answer Paragraph Like/Dislike Overall Rating | D75: New Case
A77: Colloboration Hub
B78: Colloboration Hub | C78: Verify and check the collabhub in learner site
B79: Colloboration Hub | C79: Verify and check the recommendation tab in Items need attention
B80: Colloboration Hub | C80: Verify and check the Recommendations tab will list the training that is recommended by the Manages for the learner
B81: Colloboration Hub | C81: Verify and check the Manage recommended course in user login
B82: Colloboration Hub | C82: Verify and check In the recommendation, the list of recommendation will be separated by 3 sections. 1. Based on Similar Profile 2. Based on your Profile 3. Manage Recommended
B83: Colloboration Hub | C83: Verify that Collaboration Hub is visible only for the user having Manager Role
B84: Colloboration Hub | C84: Verify and check the able to recommended course by Manager
B85: Colloboration Hub | C85: Verify and check the recommendation tab navigation
B86: Colloboration Hub | C86: Verify and check the course recommended by the Manage should display in catalog recommendation tab
B87: Colloboration Hub | C87: Verify and check created Manager user able to login in learner
B88: Colloboration Hub | C88: Verify and check the assigned user to the Manager able to display in my team section
B89: Colloboration Hub | C89: Verify whether the reason for Cancellation acts as a Mandatory field when we cancel any course from
B90: Colloboration Hub | C90: Verify and check the filter by report,location and jobrole
B91: Colloboration Hub | C91: Verify Approved, Rejected and Pending Filters are working correctly | D91: New Case
B92: Colloboration Hub | C92: Verify whether the Date Filter is working correctly | D92: New Case
B93: Colloboration Hub | C93: Verify whether the Sort is working correctly | D93: New Case
B94: Colloboration Hub | C94: Verify and check the Manage recommended course which is enrolled by user can disply in view learning
B95: Colloboration Hub | C95: Verify and check the created direct Manage reportee should display properly
B96: Colloboration Hub | C96: Verify and check the created virtual Manage reportee should display properly
B97: Colloboration Hub | C97: Verify and check the course can recommended to the entire team
B98: Colloboration Hub | C98: Verify and check the course can recommended to the selected team members.
B99: Colloboration Hub | C99: Verify and check Manage able to approve the course to the requested user
B100: Colloboration Hub | C100: Verify and check after Manage approval the confirmation popup will be open.
B101: Colloboration Hub | C101: Verify and check Manage able to reject the course to the requested user
...

Sheet Anu
A1: CONTENT
B2: Verify whether admin is able to access content from menu toggle - Learning>>Content and from quick access also
B3: Verify whether content listing page is displayed on clicking edit content option from quick access
B4: Verify whether create content screen is displayed on clicking create content button
B5: Verify whether able to give content title with varchar and special chars
B6: Verify whether content title is auto-populated when the file is attached and the title field is kept blank
B7: Verify whether able to create a content with all the content types - AICC - TINCAN - Scorm (scrom 2004, scorm1.2, multi-scorm, scorm from cloud, pink-elephant) - url (YouTube, Vimeo, Hosted mp4, or Brightcove, AICC, SCORM 2004, SCORM 1.2) - pdf - ppt (PPS, PPSX, PPT, PPTX) - Doc (DOC, DOCX, TXT) - Excel (XLS, XLSX) - audio (MP3 extension, ACC, WAV, M4A) - Image (JPEG, JPG, PNG) - video (MP4 extension, WEBM, MOV, WMV)
B8: Verify whether alert message is displayed when invalid url and unsupported file is uploaded
B9: Verify whether title is retained when uploaded file/url is deleted during content creation
B10: Verify whether able to upload a file with size upto 4GB instantly
B11: Verify whether alert message is displayed when a file with more than 4GB is uploaded
B12: Verify whether the content type is auto-populated based on the file attached
B13: Verify whether the content type is retained when an existing file is deleted and re-uploaded
... B84: Verify whether the content created in tenant A is not displayed in tenant B (Both admin & learner side) Also verify whether its not displayed in create course page - content library listing Example: If admin from tenant A creates a content, that content should not be displayed for the users tenant B
A86: HEADER SECTION
B87: Verify whether list of domains are displayed when door icon is clicked from the header
B88: Verify whether the domains are clickable and the learner is navigated to the respected domain when its clicked
B89: Verify whether user previleges(Collaboration Hub, Admin, Instructor, Reports) are displayed in admin icon based on the user role
B90: Verify whether user is navigated to Collaboration hub page when collaboration hub option is clicked from admin options - (Should display only when the user has manager role)
B91: Verify whether user is navigated to Admin page when admin option is clicked from admin options - (Should display only when the user has admin role)
B92: Verify whether user is navigated to Instructor page when instructor option is clicked from admin options - (Should display only when the user has instructor role)
B93: Verify whether user is navigated to Reports page when reports option is clicked from admin options - (Should display only when the user has reports admin role)
B94: Verify whether the page scrolls to My Learning section when My Learning is clicked from the header section
B95: Verify whether the page scrolls to My Dashboard section when My Dashboard is clicked from the header section
B96: Verify whether the page scrolls to My Profile sectionwhen My Profile is clicked from the header section
B97: Verify whether the page scrolls to Catalog section when Catalog is clicked from the header section
B98: Verfiy whether Alerts push-box is opened when alert icon is clicked from header section
... B154: Verify whether the user get signed-out when Sign-Out icon is clicked from the header section
A156: ANNOUNCEMENT
B157: Verify whether Announcement listing page is displayed when Announcement is clicked from menu toggle - Communication>>Announcement | C157: duplicating - make it in single row
B158: Verify whether by default Published tab is displayed when navigating to annoucnement listing page
B159: Verify whether create announcement screen is displayed on clicking create announcement button | C159: correct spelling mistakes
B160: Verify whether the Announcement Title field accept 100 characters and check title field character limits
B161: Verify whether the Announcement field accept 5000 characters and check announcement field character limits
B162: Verify whether the announcement will have the below listed items . -Bold -Italic -underlined -Bulleted list -Numbered list -image upload -H1 & H2 to highlight the headings
B163: Verify whether discard and save draft buttons are enabled when title is given
B164: Verify whether discard, save draft and publish buttons are enabled only when all the mandatory fields are given
B165: Verify whether able to select and unselect the domains from the domain drop-down
B166: Verify whether Low and High options are displayed and selectable in Priority drop-down
B167: Verify whether Calender push-box is displayed when Display From and Display To fields
B168: Verify whether past dates are disabled and unselectable in the calendar
B169: Verify whether the selected date is displayed in MM/DD/YYYY format in the Display From and Display To fields
B170: Verify the Announcement Title field will display the "Title is required" soft warning when click on save Draft or Publish without entering the Title
B171: Verify the Announcement field will display the "Announcement is required" soft warning when click on save Draft or Publish without entering the Announcement
... B178: Verify the search, filter, sort and export options in announcement listing page
B179: Verify edit icons in the saved draft,published and unpublished tab in annoucement listing page | C179: add delete in below row
B180: Verify whether the page navigated to edit announcement page when title is clicked from Saved Drafts tab in Announcement listing page
B181: Verify whether the page is navigated to listing page when discard button is clicked from the edit announcement page
B182: Verify whether "Are you sure you want to delete the announcement “#announcement title#”?" is displayed with cancel and remove buttons when delete option is clicked from Saved draft/Unpublished tab
B183: Verify whether the annoucement is removed from the saved draft and unpublished tab and the count is updated when remove button is clicked from the delete announcement light box
B184: Verify whether edit announcement page is opened and a copy of annoucement is created when clone icon is clicked from saved draft,published and unpublished tab
B185: Verify whether the Saved Draft announcement are listed under Saved draft tab and verify the count
B186: Verify whether the Published announcement are listed under published tab and verify the count
B187: Verify whether the Unpublished announcement are listed under unpublished tab and verify the count
B188: Verify whether able to unpublish the announcement from published tab
B189: Verify whether able to publish the announcement from unpublished tab
B190: Verify the records are populated when click loadmore
B191: Verfiy whether the published announcement is displayed for the respective learners based on the admin group and learner group access in learner page announcements | C191: add removing the grp access for announcement
B192: Verfiy whether the published announcement is removed in the learner page for the respective learners when the admin group and learner group access in removed for the learner
B193: Verify whether the announcement is not visible for learner if learner logged and checked Announcement before the display from date Example: Display From date as (09/15/2022),user logged in (09/08/2022)
B194: Verify whether the announcement is visible for learner if learner logged and checked Announcement on display from date Example: Display From date as (09/15/2022),user logged in (09/15/2022)
B195: Verify whether the published announcement is displayed in the learner page header all the time when display from and display to is not set
B196: Verify whether the annoucement is moved to unpublished tab when crossed the "Display TO" date (cron job)
B197: Verify whether the announcement is not visible for learner when crossed the "Display TO" date after the above cron is run and the announcement is moved to unpublished status
B198: Verify whether the High Priority type is displayed in learner announcement when priority is given as High during announcement creation
B199: Verify whether the annoncement created in portal A is not displayed in portal B (Both admin & learner side) Example: If admin from portal A creates an announcement, that announcement should not be displayed for the users in poratal B unless that user have access to that portal
B200: Verify whether the announcement created in tenant A is not displayed in tenant B (Both admin & learner side) Example: If admin from tenant A creates an announcement, that announcement should not be displayed for the users tenant B
B201: Verify whether the announcement is displayed for the learner based on day-light time zone
B202: Verify whether the announcement is displayed for the user with different time zone(check two or three time zones)
B203: Verify whether the Cloned announcement is displayed for the learner
... B208: Verify the filter, sort and export options in change log
A210: COMPLETION CERTIFICATE
B211: Verify whether admin is able to access Announcement from menu toggle - Learning>>Completion Certificate and from quick access
B212: Verify whether Completion Certificate listing page is displayed when Completion Certificate is clicked from menu toggle - Learning>>Completion Certificate
B213: Verify whether Completion Certificate listing page is displayed on clicking edit Completion Certificate option from quick access
B214: Verify whether by default Published tab is displayed when navigating to Completion Certificate listing page
B215: Verify whether create Completion Certificate screen is displayed on clicking create Completion Certificate button
B216: Verify whether discard and save draft buttons are enabled when title is given
B217: Verify whether discard, save draft and publish buttons are enabled only when all the mandatory fields are given
B218: Verify whether the page is navigated to listing page when discard button is clicked from the edit completion certificate page
B219: Verify whether able to select and unselect the domains from the domain drop-down
B220: Verify whether able to select certificate template
B221: Verify whether Modify Access light box is displayed with a message "This Program will be assigned to 'All Learners' group and the admin groups that you're part of. Please validate your decision." when Save draft/Publish button is clicked along with "No,Modify the Access" and "Yes,Proceed" buttons
B222: Verify whether the Completion Certificate is saved as draft/published with the default access when "Yes,Proceed" button is clicked
... B249: Verfiy whether the Change log is closed when - icon is clicked
A251: CUSTOM FIELD
B252: Verify whether admin is able to access Custom Field from toggle menu - MetaData Library>>Custom Field and from quick access
B253: Verify whether Custom Field listing page is displayed when Custom Field is clicked from menu toggle - MetaData Library>>Custom Field
B254: Verify whether Custom Field listing page is displayed on clicking edit Custom Field option from quick access
B255: Verify whether by default Enabled tab is displayed when navigating to custom field listing page
B256: Verify whether create custom field screen is displayed on clicking create custom field button
B257: Verify whether the radio buttons are selectable for the below options -Check Box -Drop Down -Radio Button -Text Are -Text Box -Date Picker
B258: Verify whether the discard and save draft buttons are enabled when field name is given
B259: Verify whether the discard, save draft and enable buttons are enabled only when option fields are given
B260: Verify whether if Admin clicks on Save Draft or Enable without adding the option field, a alert message is displayed as “Options are required”
B261: Verify whether if Admin clicks on Save Draft or Enable without adding the field name, a alert message is displayed as “Field Name is required”
B262: Verify whether if Admin clicks on Save Draft or Enable without adding the Show in Entity field, a alert message is displayed as “Selecting the Show in Entities is required”
B263: Verify whether if Admin clicks on Save Draft or Enable without adding the Field Length, a alert message is displayed as “Field Length is required”
... B332: To verify that the Custom Field created in one tenant is not reflected in another tenant For eg : Custom field created in ABB tenant should not be displayed in Hitachi tenant
A334: SINGLE REGISTRATION
...

Sheet Priya
A2: BANNER
B3: Verify and check able to create the banner and created banner can view in Learner UI as anonymous user | C3: New Case
B4: Verify and check able to create the banner and created banner can view in Learner UI as authenticated user | C4: New Case
B5: Verify and check able to create the banner with display from option, the learner can view the banner based on mentioned from date | C5: New Case
B6: Verify and check able to create the banner with display to option,the learner can view the banner until the to date | C6: New Case
B7: Verify and check able to create the banner with display from option,the learner cannot view the banner before the mentioned date | C7: New Case
B8: Verify and check able to create the banner with display to option,the learner cannot view the banner if the date exceeds | C8: New Case
B9: Verify and check able to create the banner with sequence,the learner can view the banner based on sequence order | C9: New Case
B10: Verify and check able to create the video banner,the learner can view the banner as video | C10: New Case
B11: Verify and check able to create the image banner with supported files jpg, jpeg, Png,the learner can view the banner as uploaded files | C11: New Case
B12: Verify and check able to create the banner with Display From date calendar should show only the Present and Future dates | C12: New Case
B13: Verify and check By default, the previous dates will be disabled in the calendar for selection. | C13: New Case
B14: Verify and check Once the banner end date (Display To date) is over, the banner will be moved to the unpublished tab | C14: New Case
... B65: Verify and check the banner Supported File Formats: jpg, jpeg, png, gif | C65: New Case
A66: PM | B66: Verify and check invalid URL the following message needs to be displayed. | C66: New Case
A67: PM | B67: Verify and check the warning message needs to be throw if uploaded unsupported file formats | C67: New Case
A69: ORGANIZATION | B69: Verify able to create and edit the organization from toggle menu bar and quick access | C69: New Case
B70: Verify and check the newly created Organization will be accessible to all the admin groups by default | C70: New Case
B71: Verify able to create, Edit and Delete an organization
B72: Verify and check after created the organization the following success message need to be displayed " Title of the organization” has been Created Successfully". | C72: New Case
B73: Verify unable to create the organization with same name the following message needs to be displayed "Name already Exists”. | C73: New Case
B74: -Verify able to create an organization type as Internal -Ensure In user creation page after setting the organization the organization type need to change as Internal
B75: - To Verify able to create an organization type as External - In user creation page after setting the organization the organization type need to change as External
B76: To Verify the created organizations are listing in various domains
B77: To Verify the created organizations are listing in other domains which is not having access
B78: To Verify the created organizations are not listing in other Tenants
B79: To Verify the created organizations will be displayed in user creation page and group creation. | C79: New Case
B80: - To Verify that able to add a parent organization (Test org) - The created organization should associated as a child to (Test org)
B81: To Verify and check when the code convention is off ,should allow to enter the code manually | C81: New Case
B82: To Verify and check when the code convention is off , if entered the existing code the following error message should be thrown "Code already Exists". | C82: New Case
B83: To Verify and check able to create the same code in multi tenant scenario. | C83: New Case
B84: To Verify and check if the code convention is turned ON the code will be auto generated | C84: New Case
B85: To Verify and check in parent organization field type 3 letters all the organization will be listed as ascending order | C85: New Case
B86: To Verify and check the he child organization action icon and active user action will be disabled in creation page | C86: New Case
B87: To Verify admin can delete the child organization without active users
B88: To Verify admin cannot delete the child organization with active users
B89: To Verify and check after deleting the organization the following message needs to be displayed "Name of the organization” has been deleted Successfully". | C89: New Case
B90: To Verify and check after suspended the organization the following message needs to be displayed "Name of the organization” has been suspended Successfully". | C90: New Case
B91: To Verify and check after activated the organization the following message needs to be displayed "Name of the organization” has been activated Successfully". | C91: New Case
B92: To Verify and check after created the organization the following 3 buttons should be dispalyed 1) Create New organization -By clicking the create new organization should navigate to the organization creation page. 2) Edit organization- By clicking the edit organization should navigate to the edit organization page. 3) Go to Listing-By clicking the listing should navigate to the organization listing page. | C92: New Case
B93: To Verify and check after deleting the organization the following 2 buttons only will be getting displayed -Create New organization -GoTo Listing | C93: New Case
B94: To Verify admin can delete the Parent organization without having active users
B95: To Verify admin cannot delete the Parent organization while having active users
B96: To Verify admin cannot delete the Parent organization while having child organizations
B97: To Verify the delete icon is available for the who has edit permission
B98: To Verify the delete icon is available when there are no users, groups and child organizations
B99: To Verify in learner page organization name is showing on the Header section of a learner profile
B100: To Verify in learner page organization can be updated on the my profile preferences tab
B101: To Verify able to create an organization by entering the cost center value
B102: To Verify the added cost center value should be shown in Manage approval request pop up box
B103: To Verify that access and custom field is only for Mid and Complex edition
B104: To Verify the newly created organization should have access group based on the portal by default
B105: To Verify that admin can able to export the child organizations
... B116: To Verify that discard button should not be enabled in edit page untill the admin edits it
B117: To Verify that save button will be enabled only if all the mandatory fields are filled. | C117: New case
B118: "-To Verify after clicking save the access pop up box should get opened with the message -This organization will be assigned to 'All Learners' group and the admin groups that you're part of. Please validate your decision. - And Yes, proceed and No, modify the access buttons should be listed in the pop up box"
B119: To verify and check the admin group will be sorted as alphabetical order | C119: New case
B120: To verify and check able to select the groups in access or remove by clicking on x icon. | C120: New case
B121: To verify and check if custom field is mandatory the following warning should be display "(Field Name) is required". | C121: New case
B122: To verify and check max 3 custom fields will be visible in a single row. | C122: New case
B123: To verify and check while creating the organization access icon will be disabled and its mandatory | C123: New case
B124: Verify and check domain based learner and admin groups will be displayed in the access | C124: New case
B125: Verify and check the access action icon will get enabled only on the edit page | C125: New case
B126: Verify and check the access option will be displayed in both edit and listing page | C126: New case
B127: Verify and check while adding a new domain to the organization from the edit page based on the portal "access group" should be auto assigned to the organization | C127: New case
B128: Verify and check the tooltip message for the access,export,suspend,delete and edit icons | C128: New case
B129: Verify and check if the searched filters is not found the following message needs to be displayed "There are no results that match your current filters. Try removing some of them to get better results". | C129: New case
B130: Verify and check filter by portal and with organization is selected as active ,only the active organization based on the portal will be getting displayed. | C130: New case
B131: To Verify that clearing the field should disable the discard and update button
B132: To Verifty that list view should show the recently updated on top
B133: -To verify whether organization which is listing in other domains which does not have access -Organization which has domain1 access and should not list in user creation page of domain2
B134: -While setting a parent Org, verify whether the parent orgs are listing from other domains
B135: -To verify whether parent organization is listing from other Tenants
B136: Verify and check the change log values after made some update,delete and access add or remove records will be displaying properly | C136: New case
B137: Verify and check the change log has the Filter, Sort, and export options | C137: New case
B138: Verify and check the change log load more button will be displayed for morethan 10 records | C138: New case
B139: Verify and check the change log load more button should not display for the less tahn or equal to 10 records | C139: New case
B140: Verify and check the change log the following fields should be record "What Changed Field Name Old value New Value Changes By Changes Date". | C140: New case
B141: Verify and check the custom admin role based organization | C141: New case
B142: Verify and check the active users count should be displayed in the listing page | C142: Ticket
B143: Verify and check the active button visible only for the suspended organization | C143: New case
B144: Verify and check the will be visible in only two places (edit and user listing page) | C144: New case
B145: Verify and check the filters by organization type,Domain name and organization status(active and suspended) | C145: New case
B146: Verify and check search by minimum of 3 letters the list of organization will be sorted in ascending order | C146: New case
B147: Verify and check the sort by A-Z,Z-A,New -Old,Old-New and By default, the list is sorted on Last updated | C147: New case
... B156: Verify and check the organization should allow the 200 characters in description | C156: Ticket
A157: USER
B158: Verify that able to create a user with all the fields
B159: Verify that able to create a user with instructor role alone
B160: Verify that able to create a user with Manager role alone
B161: Verity that able to create a user with Instructor and Manager role
B162: Verify that should not able to create a user with no domain
B163: Verify that able to login as a created user in Learner side
B164: Verify that you should not be able to assign a suspended user as a Managerr.
B165: Verify that you should not be able to assign a suspended user as a Instructor.
B166: Verify that able to login as a created user in Admin side
B167: Verify that should not able to create same user in different domain
B168: Verify that able to login in different domain where the user is having access
B169: Verify that able to create a same user in another Tenant
... B199: Verify that clearing the field should disable the discard and update button
...

Sheet Sheet9
A1: Modules | B1: Submodules
A2: Learning | B2: Course
B3: Certification
B4: Learning Path
B5: Location
B6: Content
B7: Learning Assignment
A9: Enrollments | B9: Enroll
B10: View/Update Status - Course/TP
B11: View Status/Enroll learner to TP Courses
B12: View/Update Status - Learner
B13: Create order
B14: Bulk Upload
B15: Transfer Enrollment - Course
B16: Transfer Enrollment - Training Plan
A18: People | B18: User
B19: Organization
B20: Admin Role
B21: Admin Group
B22: Learner Group
A24: Instructor
A26: Survey | B26: Survey
B27: Questions
A29: Assessment | B29: Assessment
B30: Questions
A32: Communication | B32: Banner
B33: Announcement
B34: Notification
A36: Reports | B36: Reports Dashboard
B37: Reports
A39: Commerce | B39: Order
B40: Discount
B41: Tax
A43: Site Admin | B43: Site Settings
B44: Admin Branding
B45: Admin Configuratin
B46: Learner Branding
B47: Learner Configuration
B48: Learner Page Builder
A50: Meta Data Library | B50: Learning
B51: People
B52: Ecommerce
B53: General
B54: Custom Field
B56: Tenant
B57: Portal
B58: Collabortation HUB

Sheet Sheet7
